Workbook
Name economist_emea_tier2: 'Master_Plan_2025_Bigquery CB do'!$D$67:$AY$88
Name economist_latam: 'Master_Plan_2025_Bigquery CB do'!$D$90:$AY$111
Name wsj_non_media: 'Master_Plan_2025_Bigquery CB do'!$D$251:$AY$259
Name economist_us: 'Master_Plan_2025_Bigquery CB do'!$D$5:$AY$23
Name nativo_nam: 'Master_Plan_2025_Bigquery CB do'!$D$261:$AY$299
Name wsj_global: 'Master_Plan_2025_Bigquery CB do'!$D$225:$AY$245
Name mobkoi_global: 'Master_Plan_2025_Bigquery CB do'!$D$382:$AY$418
Name economist_apac: 'Master_Plan_2025_Bigquery CB do'!$D$113:$AY$128
Name economist_added_value: 'Master_Plan_2025_Bigquery CB do'!$D$130:$AY$137
Name ft_apac: 'Master_Plan_2025_Bigquery CB do'!$D$191:$AY$200
Name ft_emea_tier1: 'Master_Plan_2025_Bigquery CB do'!$D$151:$AY$160
Name wsj_nam: 'Master_Plan_2025_Bigquery CB do'!$D$210:$AY$223
Name ft_emea_tier2: 'Master_Plan_2025_Bigquery CB do'!$D$164:$AY$175
Name economist_ca: 'Master_Plan_2025_Bigquery CB do'!$D$26:$AY$45
Name ft_added_value: 'Master_Plan_2025_Bigquery CB do'!$D$202:$AY$207
Name ft_latam: 'Master_Plan_2025_Bigquery CB do'!$D$180:$AY$189
Name mobkoi_nam: 'Master_Plan_2025_Bigquery CB do'!$D$342:$AY$376
Name nativo_global: 'Master_Plan_2025_Bigquery CB do'!$D$303:$AY$339
Name ft_us: 'Master_Plan_2025_Bigquery CB do'!$D$140:$AY$149
Name economist_emea_tier1: 'Master_Plan_2025_Bigquery CB do'!$D$47:$AY$65

Sheet Master Plan 2025
I4: Total Year | P4: SPEND | AB4: IMPRESSONS | AN4: CLICKS
B5: VENDOR | C5: REGION | D5: TARGETING | E5: TARGETING TYPE | F5: PLACEMENT | G5: PLACEMENT NAME | H5: PLACEMENT GROUP NAME | I5: SPEND (NET) | J5: IMPRESSIONS | K5: CPM / FLAT RATE (NET) | L5: CLICKS | M5: CTR | N5: VIEWABILITY | O5: Monthly Unique users | P5: FEBRUARY | Q5: MARCH | R5: APRIL | S5: MAY | T5: JUNE | U5: JULY | V5: AUGUST | W5: SEPTEMBER | X5: OCTOBER | Y5: NOVEMBER | Z5: DECEMBER | AA5: JANUARY | AB5: FEBRUARY | AC5: MARCH | AD5: APRIL | AE5: MAY | AF5: JUNE | AG5: JULY | AH5: AUGUST | AI5: SEPTEMBER | AJ5: OCTOBER | AK5: NOVEMBER | AL5: DECEMBER | AM5: JANUARY | AN5: FEBRUARY | AO5: MARCH | AP5: APRIL | AQ5: MAY | AR5: JUNE | AS5: JULY | AT5: AUGUST | AU5: SEPTEMBER | AV5: OCTOBER | AW5: NOVEMBER | AX5: DECEMBER | AY5: JANUARY
B6: THE ECONOMIST | C6: ='Economist OLD'!B6 -> North America 0 US (US Metro targetting, Canada Country targetting) | D6: ='Economist OLD'!F7 -> C0Level + Custom audience targeting companies 5,000+ | E6: Audience | F6: ResponsiveBillboard | G6: Economist_US_Audience_Display_ResponsiveBillboard | H6: Economist_US_Audience | I6: =sum(P6:AA6) -> 5799.38 | J6: =sum(AB6:AM6) -> 116744.1 | K6: ='Economist OLD'!Q7 -> 49.676 | L6: ='Economist OLD'!AW7 -> 81.720871 | M6: ='Economist OLD'!AV7 -> 0.0007 | N6: 0.75 | O6: ='Economist OLD'!AS7 -> 581400 | P6: 0 | Q6: ='Economist OLD'!V7 -> 662.01481 | R6: ='Economist OLD'!V7 -> 662.01481 | S6: ='Economist OLD'!W7 -> 662.01481 | T6: ='Economist OLD'!X7 -> 662.01481 | U6: ='Economist OLD'!Y7 -> 662.01481 | V6: ='Economist OLD'!Z7 -> 857.78411 | W6: ='Economist OLD'!AA7 -> 195.76929 | X6: ='Economist OLD'!AB7 -> 662.01481 | Y6: ='Economist OLD'!AC7 -> 526.7767 | ... AA6: ='Economist OLD'!AE7 -> 93.004102 | AB6: 0 | AC6: ='Economist OLD'!AG7 -> 13326.653 | AD6: ='Economist OLD'!AH7 -> 13326.653 | AE6: ='Economist OLD'!AI7 -> 13326.653 | AF6: ='Economist OLD'!AJ7 -> 13326.653 | AG6: ='Economist OLD'!AK7 -> 13326.653 | AH6: ='Economist OLD'!AL7 -> 17267.576 | AI6: ='Economist OLD'!AM7 -> 3940.9231 | AJ6: ='Economist OLD'!AN7 -> 13326.653 | ... AM6: ='Economist OLD'!AQ7 -> 1872.214 | AN6: 0 | AO6: =$L$6/11 -> 7.4291701 | AP6: =$L$6/11 -> 7.4291701 | AQ6: =$L$6/11 -> 7.4291701 | AR6: =$L$6/11 -> 7.4291701 | AS6: =$L$6/11 -> 7.4291701 | AT6: =$L$6/11 -> 7.4291701 | AU6: =$L$6/11 -> 7.4291701 | AV6: =$L$6/11 -> 7.4291701 | ... AY6: =$L$6/11 -> 7.4291701
D7: ='Economist OLD'!F8 -> C0Level + Custom audience targeting companies 5,000+ | E7: Audience | F7: ='Economist OLD'!I8 -> 300x600 | G7: Economist_US_Audience_Display_300x600 | H7: Economist_US_Audience | I7: ='Economist OLD'!S8+P7 -> 5682.4985 | J7: ='Economist OLD'!M8 -> 85263.085 | K7: ='Economist OLD'!Q8 -> 41.92 | L7: ='Economist OLD'!AW8 -> 42.631543 | M7: ='Economist OLD'!AV8 -> 0.0005 | N7: 0.75 | O7: ='Economist OLD'!AS8 -> 581400 | P7: 2108.27 | Q7: ='Economist OLD'!V8 -> 408.00779 | R7: =Q7 -> 408.00779 | S7: ='Economist OLD'!W8 -> 408.00779 | T7: ='Economist OLD'!X8 -> 408.00779 | U7: ='Economist OLD'!Y8 -> 408.00779 | V7: ='Economist OLD'!Z8 -> 528.66279 | W7: ='Economist OLD'!AA8 -> 120.655 | X7: ='Economist OLD'!AB8 -> 408.00779 | Y7: ='Economist OLD'!AC8 -> 324.6589 | Z7: ='Economist OLD'!AD8 -> 94.885533 | AA7: ='Economist OLD'!AE8 -> 57.319561 | AB7: 50293 | AC7: ='Economist OLD'!AG8 -> 9733.0103 | AD7: ='Economist OLD'!AH8 -> 9733.0103 | AE7: ='Economist OLD'!AI8 -> 9733.0103 | AF7: ='Economist OLD'!AJ8 -> 9733.0103 | AG7: ='Economist OLD'!AK8 -> 9733.0103 | AH7: ='Economist OLD'!AL8 -> 12611.231 | AI7: ='Economist OLD'!AM8 -> 2878.2204 | AJ7: ='Economist OLD'!AN8 -> 9733.0103 | ... AM7: ='Economist OLD'!AQ8 -> 1367.3559 | AN7: 25 | AO7: =L7/11 -> 3.8755948 | AP7: =AO7 -> 3.8755948 | AQ7: =AP7 -> 3.8755948 | AR7: =AQ7 -> 3.8755948 | AS7: =AR7 -> 3.8755948 | AT7: =AS7 -> 3.8755948 | AU7: =AT7 -> 3.8755948 | AV7: =AU7 -> 3.8755948 | AW7: =AV7 -> 3.8755948 | ... AY7: =AX7 -> 3.8755948
D8: ='Economist OLD'!F9 -> C0Level + Custom audience targeting companies 5,000+ | E8: Audience | F8: ='Economist OLD'!I9 -> Interscroller | G8: Economist_US_Audience_Display_Interscroller | H8: Economist_US_Audience | I8: ='Economist OLD'!S9+P8 -> 5518.124 | J8: ='Economist OLD'!M9 -> 93833.589 | K8: ='Economist OLD'!Q9 -> 41.92 | L8: ='Economist OLD'!AW9 -> 281.50077 | M8: ='Economist OLD'!AV9 -> 0.003 | N8: 0.75 | O8: ='Economist OLD'!AS9 -> 581400 | P8: 1584.62 | Q8: ='Economist OLD'!V9 -> 449.02006 | R8: =Q8 -> 449.02006 | S8: ='Economist OLD'!W9 -> 449.02006 | T8: ='Economist OLD'!X9 -> 449.02006 | U8: ='Economist OLD'!Y9 -> 449.02006 | V8: ='Economist OLD'!Z9 -> 581.8031 | W8: ='Economist OLD'!AA9 -> 132.78304 | X8: ='Economist OLD'!AB9 -> 449.02006 | Y8: ='Economist OLD'!AC9 -> 357.29307 | Z8: ='Economist OLD'!AD9 -> 104.42327 | AA8: ='Economist OLD'!AE9 -> 63.081228 | AB8: 37801 | AC8: ='Economist OLD'!AG9 -> 10711.356 | AD8: ='Economist OLD'!AH9 -> 10711.356 | AE8: ='Economist OLD'!AI9 -> 10711.356 | AF8: ='Economist OLD'!AJ9 -> 10711.356 | AG8: ='Economist OLD'!AK9 -> 10711.356 | AH8: ='Economist OLD'!AL9 -> 13878.891 | AI8: ='Economist OLD'!AM9 -> 3167.5344 | AJ8: ='Economist OLD'!AN9 -> 10711.356 | ... AM8: ='Economist OLD'!AQ9 -> 1504.8003 | AN8: 113 | AO8: =L8/11 -> 25.590979 | AP8: =AO8 -> 25.590979 | AQ8: =AP8 -> 25.590979 | AR8: =AQ8 -> 25.590979 | AS8: =AR8 -> 25.590979 | AT8: =AS8 -> 25.590979 | AU8: =AT8 -> 25.590979 | AV8: =AU8 -> 25.590979 | AW8: =AV8 -> 25.590979 | ... AY8: =AX8 -> 25.590979
D9: ='Economist OLD'!F10 -> C0Level + ESG articles and content | E9: Audience+Contextual | F9: ResponsiveBillboard | G9: Economist_US_Audience+Contextual_Display_ResponsiveBillboard | H9: Economist_US_Audience+Contextual | I9: ='Economist OLD'!S10+P9 -> 3656.25 | J9: ='Economist OLD'!M10 -> 82440.812 | K9: ='Economist OLD'!Q10 -> 44.35 | L9: ='Economist OLD'!AW10 -> 57.708568 | M9: ='Economist OLD'!AV10 -> 0.0007 | N9: 0.75 | O9: ='Economist OLD'!AS10 -> 4175000 | P9: 0 | Q9: ='Economist OLD'!V10 -> 417.37076 | R9: =Q9 -> 417.37076 | S9: ='Economist OLD'!W10 -> 417.37076 | T9: ='Economist OLD'!X10 -> 417.37076 | U9: ='Economist OLD'!Y10 -> 417.37076 | V9: ='Economist OLD'!Z10 -> 540.79456 | W9: ='Economist OLD'!AA10 -> 123.42379 | X9: ='Economist OLD'!AB10 -> 417.37076 | Y9: ='Economist OLD'!AC10 -> 332.10918 | Z9: ='Economist OLD'!AD10 -> 97.062968 | AA9: ='Economist OLD'!AE10 -> 58.634931 | AB9: 0 | AC9: ='Economist OLD'!AG10 -> 9410.8402 | AD9: ='Economist OLD'!AH10 -> 9410.8402 | AE9: ='Economist OLD'!AI10 -> 9410.8402 | AF9: ='Economist OLD'!AJ10 -> 9410.8402 | AG9: ='Economist OLD'!AK10 -> 9410.8402 | AH9: ='Economist OLD'!AL10 -> 12193.789 | AI9: ='Economist OLD'!AM10 -> 2782.9491 | AJ9: ='Economist OLD'!AN10 -> 9410.8402 | ... AM9: ='Economist OLD'!AQ10 -> 1322.0954 | AN9: 0 | AO9: =L9/11 -> 5.2462335 | AP9: =AO9 -> 5.2462335 | AQ9: =AP9 -> 5.2462335 | AR9: =AQ9 -> 5.2462335 | AS9: =AR9 -> 5.2462335 | AT9: =AS9 -> 5.2462335 | AU9: =AT9 -> 5.2462335 | AV9: =AU9 -> 5.2462335 | AW9: =AV9 -> 5.2462335 | ... AY9: =AX9 -> 5.2462335
D10: ='Economist OLD'!F11 -> C0Level + ESG articles and content | E10: Audience+Contextual | F10: ='Economist OLD'!I11 -> 300x600 | G10: Economist_US_Audience+Contextual_Display_300x600 | H10: Economist_US_Audience+Contextual | I10: ='Economist OLD'!S11+P10 -> 2549.999 | J10: ='Economist OLD'!M11 -> 47754.062 | K10: ='Economist OLD'!Q11 -> 37.9 | L10: ='Economist OLD'!AW11 -> 23.877031 | M10: ='Economist OLD'!AV11 -> 0.0005 | N10: 0.75 | O10: ='Economist OLD'!AS11 -> 4175000 | P10: 740.12 | Q10: ='Economist OLD'!V11 -> 206.60255 | R10: =Q10 -> 206.60255 | S10: ='Economist OLD'!W11 -> 206.60255 | T10: ='Economist OLD'!X11 -> 206.60255 | U10: ='Economist OLD'!Y11 -> 206.60255 | V10: ='Economist OLD'!Z11 -> 267.69851 | W10: ='Economist OLD'!AA11 -> 61.095966 | X10: ='Economist OLD'!AB11 -> 206.60255 | Y10: ='Economist OLD'!AC11 -> 164.39724 | Z10: ='Economist OLD'!AD11 -> 48.047104 | AA10: ='Economist OLD'!AE11 -> 29.024856 | AB10: 19528 | AC10: ='Economist OLD'!AG11 -> 5451.2545 | AD10: ='Economist OLD'!AH11 -> 5451.2545 | AE10: ='Economist OLD'!AI11 -> 5451.2545 | AF10: ='Economist OLD'!AJ11 -> 5451.2545 | AG10: ='Economist OLD'!AK11 -> 5451.2545 | AH10: ='Economist OLD'!AL11 -> 7063.2853 | AI10: ='Economist OLD'!AM11 -> 1612.0308 | AJ10: ='Economist OLD'!AN11 -> 5451.2545 | ... AM10: ='Economist OLD'!AQ11 -> 765.82732 | AN10: 10 | AO10: =L10/11 -> 2.1706392 | AP10: =AO10 -> 2.1706392 | AQ10: =AP10 -> 2.1706392 | AR10: =AQ10 -> 2.1706392 | AS10: =AR10 -> 2.1706392 | AT10: =AS10 -> 2.1706392 | AU10: =AT10 -> 2.1706392 | AV10: =AU10 -> 2.1706392 | AW10: =AV10 -> 2.1706392 | ... AY10: =AX10 -> 2.1706392
D11: ='Economist OLD'!F12 -> C0Level + ESG articles and content | E11: Audience+Contextual | F11: ='Economist OLD'!I12 -> Interscroller | G11: Economist_US_Audience+Contextual_Display_Interscroller | H11: Economist_US_Audience+Contextual | I11: ='Economist OLD'!S12+P11 -> 3656.2558 | J11: ='Economist OLD'!M12 -> 82417.567 | K11: ='Economist OLD'!Q12 -> 37.9 | L11: ='Economist OLD'!AW12 -> 247.2527 | M11: ='Economist OLD'!AV12 -> 0.003 | N11: 0.75 | O11: ='Economist OLD'!AS12 -> 4175000 | P11: 532.63 | Q11: ='Economist OLD'!V12 -> 356.57028 | R11: =Q11 -> 356.57028 | S11: ='Economist OLD'!W12 -> 356.57028 | T11: ='Economist OLD'!X12 -> 356.57028 | U11: ='Economist OLD'!Y12 -> 356.57028 | V11: ='Economist OLD'!Z12 -> 462.01431 | W11: ='Economist OLD'!AA12 -> 105.44403 | X11: ='Economist OLD'!AB12 -> 356.57028 | Y11: ='Economist OLD'!AC12 -> 283.72917 | Z11: ='Economist OLD'!AD12 -> 82.923321 | AA11: ='Economist OLD'!AE12 -> 50.093288 | AB11: 14054 | AC11: ='Economist OLD'!AG12 -> 9408.1868 | AD11: ='Economist OLD'!AH12 -> 9408.1868 | AE11: ='Economist OLD'!AI12 -> 9408.1868 | AF11: ='Economist OLD'!AJ12 -> 9408.1868 | AG11: ='Economist OLD'!AK12 -> 9408.1868 | AH11: ='Economist OLD'!AL12 -> 12190.351 | AI11: ='Economist OLD'!AM12 -> 2782.1645 | AJ11: ='Economist OLD'!AN12 -> 9408.1868 | ... AM11: ='Economist OLD'!AQ12 -> 1321.7226 | AN11: 42 | AO11: =L11/11 -> 22.477518 | AP11: =AO11 -> 22.477518 | AQ11: =AP11 -> 22.477518 | AR11: =AQ11 -> 22.477518 | AS11: =AR11 -> 22.477518 | AT11: =AS11 -> 22.477518 | AU11: =AT11 -> 22.477518 | AV11: =AU11 -> 22.477518 | AW11: =AV11 -> 22.477518 | ... AY11: =AX11 -> 22.477518
D12: ='Economist OLD'!F13 -> Economist Subscribers | E12: Subscribers | F12: ResponsiveBillboard | G12: Economist_US_Subscribers_Display_ResponsiveBillboard | H12: Economist_US_Audience+Contextual | I12: ='Economist OLD'!S13+P12 -> 12799.372 | J12: ='Economist OLD'!M13 -> 257657.06 | K12: ='Economist OLD'!Q13 -> 49.676 | L12: ='Economist OLD'!AW13 -> 180.35994 | M12: ='Economist OLD'!AV13 -> 0.0007 | N12: 0.75 | O12: ='Economist OLD'!AS13 -> 456000 | P12: 0 | Q12: ='Economist OLD'!V13 -> 1461.0827 | R12: =Q12 -> 1461.0827 | S12: ='Economist OLD'!W13 -> 1461.0827 | T12: ='Economist OLD'!X13 -> 1461.0827 | U12: ='Economist OLD'!Y13 -> 1461.0827 | V12: ='Economist OLD'!Z13 -> 1893.1503 | W12: ='Economist OLD'!AA13 -> 432.06758 | X12: ='Economist OLD'!AB13 -> 1461.0827 | Y12: ='Economist OLD'!AC13 -> 1162.6089 | Z12: ='Economist OLD'!AD13 -> 339.78668 | AA12: ='Economist OLD'!AE13 -> 205.26231 | AB12: 0 | AC12: ='Economist OLD'!AG13 -> 29412.246 | AD12: ='Economist OLD'!AH13 -> 29412.246 | AE12: ='Economist OLD'!AI13 -> 29412.246 | AF12: ='Economist OLD'!AJ13 -> 29412.246 | AG12: ='Economist OLD'!AK13 -> 29412.246 | AH12: ='Economist OLD'!AL13 -> 38109.959 | AI12: ='Economist OLD'!AM13 -> 8697.7127 | AJ12: ='Economist OLD'!AN13 -> 29412.246 | ... AM12: ='Economist OLD'!AQ13 -> 4132.0216 | AN12: 0 | AO12: =L12/11 -> 16.396358 | AP12: =AO12 -> 16.396358 | AQ12: =AP12 -> 16.396358 | AR12: =AQ12 -> 16.396358 | AS12: =AR12 -> 16.396358 | AT12: =AS12 -> 16.396358 | AU12: =AT12 -> 16.396358 | AV12: =AU12 -> 16.396358 | AW12: =AV12 -> 16.396358 | ... AY12: =AX12 -> 16.396358
D13: ='Economist OLD'!F14 -> Economist Subscribers | E13: Subscribers | F13: ='Economist OLD'!I14 -> 300x600 | G13: Economist_US_Subscribers_Display_300x600 | H13: Economist_US_Subscribers | I13: ='Economist OLD'!S14+P13 -> 13222.503 | J13: ='Economist OLD'!M14 -> 263773.94 | K13: ='Economist OLD'!Q14 -> 41.92 | L13: ='Economist OLD'!AW14 -> 131.88697 | M13: ='Economist OLD'!AV14 -> 0.0005 | N13: 0.75 | O13: ='Economist OLD'!AS14 -> 456000 | P13: 2165.1 | Q13: ='Economist OLD'!V14 -> 1262.2323 | R13: =Q13 -> 1262.2323 | S13: ='Economist OLD'!W14 -> 1262.2323 | T13: ='Economist OLD'!X14 -> 1262.2323 | U13: ='Economist OLD'!Y14 -> 1262.2323 | V13: ='Economist OLD'!Z14 -> 1635.4964 | W13: ='Economist OLD'!AA14 -> 373.26405 | X13: ='Economist OLD'!AB14 -> 1262.2323 | Y13: ='Economist OLD'!AC14 -> 1004.3802 | Z13: ='Economist OLD'!AD14 -> 293.5424 | AA13: ='Economist OLD'!AE14 -> 177.32652 | AB13: 51648 | AC13: ='Economist OLD'!AG14 -> 30110.504 | AD13: ='Economist OLD'!AH14 -> 30110.504 | AE13: ='Economist OLD'!AI14 -> 30110.504 | AF13: ='Economist OLD'!AJ14 -> 30110.504 | AG13: ='Economist OLD'!AK14 -> 30110.504 | AH13: ='Economist OLD'!AL14 -> 39014.704 | AI13: ='Economist OLD'!AM14 -> 8904.1997 | AJ13: ='Economist OLD'!AN14 -> 30110.504 | ... AM13: ='Economist OLD'!AQ14 -> 4230.1174 | AN13: 26 | AO13: =L13/11 -> 11.989724 | AP13: =AO13 -> 11.989724 | AQ13: =AP13 -> 11.989724 | AR13: =AQ13 -> 11.989724 | AS13: =AR13 -> 11.989724 | AT13: =AS13 -> 11.989724 | AU13: =AT13 -> 11.989724 | AV13: =AU13 -> 11.989724 | AW13: =AV13 -> 11.989724 | ... AY13: =AX13 -> 11.989724
D14: ='Economist OLD'!F15 -> Economist Subscribers | E14: Subscribers | F14: ='Economist OLD'!I15 -> Interscroller | G14: Economist_US_Subscribers_Display_Interscroller | H14: Economist_US_Subscribers | I14: ='Economist OLD'!S15+P14 -> 12189.38 | J14: ='Economist OLD'!M15 -> 236439.64 | K14: ='Economist OLD'!Q15 -> 41.92 | L14: ='Economist OLD'!AW15 -> 709.31893 | M14: ='Economist OLD'!AV15 -> 0.003 | N14: 0.75 | O14: ='Economist OLD'!AS15 -> 456000 | P14: 2277.83 | Q14: ='Economist OLD'!V15 -> 1131.43 | R14: =Q14 -> 1131.43 | S14: ='Economist OLD'!W15 -> 1131.43 | T14: ='Economist OLD'!X15 -> 1131.43 | U14: ='Economist OLD'!Y15 -> 1131.43 | V14: ='Economist OLD'!Z15 -> 1466.0136 | W14: ='Economist OLD'!AA15 -> 334.58354 | X14: ='Economist OLD'!AB15 -> 1131.43 | Y14: ='Economist OLD'!AC15 -> 900.29856 | Z14: ='Economist OLD'!AD15 -> 263.12327 | AA14: ='Economist OLD'!AE15 -> 158.95058 | AB14: 54337 | AC14: ='Economist OLD'!AG15 -> 26990.22 | AD14: ='Economist OLD'!AH15 -> 26990.22 | AE14: ='Economist OLD'!AI15 -> 26990.22 | AF14: ='Economist OLD'!AJ15 -> 26990.22 | AG14: ='Economist OLD'!AK15 -> 26990.22 | AH14: ='Economist OLD'!AL15 -> 34971.698 | AI14: ='Economist OLD'!AM15 -> 7981.4776 | AJ14: ='Economist OLD'!AN15 -> 26990.22 | ... AM14: ='Economist OLD'!AQ15 -> 3791.7599 | AN14: 163 | AO14: =L14/11 -> 64.483539 | AP14: =AO14 -> 64.483539 | AQ14: =AP14 -> 64.483539 | AR14: =AQ14 -> 64.483539 | AS14: =AR14 -> 64.483539 | AT14: =AS14 -> 64.483539 | AU14: =AT14 -> 64.483539 | AV14: =AU14 -> 64.483539 | AW14: =AV14 -> 64.483539 | ... AY14: =AX14 -> 64.483539
D15: ='Economist OLD'!F16 -> Economist Subscribers | E15: Subscribers | F15: ='Economist OLD'!I16 -> 300x250 | G15: Economist_US_Subscribers_Display_300x250 | H15: Economist_US_Subscribers | I15: ='Economist OLD'!S16+P15 -> 11169.538 | J15: ='Economist OLD'!M16 -> 134448.47 | K15: ='Economist OLD'!Q16 -> 60 | L15: ='Economist OLD'!AW16 -> 94.113931 | M15: ='Economist OLD'!AV16 -> 0.0007 | N15: 0.75 | O15: ='Economist OLD'!AS16 -> 445000 | P15: 3102.63 | Q15: ='Economist OLD'!V16 -> 920.85927 | R15: =Q15 -> 920.85927 | S15: ='Economist OLD'!W16 -> 920.85927 | T15: ='Economist OLD'!X16 -> 920.85927 | U15: ='Economist OLD'!Y16 -> 920.85927 | V15: ='Economist OLD'!Z16 -> 1193.1734 | W15: ='Economist OLD'!AA16 -> 272.3141 | X15: ='Economist OLD'!AB16 -> 920.85927 | Y15: ='Economist OLD'!AC16 -> 732.74374 | Z15: ='Economist OLD'!AD16 -> 214.15332 | AA15: ='Economist OLD'!AE16 -> 129.36824 | AB15: 51711 | AC15: ='Economist OLD'!AG16 -> 15347.654 | AD15: ='Economist OLD'!AH16 -> 15347.654 | AE15: ='Economist OLD'!AI16 -> 15347.654 | AF15: ='Economist OLD'!AJ16 -> 15347.654 | AG15: ='Economist OLD'!AK16 -> 15347.654 | AH15: ='Economist OLD'!AL16 -> 19886.223 | AI15: ='Economist OLD'!AM16 -> 4538.5684 | AJ15: ='Economist OLD'!AN16 -> 15347.654 | ... AM15: ='Economist OLD'!AQ16 -> 2156.1373 | AN15: 36 | AO15: =L15/11 -> 8.5558119 | AP15: =AO15 -> 8.5558119 | AQ15: =AP15 -> 8.5558119 | AR15: =AQ15 -> 8.5558119 | AS15: =AR15 -> 8.5558119 | AT15: =AS15 -> 8.5558119 | AU15: =AT15 -> 8.5558119 | AV15: =AU15 -> 8.5558119 | AW15: =AV15 -> 8.5558119 | ... AY15: =AX15 -> 8.5558119
D16: ='Economist OLD'!F17 -> Economist Subscribers | E16: Subscribers | F16: ='Economist OLD'!I17 -> App Interscroller | G16: Economist_US_Subscribers_Display_appInterscroller | H16: Economist_US_Subscribers | I16: ='Economist OLD'!S17+P16 -> 57420 | J16: ='Economist OLD'!M17 -> 574200 | K16: ='Economist OLD'!Q17 -> 100 | L16: ='Economist OLD'!AW17 -> 0 | M16: ='Economist OLD'!AV17 -> 0 | N16: 0.75 | O16: ='Economist OLD'!AS17 -> 445000 | P16: 0 | Q16: ='Economist OLD'!V17 -> 5220 | R16: =Q16 -> 5220 | S16: ='Economist OLD'!W17 -> 5220 | T16: ='Economist OLD'!X17 -> 5220 | U16: ='Economist OLD'!Y17 -> 5220 | V16: ='Economist OLD'!Z17 -> 0 | W16: ='Economist OLD'!AA17 -> 10440 | X16: ='Economist OLD'!AB17 -> 5220 | Y16: ='Economist OLD'!AC17 -> 5220 | Z16: ='Economist OLD'!AD17 -> 5220 | AA16: ='Economist OLD'!AE17 -> 5220 | AB16: 0 | AC16: ='Economist OLD'!AG17 -> 52200 | AD16: ='Economist OLD'!AH17 -> 52200 | AE16: ='Economist OLD'!AI17 -> 52200 | AF16: ='Economist OLD'!AJ17 -> 52200 | AG16: ='Economist OLD'!AK17 -> 52200 | AH16: ='Economist OLD'!AL17 -> 0 | AI16: ='Economist OLD'!AM17 -> 104400 | AJ16: ='Economist OLD'!AN17 -> 52200 | ... AM16: ='Economist OLD'!AQ17 -> 52200 | AN16: 0 | AO16: 0 | AP16: 0 | AQ16: 0 | AR16: 0 | AS16: 0 | AT16: 0 | AU16: 0 | AV16: 0 | AW16: 0 | AX16: 0 | AY16: 0
D17: ='Economist OLD'!F18 -> Science & Technology (COP) | E17: Takeover | F17: Takeover | I17: ='Economist OLD'!S18+P17 -> 1486.1949 | J17: ='Economist OLD'!M18 -> 23490 | K17: ='Economist OLD'!Q18 -> 1486.1949 | L17: ='Economist OLD'!AW18 -> 16.443 | M17: ='Economist OLD'!AV18 -> 0.0007 | N17: 0.75 | O17: ='Economist OLD'!AS18 -> 445000 | P17: 0 | Q17: ='Economist OLD'!V18 -> 0 | R17: =Q17 -> 0 | S17: ='Economist OLD'!W18 -> 0 | T17: ='Economist OLD'!X18 -> 0 | U17: ='Economist OLD'!Y18 -> 0 | V17: ='Economist OLD'!Z18 -> 0 | W17: ='Economist OLD'!AA18 -> 1486.1949 | X17: ='Economist OLD'!AB18 -> 0 | Y17: ='Economist OLD'!AC18 -> 0 | Z17: ='Economist OLD'!AD18 -> 0 | AA17: ='Economist OLD'!AE18 -> 0 | AB17: 0 | AC17: ='Economist OLD'!AG18 -> 0 | AD17: ='Economist OLD'!AH18 -> 0 | AE17: ='Economist OLD'!AI18 -> 0 | AF17: ='Economist OLD'!AJ18 -> 0 | AG17: ='Economist OLD'!AK18 -> 0 | AH17: ='Economist OLD'!AL18 -> 0 | AI17: ='Economist OLD'!AM18 -> 23490 | AJ17: ='Economist OLD'!AN18 -> 0 | ... AM17: ='Economist OLD'!AQ18 -> 0 | AN17: 0 | AO17: =L17/11 -> 1.4948182 | AP17: =AO17 -> 1.4948182 | AQ17: =AP17 -> 1.4948182 | AR17: =AQ17 -> 1.4948182 | AS17: =AR17 -> 1.4948182 | AT17: =AS17 -> 1.4948182 | AU17: =AT17 -> 1.4948182 | AV17: =AU17 -> 1.4948182 | AW17: =AV17 -> 1.4948182 | ... AY17: =AX17 -> 1.4948182
D18: ='Economist OLD'!F19 -> Science & Technology (COP) | E18: Takeover | F18: Takeover | I18: ='Economist OLD'!S19+P18 -> 1486.1949 | J18: ='Economist OLD'!M19 -> 23490 | K18: ='Economist OLD'!Q19 -> 1486.1949 | L18: ='Economist OLD'!AW19 -> 16.443 | M18: ='Economist OLD'!AV19 -> 0.0007 | N18: 0.75 | O18: ='Economist OLD'!AS19 -> 445000 | P18: 0 | Q18: ='Economist OLD'!V19 -> 0 | R18: =Q18 -> 0 | S18: ='Economist OLD'!W19 -> 0 | T18: ='Economist OLD'!X19 -> 0 | U18: ='Economist OLD'!Y19 -> 0 | V18: ='Economist OLD'!Z19 -> 0 | W18: ='Economist OLD'!AA19 -> 1486.1949 | X18: ='Economist OLD'!AB19 -> 0 | Y18: ='Economist OLD'!AC19 -> 0 | Z18: ='Economist OLD'!AD19 -> 0 | AA18: ='Economist OLD'!AE19 -> 0 | AB18: 0 | AC18: ='Economist OLD'!AG19 -> 0 | AD18: ='Economist OLD'!AH19 -> 0 | AE18: ='Economist OLD'!AI19 -> 0 | AF18: ='Economist OLD'!AJ19 -> 0 | AG18: ='Economist OLD'!AK19 -> 0 | AH18: ='Economist OLD'!AL19 -> 0 | AI18: ='Economist OLD'!AM19 -> 23490 | AJ18: ='Economist OLD'!AN19 -> 0 | ... AM18: ='Economist OLD'!AQ19 -> 0 | AN18: 0 | AO18: =L18/11 -> 1.4948182 | AP18: =AO18 -> 1.4948182 | AQ18: =AP18 -> 1.4948182 | AR18: =AQ18 -> 1.4948182 | AS18: =AR18 -> 1.4948182 | AT18: =AS18 -> 1.4948182 | AU18: =AT18 -> 1.4948182 | AV18: =AU18 -> 1.4948182 | AW18: =AV18 -> 1.4948182 | ... AY18: =AX18 -> 1.4948182
D19: ='Economist OLD'!F20 -> Science & Technology (COP) | E19: Takeover | F19: Takeover | I19: ='Economist OLD'!S20+P19 -> 1486.1949 | J19: ='Economist OLD'!M20 -> 23490 | K19: ='Economist OLD'!Q20 -> 1486.1949 | L19: ='Economist OLD'!AW20 -> 16.443 | M19: ='Economist OLD'!AV20 -> 0.0007 | N19: 0.75 | O19: ='Economist OLD'!AS20 -> 445000 | P19: 0 | Q19: ='Economist OLD'!V20 -> 0 | R19: =Q19 -> 0 | S19: ='Economist OLD'!W20 -> 0 | T19: ='Economist OLD'!X20 -> 0 | U19: ='Economist OLD'!Y20 -> 0 | V19: ='Economist OLD'!Z20 -> 0 | W19: ='Economist OLD'!AA20 -> 0 | X19: ='Economist OLD'!AB20 -> 0 | Y19: ='Economist OLD'!AC20 -> 1486.1949 | Z19: ='Economist OLD'!AD20 -> 0 | AA19: ='Economist OLD'!AE20 -> 0 | AB19: 0 | AC19: ='Economist OLD'!AG20 -> 0 | AD19: ='Economist OLD'!AH20 -> 0 | AE19: ='Economist OLD'!AI20 -> 0 | AF19: ='Economist OLD'!AJ20 -> 0 | AG19: ='Economist OLD'!AK20 -> 0 | AH19: ='Economist OLD'!AL20 -> 0 | AI19: ='Economist OLD'!AM20 -> 0 | AJ19: ='Economist OLD'!AN20 -> 0 | ... AM19: ='Economist OLD'!AQ20 -> 0 | AN19: 0 | AO19: =L19/11 -> 1.4948182 | AP19: =AO19 -> 1.4948182 | AQ19: =AP19 -> 1.4948182 | AR19: =AQ19 -> 1.4948182 | AS19: =AR19 -> 1.4948182 | AT19: =AS19 -> 1.4948182 | AU19: =AT19 -> 1.4948182 | AV19: =AU19 -> 1.4948182 | AW19: =AV19 -> 1.4948182 | ... AY19: =AX19 -> 1.4948182
D20: ='Economist OLD'!F21 -> Business & Finance (Davos) | E20: Takeover | F20: Takeover | I20: ='Economist OLD'!S21+P20 -> 6253.125 | J20: ='Economist OLD'!M21 -> 100050 | K20: ='Economist OLD'!Q21 -> 6253.125 | L20: ='Economist OLD'!AW21 -> 70.035 | M20: ='Economist OLD'!AV21 -> 0.0007 | N20: 0.75 | O20: ='Economist OLD'!AS21 -> 445000 | P20: 0 | Q20: ='Economist OLD'!V21 -> 0 | R20: =Q20 -> 0 | S20: ='Economist OLD'!W21 -> 0 | T20: ='Economist OLD'!X21 -> 0 | U20: ='Economist OLD'!Y21 -> 0 | V20: ='Economist OLD'!Z21 -> 0 | W20: ='Economist OLD'!AA21 -> 0 | X20: ='Economist OLD'!AB21 -> 0 | Y20: ='Economist OLD'!AC21 -> 0 | Z20: ='Economist OLD'!AD21 -> 0 | AA20: ='Economist OLD'!AE21 -> 6253.125 | AB20: 0 | AC20: ='Economist OLD'!AG21 -> 0 | AD20: ='Economist OLD'!AH21 -> 0 | AE20: ='Economist OLD'!AI21 -> 0 | AF20: ='Economist OLD'!AJ21 -> 0 | AG20: ='Economist OLD'!AK21 -> 0 | AH20: ='Economist OLD'!AL21 -> 0 | AI20: ='Economist OLD'!AM21 -> 0 | AJ20: ='Economist OLD'!AN21 -> 0 | ... AM20: ='Economist OLD'!AQ21 -> 100050 | AN20: 0 | AO20: =L20/11 -> 6.3668182 | AP20: =AO20 -> 6.3668182 | AQ20: =AP20 -> 6.3668182 | AR20: =AQ20 -> 6.3668182 | AS20: =AR20 -> 6.3668182 | AT20: =AS20 -> 6.3668182 | AU20: =AT20 -> 6.3668182 | AV20: =AU20 -> 6.3668182 | AW20: =AV20 -> 6.3668182 | ... AY20: =AX20 -> 6.3668182
C21: TOTAL | I21: =SUM(I6:I20) -> 144375.01 | J21: =SUM(J6:J20) -> 2145492.3 | L21: =SUM(L6:L20) -> 1969.7352
C22: ='Economist OLD'!B22 -> North America 0 CA | D22: ='Economist OLD'!F23 -> C0Level + Custom audience targeting companies 5,000+ | E22: Audience | F22: ResponsiveBillboard | G22: Economist_CA_Audience_Display_ResponsiveBillboard | H22: Economist_CA_Audience | I22: ='Economist OLD'!S23+P22 -> 3599.7917 | J22: ='Economist OLD'!M23 -> 72465.409 | K22: ='Economist OLD'!Q23 -> 49.676 | L22: ='Economist OLD'!AW23 -> 50.725786 | M22: ='Economist OLD'!AV23 -> 0.0007 | N22: 0.75 | O22: ='Economist OLD'!AS23 -> 64600 | P22: 0 | Q22: ='Economist OLD'!U23 -> 359.90097 | R22: ='Economist OLD'!V23 -> 359.90097 | S22: ='Economist OLD'!W23 -> 359.90097 | T22: ='Economist OLD'!X23 -> 359.90097 | U22: ='Economist OLD'!Y23 -> 359.90097 | V22: ='Economist OLD'!Z23 -> 359.90097 | W22: ='Economist OLD'!AA23 -> 312.56137 | X22: ='Economist OLD'!AB23 -> 359.90097 | ... AA22: ='Economist OLD'!AE23 -> 260.31093 | AB22: 0 | AC22: ='Economist OLD'!AG23 -> 7244.9667 | AD22: ='Economist OLD'!AH23 -> 7244.9667 | AE22: ='Economist OLD'!AI23 -> 7244.9667 | AF22: ='Economist OLD'!AJ23 -> 7244.9667 | AG22: ='Economist OLD'!AK23 -> 7244.9667 | AH22: ='Economist OLD'!AL23 -> 7244.9667 | AI22: ='Economist OLD'!AM23 -> 6291.9996 | AJ22: ='Economist OLD'!AN23 -> 7244.9667 | ... AM22: ='Economist OLD'!AQ23 -> 5240.175 | AN22: 0 | AO22: =L22/11 -> 4.6114351 | AP22: =AO22 -> 4.6114351 | AQ22: =AP22 -> 4.6114351 | AR22: =AQ22 -> 4.6114351 | AS22: =AR22 -> 4.6114351 | AT22: =AS22 -> 4.6114351 | AU22: =AT22 -> 4.6114351 | AV22: =AU22 -> 4.6114351 | AW22: =AV22 -> 4.6114351 | ... AY22: =AX22 -> 4.6114351
D23: ='Economist OLD'!F24 -> C0Level + Custom audience targeting companies 5,000+ | E23: Audience | F23: ='Economist OLD'!I24 -> 300x600 | G23: Economist_CA_Audience_Display_300x600 | H23: Economist_CA_Audience | I23: ='Economist OLD'!S24+P23 -> 2560.8286 | J23: ='Economist OLD'!M24 -> 55336.083 | K23: ='Economist OLD'!Q24 -> 41.92 | L23: ='Economist OLD'!AW24 -> 27.668041 | M23: ='Economist OLD'!AV24 -> 0.0005 | N23: 0.75 | O23: ='Economist OLD'!AS24 -> 64600 | P23: 241.14 | Q23: ='Economist OLD'!U24 -> 231.91847 | R23: ='Economist OLD'!V24 -> 231.91847 | S23: ='Economist OLD'!W24 -> 231.91847 | T23: ='Economist OLD'!X24 -> 231.91847 | U23: ='Economist OLD'!Y24 -> 231.91847 | V23: ='Economist OLD'!Z24 -> 231.91847 | W23: ='Economist OLD'!AA24 -> 201.41306 | X23: ='Economist OLD'!AB24 -> 231.91847 | ... AA23: ='Economist OLD'!AE24 -> 167.74312 | AB23: 5752 | AC23: ='Economist OLD'!AG24 -> 5532.4062 | AD23: ='Economist OLD'!AH24 -> 5532.4062 | AE23: ='Economist OLD'!AI24 -> 5532.4062 | AF23: ='Economist OLD'!AJ24 -> 5532.4062 | AG23: ='Economist OLD'!AK24 -> 5532.4062 | AH23: ='Economist OLD'!AL24 -> 5532.4062 | AI23: ='Economist OLD'!AM24 -> 4804.7008 | AJ23: ='Economist OLD'!AN24 -> 5532.4062 | ... AM23: ='Economist OLD'!AQ24 -> 4001.5058 | AN23: 3 | AO23: =L23/11 -> 2.5152765 | AP23: =AO23 -> 2.5152765 | AQ23: =AP23 -> 2.5152765 | AR23: =AQ23 -> 2.5152765 | AS23: =AR23 -> 2.5152765 | AT23: =AS23 -> 2.5152765 | AU23: =AT23 -> 2.5152765 | AV23: =AU23 -> 2.5152765 | AW23: =AV23 -> 2.5152765 | ... AY23: =AX23 -> 2.5152765
D24: ='Economist OLD'!F25 -> C0Level + Custom audience targeting companies 5,000+ | E24: Audience | F24: ='Economist OLD'!I25 -> Interscroller | G24: Economist_CA_Audience_Display_Interscroller | H24: Economist_CA_Audience | I24: ='Economist OLD'!S25+P24 -> 3839.3743 | J24: ='Economist OLD'!M25 -> 88303.775 | K24: ='Economist OLD'!Q25 -> 41.92 | L24: ='Economist OLD'!AW25 -> 264.91133 | M24: ='Economist OLD'!AV25 -> 0.003 | N24: 0.75 | O24: ='Economist OLD'!AS25 -> 64600 | P24: 137.68 | Q24: ='Economist OLD'!U25 -> 370.08901 | R24: ='Economist OLD'!V25 -> 370.08901 | S24: ='Economist OLD'!W25 -> 370.08901 | T24: ='Economist OLD'!X25 -> 370.08901 | U24: ='Economist OLD'!Y25 -> 370.08901 | V24: ='Economist OLD'!Z25 -> 370.08901 | W24: ='Economist OLD'!AA25 -> 321.40933 | X24: ='Economist OLD'!AB25 -> 370.08901 | ... AA24: ='Economist OLD'!AE25 -> 267.67979 | AB24: 3284 | AC24: ='Economist OLD'!AG25 -> 8828.4593 | AD24: ='Economist OLD'!AH25 -> 8828.4593 | AE24: ='Economist OLD'!AI25 -> 8828.4593 | AF24: ='Economist OLD'!AJ25 -> 8828.4593 | AG24: ='Economist OLD'!AK25 -> 8828.4593 | AH24: ='Economist OLD'!AL25 -> 8828.4593 | AI24: ='Economist OLD'!AM25 -> 7667.2074 | AJ24: ='Economist OLD'!AN25 -> 8828.4593 | ... AM24: ='Economist OLD'!AQ25 -> 6385.4913 | AN24: 10 | AO24: =L24/11 -> 24.082848 | AP24: =AO24 -> 24.082848 | AQ24: =AP24 -> 24.082848 | AR24: =AQ24 -> 24.082848 | AS24: =AR24 -> 24.082848 | AT24: =AS24 -> 24.082848 | AU24: =AT24 -> 24.082848 | AV24: =AU24 -> 24.082848 | AW24: =AV24 -> 24.082848 | ... AY24: =AX24 -> 24.082848
D25: ='Economist OLD'!F26 -> C0Level + ESG articles and content | E25: Audience+Contextual | F25: ResponsiveBillboard | G25: Economist_CA_Audience+Contextual_Display_ResponsiveBillboard | H25: Economist_CA_Audience+Contextual | I25: ='Economist OLD'!S26+P25 -> 1885.4202 | J25: ='Economist OLD'!M26 -> 42512.292 | K25: ='Economist OLD'!Q26 -> 44.35 | L25: ='Economist OLD'!AW26 -> 29.758605 | M25: ='Economist OLD'!AV26 -> 0.0007 | N25: 0.75 | O25: ='Economist OLD'!AS26 -> 402000 | P25: 0 | Q25: ='Economist OLD'!U26 -> 188.50106 | R25: ='Economist OLD'!V26 -> 188.50106 | S25: ='Economist OLD'!W26 -> 188.50106 | T25: ='Economist OLD'!X26 -> 188.50106 | U25: ='Economist OLD'!Y26 -> 188.50106 | V25: ='Economist OLD'!Z26 -> 188.50106 | W25: ='Economist OLD'!AA26 -> 163.70656 | X25: ='Economist OLD'!AB26 -> 188.50106 | ... AA25: ='Economist OLD'!AE26 -> 136.33997 | AB25: 0 | AC25: ='Economist OLD'!AG26 -> 4250.3057 | AD25: ='Economist OLD'!AH26 -> 4250.3057 | AE25: ='Economist OLD'!AI26 -> 4250.3057 | AF25: ='Economist OLD'!AJ26 -> 4250.3057 | AG25: ='Economist OLD'!AK26 -> 4250.3057 | AH25: ='Economist OLD'!AL26 -> 4250.3057 | AI25: ='Economist OLD'!AM26 -> 3691.2415 | AJ25: ='Economist OLD'!AN26 -> 4250.3057 | ... AM25: ='Economist OLD'!AQ26 -> 3074.1819 | AN25: 0 | AO25: =M25/12 -> 5.8333333e-05 | AP25: =AO25 -> 5.8333333e-05 | AQ25: =AP25 -> 5.8333333e-05 | AR25: =AQ25 -> 5.8333333e-05 | AS25: =AR25 -> 5.8333333e-05 | AT25: =AS25 -> 5.8333333e-05 | AU25: =AT25 -> 5.8333333e-05 | AV25: =AU25 -> 5.8333333e-05 | AW25: =AV25 -> 5.8333333e-05 | ... AY25: =AX25 -> 5.8333333e-05
D26: ='Economist OLD'!F27 -> C0Level + ESG articles and content | E26: Audience+Contextual | F26: ='Economist OLD'!I27 -> 300x600 | G26: Economist_CA_Audience+Contextual_Display_300x600 | H26: Economist_CA_Audience+Contextual | I26: ='Economist OLD'!S27+P26 -> 850.00357 | J26: ='Economist OLD'!M27 -> 19523.841 | K26: ='Economist OLD'!Q27 -> 37.9 | L26: ='Economist OLD'!AW27 -> 9.7619205 | M26: ='Economist OLD'!AV27 -> 0.0005 | N26: 0.75 | O26: ='Economist OLD'!AS27 -> 402000 | P26: 110.05 | Q26: ='Economist OLD'!U27 -> 73.979283 | R26: ='Economist OLD'!V27 -> 73.979283 | S26: ='Economist OLD'!W27 -> 73.979283 | T26: ='Economist OLD'!X27 -> 73.979283 | U26: ='Economist OLD'!Y27 -> 73.979283 | V26: ='Economist OLD'!Z27 -> 73.979283 | W26: ='Economist OLD'!AA27 -> 64.248414 | X26: ='Economist OLD'!AB27 -> 73.979283 | ... AA26: ='Economist OLD'!AE27 -> 53.508098 | AB26: 2904 | AC26: ='Economist OLD'!AG27 -> 1951.96 | AD26: ='Economist OLD'!AH27 -> 1951.96 | AE26: ='Economist OLD'!AI27 -> 1951.96 | AF26: ='Economist OLD'!AJ27 -> 1951.96 | AG26: ='Economist OLD'!AK27 -> 1951.96 | AH26: ='Economist OLD'!AL27 -> 1951.96 | AI26: ='Economist OLD'!AM27 -> 1695.2088 | AJ26: ='Economist OLD'!AN27 -> 1951.96 | ... AM26: ='Economist OLD'!AQ27 -> 1411.8232 | AN26: 1 | AO26: =L26/11 -> 0.88744732 | AP26: =AO26 -> 0.88744732 | AQ26: =AP26 -> 0.88744732 | AR26: =AQ26 -> 0.88744732 | AS26: =AR26 -> 0.88744732 | AT26: =AS26 -> 0.88744732 | AU26: =AT26 -> 0.88744732 | AV26: =AU26 -> 0.88744732 | AW26: =AV26 -> 0.88744732 | ... AY26: =AX26 -> 0.88744732
D27: ='Economist OLD'!F28 -> C0Level + ESG articles and content | E27: Audience+Contextual | F27: ='Economist OLD'!I28 -> Interscroller | G27: Economist_CA_Audience+Contextual_Display_Interscroller | H27: Economist_CA_Audience+Contextual | I27: ='Economist OLD'!S28+P27 -> 1885.4168 | J27: ='Economist OLD'!M28 -> 45062.713 | K27: ='Economist OLD'!Q28 -> 37.9 | L27: ='Economist OLD'!AW28 -> 135.18814 | M27: ='Economist OLD'!AV28 -> 0.003 | N27: 0.75 | O27: ='Economist OLD'!AS28 -> 402000 | P27: 177.54 | Q27: ='Economist OLD'!U28 -> 170.75058 | R27: ='Economist OLD'!V28 -> 170.75058 | S27: ='Economist OLD'!W28 -> 170.75058 | T27: ='Economist OLD'!X28 -> 170.75058 | U27: ='Economist OLD'!Y28 -> 170.75058 | V27: ='Economist OLD'!Z28 -> 170.75058 | W27: ='Economist OLD'!AA28 -> 148.29089 | X27: ='Economist OLD'!AB28 -> 170.75058 | ... AA27: ='Economist OLD'!AE28 -> 123.50132 | AB27: 4685 | AC27: ='Economist OLD'!AG28 -> 4505.2923 | AD27: ='Economist OLD'!AH28 -> 4505.2923 | AE27: ='Economist OLD'!AI28 -> 4505.2923 | AF27: ='Economist OLD'!AJ28 -> 4505.2923 | AG27: ='Economist OLD'!AK28 -> 4505.2923 | AH27: ='Economist OLD'!AL28 -> 4505.2923 | AI27: ='Economist OLD'!AM28 -> 3912.6885 | AJ27: ='Economist OLD'!AN28 -> 4505.2923 | ... AM27: ='Economist OLD'!AQ28 -> 3258.6099 | AN27: 14 | AO27: =L27/11 -> 12.289831 | AP27: =AO27 -> 12.289831 | AQ27: =AP27 -> 12.289831 | AR27: =AQ27 -> 12.289831 | AS27: =AR27 -> 12.289831 | AT27: =AS27 -> 12.289831 | AU27: =AT27 -> 12.289831 | AV27: =AU27 -> 12.289831 | AW27: =AV27 -> 12.289831 | ... AY27: =AX27 -> 12.289831
D28: ='Economist OLD'!F29 -> Economist Subscribers | E28: Subscribers | F28: ResponsiveBillboard | G28: Economist_CA_Subscribers_Display_ResponsiveBillboard | H28: Economist_CA_Subscribers | I28: ='Economist OLD'!S29+P28 -> 5976.435 | J28: ='Economist OLD'!M29 -> 120308.3 | K28: ='Economist OLD'!Q29 -> 49.676 | L28: ='Economist OLD'!AW29 -> 84.215808 | M28: ='Economist OLD'!AV29 -> 0.0007 | N28: 0.75 | O28: ='Economist OLD'!AS29 -> 48000 | P28: 0 | Q28: ='Economist OLD'!U29 -> 597.51367 | R28: ='Economist OLD'!V29 -> 597.51367 | S28: ='Economist OLD'!W29 -> 597.51367 | T28: ='Economist OLD'!X29 -> 597.51367 | U28: ='Economist OLD'!Y29 -> 597.51367 | V28: ='Economist OLD'!Z29 -> 597.51367 | W28: ='Economist OLD'!AA29 -> 518.91967 | X28: ='Economist OLD'!AB29 -> 597.51367 | ... AA28: ='Economist OLD'!AE29 -> 432.17261 | AB28: 0 | AC28: ='Economist OLD'!AG29 -> 12028.216 | AD28: ='Economist OLD'!AH29 -> 12028.216 | AE28: ='Economist OLD'!AI29 -> 12028.216 | AF28: ='Economist OLD'!AJ29 -> 12028.216 | AG28: ='Economist OLD'!AK29 -> 12028.216 | AH28: ='Economist OLD'!AL29 -> 12028.216 | AI28: ='Economist OLD'!AM29 -> 10446.084 | AJ28: ='Economist OLD'!AN29 -> 12028.216 | ... AM28: ='Economist OLD'!AQ29 -> 8699.8271 | AN28: 0 | AO28: =L28/11 -> 7.6559825 | AP28: =AO28 -> 7.6559825 | AQ28: =AP28 -> 7.6559825 | AR28: =AQ28 -> 7.6559825 | AS28: =AR28 -> 7.6559825 | AT28: =AS28 -> 7.6559825 | AU28: =AT28 -> 7.6559825 | AV28: =AU28 -> 7.6559825 | AW28: =AV28 -> 7.6559825 | ... AY28: =AX28 -> 7.6559825
D29: ='Economist OLD'!F30 -> Economist Subscribers | E29: Subscribers | F29: ='Economist OLD'!I30 -> 300x600 | G29: Economist_CA_Subscribers_Display_300x600 | H29: Economist_CA_Subscribers | I29: ='Economist OLD'!S30+P29 -> 5894.1643 | J29: ='Economist OLD'!M30 -> 122593.85 | K29: ='Economist OLD'!Q30 -> 41.92 | L29: ='Economist OLD'!AW30 -> 61.296927 | M29: ='Economist OLD'!AV30 -> 0.0005 | N29: 0.75 | O29: ='Economist OLD'!AS30 -> 48000 | P29: 755.03 | Q29: ='Economist OLD'!U30 -> 513.80179 | R29: ='Economist OLD'!V30 -> 513.80179 | S29: ='Economist OLD'!W30 -> 513.80179 | T29: ='Economist OLD'!X30 -> 513.80179 | U29: ='Economist OLD'!Y30 -> 513.80179 | V29: ='Economist OLD'!Z30 -> 513.80179 | W29: ='Economist OLD'!AA30 -> 446.21885 | X29: ='Economist OLD'!AB30 -> 513.80179 | ... AA29: ='Economist OLD'!AE30 -> 371.62508 | AB29: 18011 | AC29: ='Economist OLD'!AG30 -> 12256.722 | AD29: ='Economist OLD'!AH30 -> 12256.722 | AE29: ='Economist OLD'!AI30 -> 12256.722 | AF29: ='Economist OLD'!AJ30 -> 12256.722 | AG29: ='Economist OLD'!AK30 -> 12256.722 | AH29: ='Economist OLD'!AL30 -> 12256.722 | AI29: ='Economist OLD'!AM30 -> 10644.534 | AJ29: ='Economist OLD'!AN30 -> 12256.722 | ... AM29: ='Economist OLD'!AQ30 -> 8865.102 | AN29: 9 | AO29: =M29/12 -> 4.1666667e-05 | AP29: =AO29 -> 4.1666667e-05 | AQ29: =AP29 -> 4.1666667e-05 | AR29: =AQ29 -> 4.1666667e-05 | AS29: =AR29 -> 4.1666667e-05 | AT29: =AS29 -> 4.1666667e-05 | AU29: =AT29 -> 4.1666667e-05 | AV29: =AU29 -> 4.1666667e-05 | AW29: =AV29 -> 4.1666667e-05 | ... AY29: =AX29 -> 4.1666667e-05
D30: ='Economist OLD'!F31 -> Economist Subscribers | E30: Subscribers | F30: ='Economist OLD'!I31 -> Interscroller | G30: Economist_CA_Subscribers_Display_Interscroller | H30: Economist_CA_Subscribers | I30: ='Economist OLD'!S31+P30 -> 6063.134 | J30: ='Economist OLD'!M31 -> 126523.23 | K30: ='Economist OLD'!Q31 -> 41.92 | L30: ='Economist OLD'!AW31 -> 379.5697 | M30: ='Economist OLD'!AV31 -> 0.003 | N30: 0.75 | O30: ='Economist OLD'!AS31 -> 48000 | P30: 759.28 | Q30: ='Economist OLD'!U31 -> 530.27018 | R30: ='Economist OLD'!V31 -> 530.27018 | S30: ='Economist OLD'!W31 -> 530.27018 | T30: ='Economist OLD'!X31 -> 530.27018 | U30: ='Economist OLD'!Y31 -> 530.27018 | V30: ='Economist OLD'!Z31 -> 530.27018 | W30: ='Economist OLD'!AA31 -> 460.52107 | X30: ='Economist OLD'!AB31 -> 530.27018 | ... AA30: ='Economist OLD'!AE31 -> 383.53641 | AB30: 18112 | AC30: ='Economist OLD'!AG31 -> 12649.575 | AD30: ='Economist OLD'!AH31 -> 12649.575 | AE30: ='Economist OLD'!AI31 -> 12649.575 | AF30: ='Economist OLD'!AJ31 -> 12649.575 | AG30: ='Economist OLD'!AK31 -> 12649.575 | AH30: ='Economist OLD'!AL31 -> 12649.575 | AI30: ='Economist OLD'!AM31 -> 10985.712 | AJ30: ='Economist OLD'!AN31 -> 12649.575 | ... AM30: ='Economist OLD'!AQ31 -> 9149.2465 | AN30: 54 | AO30: =L30/11 -> 34.506337 | AP30: =AO30 -> 34.506337 | AQ30: =AP30 -> 34.506337 | AR30: =AQ30 -> 34.506337 | AS30: =AR30 -> 34.506337 | AT30: =AS30 -> 34.506337 | AU30: =AT30 -> 34.506337 | AV30: =AU30 -> 34.506337 | AW30: =AV30 -> 34.506337 | ... AY30: =AX30 -> 34.506337
D31: ='Economist OLD'!F32 -> Economist Subscribers | E31: Subscribers | F31: ='Economist OLD'!I32 -> 300x250 | G31: Economist_CA_Subscribers_Display_300x250 | H31: Economist_CA_Subscribers | I31: ='Economist OLD'!S32+P31 -> 5389.8471 | J31: ='Economist OLD'!M32 -> 56669.451 | K31: ='Economist OLD'!Q32 -> 60 | L31: ='Economist OLD'!AW32 -> 39.668616 | M31: ='Economist OLD'!AV32 -> 0.0007 | N31: 0.75 | O31: ='Economist OLD'!AS32 -> 77000 | P31: 1989.68 | Q31: ='Economist OLD'!U32 -> 339.94285 | R31: ='Economist OLD'!V32 -> 339.94285 | S31: ='Economist OLD'!W32 -> 339.94285 | T31: ='Economist OLD'!X32 -> 339.94285 | U31: ='Economist OLD'!Y32 -> 339.94285 | V31: ='Economist OLD'!Z32 -> 339.94285 | W31: ='Economist OLD'!AA32 -> 295.22844 | X31: ='Economist OLD'!AB32 -> 339.94285 | ... AA31: ='Economist OLD'!AE32 -> 245.87553 | AB31: 33161 | AC31: ='Economist OLD'!AG32 -> 5665.7141 | AD31: ='Economist OLD'!AH32 -> 5665.7141 | AE31: ='Economist OLD'!AI32 -> 5665.7141 | AF31: ='Economist OLD'!AJ32 -> 5665.7141 | AG31: ='Economist OLD'!AK32 -> 5665.7141 | AH31: ='Economist OLD'!AL32 -> 5665.7141 | AI31: ='Economist OLD'!AM32 -> 4920.4741 | AJ31: ='Economist OLD'!AN32 -> 5665.7141 | ... AM31: ='Economist OLD'!AQ32 -> 4097.9254 | AN31: 23 | AO31: =L31/11 -> 3.6062378 | AP31: =AO31 -> 3.6062378 | AQ31: =AP31 -> 3.6062378 | AR31: =AQ31 -> 3.6062378 | AS31: =AR31 -> 3.6062378 | AT31: =AS31 -> 3.6062378 | AU31: =AT31 -> 3.6062378 | AV31: =AU31 -> 3.6062378 | AW31: =AV31 -> 3.6062378 | ... AY31: =AX31 -> 3.6062378
D32: ='Economist OLD'!F33 -> Economist Subscribers | E32: Subscribers | F32: ='Economist OLD'!I33 -> App Interscroller | G32: Economist_CA_Subscribers_Display_appInterscroller | H32: Economist_CA_Subscribers | I32: ='Economist OLD'!S33+P32 -> 8580 | J32: ='Economist OLD'!M33 -> 85800 | K32: ='Economist OLD'!Q33 -> 100 | L32: ='Economist OLD'!AW33 -> 0 | M32: ='Economist OLD'!AV33 -> 0 | N32: 0.75 | O32: ='Economist OLD'!AS33 -> 77000 | P32: 0 | Q32: ='Economist OLD'!U33 -> 780 | R32: ='Economist OLD'!V33 -> 780 | S32: ='Economist OLD'!W33 -> 780 | T32: ='Economist OLD'!X33 -> 780 | U32: ='Economist OLD'!Y33 -> 780 | V32: ='Economist OLD'!Z33 -> 0 | W32: ='Economist OLD'!AA33 -> 1560 | X32: ='Economist OLD'!AB33 -> 780 | ... AA32: ='Economist OLD'!AE33 -> 780 | AB32: 0 | AC32: ='Economist OLD'!AG33 -> 7800 | AD32: ='Economist OLD'!AH33 -> 7800 | AE32: ='Economist OLD'!AI33 -> 7800 | AF32: ='Economist OLD'!AJ33 -> 7800 | AG32: ='Economist OLD'!AK33 -> 7800 | AH32: ='Economist OLD'!AL33 -> 0 | AI32: ='Economist OLD'!AM33 -> 15600 | AJ32: ='Economist OLD'!AN33 -> 7800 | ... AM32: ='Economist OLD'!AQ33 -> 7800 | AN32: 0 | AO32: 0 | AP32: 0 | AQ32: 0 | AR32: 0 | AS32: 0 | AT32: 0 | AU32: 0 | AV32: 0 | AW32: 0 | AX32: 0 | AY32: 0
D33: ='Economist OLD'!F34 -> Science & Technology (COP) | E33: Takeover | F33: Takeover | I33: ='Economist OLD'!S34+P33 -> 222.0751 | J33: ='Economist OLD'!M34 -> 3510 | K33: ='Economist OLD'!Q34 -> 222.0751 | L33: ='Economist OLD'!AW34 -> 2.457 | M33: ='Economist OLD'!AV34 -> 0.0007 | N33: 0.75 | O33: ='Economist OLD'!AS34 -> 445000 | P33: 0 | Q33: ='Economist OLD'!U34 -> 0 | R33: ='Economist OLD'!V34 -> 0 | S33: ='Economist OLD'!W34 -> 0 | T33: ='Economist OLD'!X34 -> 0 | U33: ='Economist OLD'!Y34 -> 0 | V33: ='Economist OLD'!Z34 -> 0 | W33: ='Economist OLD'!AA34 -> 222.0751 | X33: ='Economist OLD'!AB34 -> 0 | ... AA33: ='Economist OLD'!AE34 -> 0 | AB33: 0 | AC33: ='Economist OLD'!AG34 -> 0 | AD33: ='Economist OLD'!AH34 -> 0 | AE33: ='Economist OLD'!AI34 -> 0 | AF33: ='Economist OLD'!AJ34 -> 0 | AG33: ='Economist OLD'!AK34 -> 0 | AH33: ='Economist OLD'!AL34 -> 0 | AI33: ='Economist OLD'!AM34 -> 3510 | AJ33: ='Economist OLD'!AN34 -> 0 | ... AM33: ='Economist OLD'!AQ34 -> 0 | AN33: 0 | AO33: =M33/12 -> 5.8333333e-05 | AP33: =AO33 -> 5.8333333e-05 | AQ33: =AP33 -> 5.8333333e-05 | AR33: =AQ33 -> 5.8333333e-05 | AS33: =AR33 -> 5.8333333e-05 | AT33: =AS33 -> 5.8333333e-05 | AU33: =AT33 -> 5.8333333e-05 | AV33: =AU33 -> 5.8333333e-05 | AW33: =AV33 -> 5.8333333e-05 | ... AY33: =AX33 -> 5.8333333e-05
D34: ='Economist OLD'!F35 -> Science & Technology (COP) | E34: Takeover | F34: Takeover | I34: ='Economist OLD'!S35+P34 -> 222.0751 | J34: ='Economist OLD'!M35 -> 3510 | K34: ='Economist OLD'!Q35 -> 222.0751 | L34: ='Economist OLD'!AW35 -> 2.457 | M34: ='Economist OLD'!AV35 -> 0.0007 | N34: 0.75 | O34: ='Economist OLD'!AS35 -> 445000 | P34: 0 | Q34: ='Economist OLD'!U35 -> 0 | R34: ='Economist OLD'!V35 -> 0 | S34: ='Economist OLD'!W35 -> 0 | T34: ='Economist OLD'!X35 -> 0 | U34: ='Economist OLD'!Y35 -> 0 | V34: ='Economist OLD'!Z35 -> 0 | W34: ='Economist OLD'!AA35 -> 222.0751 | X34: ='Economist OLD'!AB35 -> 0 | ... AA34: ='Economist OLD'!AE35 -> 0 | AB34: 0 | AC34: ='Economist OLD'!AG35 -> 0 | AD34: ='Economist OLD'!AH35 -> 0 | AE34: ='Economist OLD'!AI35 -> 0 | AF34: ='Economist OLD'!AJ35 -> 0 | AG34: ='Economist OLD'!AK35 -> 0 | AH34: ='Economist OLD'!AL35 -> 0 | AI34: ='Economist OLD'!AM35 -> 3510 | AJ34: ='Economist OLD'!AN35 -> 0 | ... AM34: ='Economist OLD'!AQ35 -> 0 | AN34: 0 | AO34: =L34/11 -> 0.22336364 | AP34: =AO34 -> 0.22336364 | AQ34: =AP34 -> 0.22336364 | AR34: =AQ34 -> 0.22336364 | AS34: =AR34 -> 0.22336364 | AT34: =AS34 -> 0.22336364 | AU34: =AT34 -> 0.22336364 | AV34: =AU34 -> 0.22336364 | AW34: =AV34 -> 0.22336364 | ... AY34: =AX34 -> 0.22336364
D35: ='Economist OLD'!F36 -> Science & Technology (COP) | E35: Takeover | F35: Takeover | I35: ='Economist OLD'!S36+P35 -> 222.0751 | J35: ='Economist OLD'!M36 -> 3510 | K35: ='Economist OLD'!Q36 -> 222.0751 | L35: ='Economist OLD'!AW36 -> 2.457 | M35: ='Economist OLD'!AV36 -> 0.0007 | N35: 0.75 | O35: ='Economist OLD'!AS36 -> 445000 | P35: 0 | Q35: ='Economist OLD'!U36 -> 0 | R35: ='Economist OLD'!V36 -> 0 | S35: ='Economist OLD'!W36 -> 0 | T35: ='Economist OLD'!X36 -> 0 | U35: ='Economist OLD'!Y36 -> 0 | V35: ='Economist OLD'!Z36 -> 0 | W35: ='Economist OLD'!AA36 -> 0 | X35: ='Economist OLD'!AB36 -> 0 | ... AA35: ='Economist OLD'!AE36 -> 0 | AB35: 0 | AC35: ='Economist OLD'!AG36 -> 0 | AD35: ='Economist OLD'!AH36 -> 0 | AE35: ='Economist OLD'!AI36 -> 0 | AF35: ='Economist OLD'!AJ36 -> 0 | AG35: ='Economist OLD'!AK36 -> 0 | AH35: ='Economist OLD'!AL36 -> 0 | AI35: ='Economist OLD'!AM36 -> 0 | AJ35: ='Economist OLD'!AN36 -> 0 | ... AM35: ='Economist OLD'!AQ36 -> 0 | AN35: 0 | AO35: =L35/11 -> 0.22336364 | AP35: =AO35 -> 0.22336364 | AQ35: =AP35 -> 0.22336364 | AR35: =AQ35 -> 0.22336364 | AS35: =AR35 -> 0.22336364 | AT35: =AS35 -> 0.22336364 | AU35: =AT35 -> 0.22336364 | AV35: =AU35 -> 0.22336364 | AW35: =AV35 -> 0.22336364 | ... AY35: =AX35 -> 0.22336364
D36: ='Economist OLD'!F37 -> Business & Finance (Davos) | E36: Takeover | F36: Takeover | I36: ='Economist OLD'!S37+P36 -> 934.375 | J36: ='Economist OLD'!M37 -> 14950 | K36: ='Economist OLD'!Q37 -> 934.375 | L36: ='Economist OLD'!AW37 -> 10.465 | M36: ='Economist OLD'!AV37 -> 0.0007 | N36: 0.75 | O36: ='Economist OLD'!AS37 -> 445000 | P36: 0 | Q36: ='Economist OLD'!U37 -> 0 | R36: ='Economist OLD'!V37 -> 0 | S36: ='Economist OLD'!W37 -> 0 | T36: ='Economist OLD'!X37 -> 0 | U36: ='Economist OLD'!Y37 -> 0 | V36: ='Economist OLD'!Z37 -> 0 | W36: ='Economist OLD'!AA37 -> 0 | X36: ='Economist OLD'!AB37 -> 0 | ... AA36: ='Economist OLD'!AE37 -> 934.375 | AB36: 0 | AC36: ='Economist OLD'!AG37 -> 0 | AD36: ='Economist OLD'!AH37 -> 0 | AE36: ='Economist OLD'!AI37 -> 0 | AF36: ='Economist OLD'!AJ37 -> 0 | AG36: ='Economist OLD'!AK37 -> 0 | AH36: ='Economist OLD'!AL37 -> 0 | AI36: ='Economist OLD'!AM37 -> 0 | AJ36: ='Economist OLD'!AN37 -> 0 | ... AM36: ='Economist OLD'!AQ37 -> 14950 | AN36: 0 | AO36: 0 | AP36: =AO36 -> 0 | AQ36: =AP36 -> 0 | AR36: =AQ36 -> 0 | AS36: =AR36 -> 0 | AT36: =AS36 -> 0 | AU36: =AT36 -> 0 | AV36: =AU36 -> 0 | AW36: =AV36 -> 0 | AX36: =AW36 -> 0 | AY36: =L36 -> 10.465
C37: TOTAL | D37: ='Economist OLD'!F38 | I37: =SUM(I22:I36) -> 48125.016 | J37: =SUM(J22:J36) -> 860578.95 | L37: =SUM(L22:L36) -> 1100.6009
C38: ='Economist OLD'!B38 -> EMEA 0 Tier 1 | D38: ='Economist OLD'!F39 -> C0Level + Custom audience targeting companies 5,000+ | E38: Audience | F38: ResponsiveBillboard | G38: Economist_EMEATier1_Audience_Display_ResponsiveBillboard | H38: Economist_EMEATier1_Audience | I38: ='Economist OLD'!S39+P38 -> 11519.336 | J38: ='Economist OLD'!M39 -> 231889.36 | K38: ='Economist OLD'!Q39 -> 49.676 | L38: ='Economist OLD'!AW39 -> 162.32255 | M38: ='Economist OLD'!AV39 -> 0.0007 | N38: 0.75 | O38: ='Economist OLD'!AS39 -> 279500 | P38: 0 | Q38: ='Economist OLD'!U39 -> 1128.232 | R38: ='Economist OLD'!V39 -> 1128.232 | S38: ='Economist OLD'!W39 -> 1128.232 | T38: ='Economist OLD'!X39 -> 1128.232 | U38: ='Economist OLD'!Y39 -> 1128.232 | V38: ='Economist OLD'!Z39 -> 1654.8895 | W38: ='Economist OLD'!AA39 -> 526.65745 | X38: ='Economist OLD'!AB39 -> 1128.232 | ... AA38: ='Economist OLD'!AE39 -> 940.36994 | AB38: 0 | AC38: ='Economist OLD'!AG39 -> 22711.813 | AD38: ='Economist OLD'!AH39 -> 22711.813 | AE38: ='Economist OLD'!AI39 -> 22711.813 | AF38: ='Economist OLD'!AJ39 -> 22711.813 | AG38: ='Economist OLD'!AK39 -> 22711.813 | AH38: ='Economist OLD'!AL39 -> 33313.662 | AI38: ='Economist OLD'!AM39 -> 10601.849 | AJ38: ='Economist OLD'!AN39 -> 22711.813 | ... AM38: ='Economist OLD'!AQ39 -> 18930.066 | AN38: 0 | AO38: =L38/11 -> 14.756595 | AP38: =AO38 -> 14.756595 | AQ38: =AP38 -> 14.756595 | AR38: =AQ38 -> 14.756595 | AS38: =AR38 -> 14.756595 | AT38: =AS38 -> 14.756595 | AU38: =AT38 -> 14.756595 | AV38: =AU38 -> 14.756595 | AW38: =AV38 -> 14.756595 | ... AY38: =AX38 -> 14.756595
D39: ='Economist OLD'!F40 -> C0Level + Custom audience targeting companies 5,000+ | E39: Audience | F39: ='Economist OLD'!I40 -> 300x600 | G39: Economist_EMEATier1_Audience_Display_300x600 | H39: Economist_EMEATier1_Audience | I39: ='Economist OLD'!S40+P39 -> 10194.668 | J39: ='Economist OLD'!M40 -> 240693.41 | K39: ='Economist OLD'!Q40 -> 41.92 | L39: ='Economist OLD'!AW40 -> 120.34671 | M39: ='Economist OLD'!AV40 -> 0.0005 | N39: 0.75 | O39: ='Economist OLD'!AS40 -> 279500 | P39: 104.8 | Q39: ='Economist OLD'!U40 -> 988.22641 | R39: ='Economist OLD'!V40 -> 988.22641 | S39: ='Economist OLD'!W40 -> 988.22641 | T39: ='Economist OLD'!X40 -> 988.22641 | U39: ='Economist OLD'!Y40 -> 988.22641 | V39: ='Economist OLD'!Z40 -> 1449.5294 | W39: ='Economist OLD'!AA40 -> 461.30299 | X39: ='Economist OLD'!AB40 -> 988.22641 | ... AA39: ='Economist OLD'!AE40 -> 823.6767 | AB39: 2500 | AC39: ='Economist OLD'!AG40 -> 23574.103 | AD39: ='Economist OLD'!AH40 -> 23574.103 | AE39: ='Economist OLD'!AI40 -> 23574.103 | AF39: ='Economist OLD'!AJ40 -> 23574.103 | AG39: ='Economist OLD'!AK40 -> 23574.103 | AH39: ='Economist OLD'!AL40 -> 34578.469 | AI39: ='Economist OLD'!AM40 -> 11004.365 | AJ39: ='Economist OLD'!AN40 -> 23574.103 | ... AM39: ='Economist OLD'!AQ40 -> 19648.776 | AN39: 1 | AO39: =L39/11 -> 10.94061 | AP39: =AO39 -> 10.94061 | AQ39: =AP39 -> 10.94061 | AR39: =AQ39 -> 10.94061 | AS39: =AR39 -> 10.94061 | AT39: =AS39 -> 10.94061 | AU39: =AT39 -> 10.94061 | AV39: =AU39 -> 10.94061 | AW39: =AV39 -> 10.94061 | ... AY39: =AX39 -> 10.94061
D40: ='Economist OLD'!F41 -> C0Level + Custom audience targeting companies 5,000+ | E40: Audience | F40: ='Economist OLD'!I41 -> Interscroller | G40: Economist_EMEATier1_Audience_Display_Interscroller | H40: Economist_EMEATier1_Audience | I40: ='Economist OLD'!S41+P40 -> 12285.997 | J40: ='Economist OLD'!M41 -> 293081.98 | K40: ='Economist OLD'!Q41 -> 41.92 | L40: ='Economist OLD'!AW41 -> 879.24593 | M40: ='Economist OLD'!AV41 -> 0.003 | N40: 0.75 | O40: ='Economist OLD'!AS41 -> 279500 | P40: 0 | Q40: ='Economist OLD'!U41 -> 1203.3206 | R40: ='Economist OLD'!V41 -> 1203.3206 | S40: ='Economist OLD'!W41 -> 1203.3206 | T40: ='Economist OLD'!X41 -> 1203.3206 | U40: ='Economist OLD'!Y41 -> 1203.3206 | V40: ='Economist OLD'!Z41 -> 1765.0294 | W40: ='Economist OLD'!AA41 -> 561.70874 | X40: ='Economist OLD'!AB41 -> 1203.3206 | ... AA40: ='Economist OLD'!AE41 -> 1002.9556 | AB40: 0 | AC40: ='Economist OLD'!AG41 -> 28705.168 | AD40: ='Economist OLD'!AH41 -> 28705.168 | AE40: ='Economist OLD'!AI41 -> 28705.168 | AF40: ='Economist OLD'!AJ41 -> 28705.168 | AG40: ='Economist OLD'!AK41 -> 28705.168 | AH40: ='Economist OLD'!AL41 -> 42104.709 | AI40: ='Economist OLD'!AM41 -> 13399.541 | AJ40: ='Economist OLD'!AN41 -> 28705.168 | ... AM40: ='Economist OLD'!AQ41 -> 23925.467 | AN40: 0 | AO40: =L40/11 -> 79.931448 | AP40: =AO40 -> 79.931448 | AQ40: =AP40 -> 79.931448 | AR40: =AQ40 -> 79.931448 | AS40: =AR40 -> 79.931448 | AT40: =AS40 -> 79.931448 | AU40: =AT40 -> 79.931448 | AV40: =AU40 -> 79.931448 | AW40: =AV40 -> 79.931448 | ... AY40: =AX40 -> 79.931448
D41: ='Economist OLD'!F42 -> C0Level + ESG articles and content | E41: Audience+Contextual | F41: ResponsiveBillboard | G41: Economist_EMEATier1_Audience+Contextual_Display_ResponsiveBillboard | H41: Economist_EMEATier1_Audience+Contextual | I41: ='Economist OLD'!S42+P41 -> 6033.3325 | J41: ='Economist OLD'!M42 -> 136039.06 | K41: ='Economist OLD'!Q42 -> 44.35 | L41: ='Economist OLD'!AW42 -> 95.227344 | M41: ='Economist OLD'!AV42 -> 0.0007 | N41: 0.75 | O41: ='Economist OLD'!AS42 -> 1060000 | P41: 0 | Q41: ='Economist OLD'!U42 -> 590.91939 | R41: ='Economist OLD'!V42 -> 590.91939 | S41: ='Economist OLD'!W42 -> 590.91939 | T41: ='Economist OLD'!X42 -> 590.91939 | U41: ='Economist OLD'!Y42 -> 590.91939 | V41: ='Economist OLD'!Z42 -> 866.7599 | W41: ='Economist OLD'!AA42 -> 275.84051 | X41: ='Economist OLD'!AB42 -> 590.91939 | ... AA41: ='Economist OLD'!AE42 -> 492.52532 | AB41: 0 | AC41: ='Economist OLD'!AG42 -> 13324 | AD41: ='Economist OLD'!AH42 -> 13324 | AE41: ='Economist OLD'!AI42 -> 13324 | AF41: ='Economist OLD'!AJ42 -> 13324 | AG41: ='Economist OLD'!AK42 -> 13324 | AH41: ='Economist OLD'!AL42 -> 19543.628 | AI41: ='Economist OLD'!AM42 -> 6219.6283 | AJ41: ='Economist OLD'!AN42 -> 13324 | ... AM41: ='Economist OLD'!AQ42 -> 11105.419 | AN41: 0 | AO41: =L41/11 -> 8.6570313 | AP41: =AO41 -> 8.6570313 | AQ41: =AP41 -> 8.6570313 | AR41: =AQ41 -> 8.6570313 | AS41: =AR41 -> 8.6570313 | AT41: =AS41 -> 8.6570313 | AU41: =AT41 -> 8.6570313 | AV41: =AU41 -> 8.6570313 | AW41: =AV41 -> 8.6570313 | ... AY41: =AX41 -> 8.6570313
D42: ='Economist OLD'!F43 -> C0Level + ESG articles and content | E42: Audience+Contextual | F42: ='Economist OLD'!I43 -> 300x600 | G42: Economist_EMEATier1_Audience+Contextual_Display_300x600 | H42: Economist_EMEATier1_Audience+Contextual | I42: ='Economist OLD'!S43+P42 -> 5383.5662 | J42: ='Economist OLD'!M43 -> 142046.6 | K42: ='Economist OLD'!Q43 -> 37.9 | L42: ='Economist OLD'!AW43 -> 71.023301 | M42: ='Economist OLD'!AV43 -> 0.0005 | N42: 0.75 | O42: ='Economist OLD'!AS43 -> 1060000 | P42: 0 | Q42: ='Economist OLD'!U43 -> 527.27969 | R42: ='Economist OLD'!V43 -> 527.27969 | S42: ='Economist OLD'!W43 -> 527.27969 | T42: ='Economist OLD'!X43 -> 527.27969 | U42: ='Economist OLD'!Y43 -> 527.27969 | V42: ='Economist OLD'!Z43 -> 773.41326 | W42: ='Economist OLD'!AA43 -> 246.13357 | X42: ='Economist OLD'!AB43 -> 527.27969 | ... AA42: ='Economist OLD'!AE43 -> 439.48228 | AB42: 0 | AC42: ='Economist OLD'!AG43 -> 13912.393 | AD42: ='Economist OLD'!AH43 -> 13912.393 | AE42: ='Economist OLD'!AI43 -> 13912.393 | AF42: ='Economist OLD'!AJ43 -> 13912.393 | AG42: ='Economist OLD'!AK43 -> 13912.393 | AH42: ='Economist OLD'!AL43 -> 20406.682 | AI42: ='Economist OLD'!AM43 -> 6494.2895 | AJ42: ='Economist OLD'!AN43 -> 13912.393 | ... AM42: ='Economist OLD'!AQ43 -> 11595.838 | AN42: 0 | AO42: =L42/11 -> 6.4566637 | AP42: =AO42 -> 6.4566637 | AQ42: =AP42 -> 6.4566637 | AR42: =AQ42 -> 6.4566637 | AS42: =AR42 -> 6.4566637 | AT42: =AS42 -> 6.4566637 | AU42: =AT42 -> 6.4566637 | AV42: =AU42 -> 6.4566637 | AW42: =AV42 -> 6.4566637 | ... AY42: =AX42 -> 6.4566637
D43: ='Economist OLD'!F44 -> C0Level + ESG articles and content | E43: Audience+Contextual | F43: ='Economist OLD'!I44 -> Interscroller | G43: Economist_EMEATier1_Audience+Contextual_Display_Interscroller | H43: Economist_EMEATier1_Audience+Contextual | I43: ='Economist OLD'!S44+P43 -> 6033.3325 | J43: ='Economist OLD'!M44 -> 159190.83 | K43: ='Economist OLD'!Q44 -> 37.9 | L43: ='Economist OLD'!AW44 -> 477.57249 | M43: ='Economist OLD'!AV44 -> 0.003 | N43: 0.75 | O43: ='Economist OLD'!AS44 -> 1060000 | P43: 0 | Q43: ='Economist OLD'!U44 -> 590.91939 | R43: ='Economist OLD'!V44 -> 590.91939 | S43: ='Economist OLD'!W44 -> 590.91939 | T43: ='Economist OLD'!X44 -> 590.91939 | U43: ='Economist OLD'!Y44 -> 590.91939 | V43: ='Economist OLD'!Z44 -> 866.7599 | W43: ='Economist OLD'!AA44 -> 275.84051 | X43: ='Economist OLD'!AB44 -> 590.91939 | ... AA43: ='Economist OLD'!AE44 -> 492.52532 | AB43: 0 | AC43: ='Economist OLD'!AG44 -> 15591.541 | AD43: ='Economist OLD'!AH44 -> 15591.541 | AE43: ='Economist OLD'!AI44 -> 15591.541 | AF43: ='Economist OLD'!AJ44 -> 15591.541 | AG43: ='Economist OLD'!AK44 -> 15591.541 | AH43: ='Economist OLD'!AL44 -> 22869.654 | AI43: ='Economist OLD'!AM44 -> 7278.1138 | AJ43: ='Economist OLD'!AN44 -> 15591.541 | ... AM43: ='Economist OLD'!AQ44 -> 12995.391 | AN43: 0 | AO43: =L43/11 -> 43.415681 | AP43: =AO43 -> 43.415681 | AQ43: =AP43 -> 43.415681 | AR43: =AQ43 -> 43.415681 | AS43: =AR43 -> 43.415681 | AT43: =AS43 -> 43.415681 | AU43: =AT43 -> 43.415681 | AV43: =AU43 -> 43.415681 | AW43: =AV43 -> 43.415681 | ... AY43: =AX43 -> 43.415681
D44: ='Economist OLD'!F45 -> Economist Subscribers | E44: Subscribers | F44: ResponsiveBillboard | G44: Economist_EMEATier1_Subscribers_Display_ResponsiveBillboard | H44: Economist_EMEATier1_Subscribers | I44: ='Economist OLD'!S45+P44 -> 26452.667 | J44: ='Economist OLD'!M45 -> 532503.97 | K44: ='Economist OLD'!Q45 -> 49.676 | L44: ='Economist OLD'!AW45 -> 372.75278 | M44: ='Economist OLD'!AV45 -> 0.0007 | N44: 0.75 | O44: ='Economist OLD'!AS45 -> 155000 | P44: 0 | Q44: ='Economist OLD'!U45 -> 2590.8392 | R44: ='Economist OLD'!V45 -> 2590.8392 | S44: ='Economist OLD'!W45 -> 2590.8392 | T44: ='Economist OLD'!X45 -> 2590.8392 | U44: ='Economist OLD'!Y45 -> 2590.8392 | V44: ='Economist OLD'!Z45 -> 3800.24 | W44: ='Economist OLD'!AA45 -> 1209.4008 | X44: ='Economist OLD'!AB45 -> 2590.8392 | ... AA44: ='Economist OLD'!AE45 -> 2159.4382 | AB44: 0 | AC44: ='Economist OLD'!AG45 -> 52154.746 | AD44: ='Economist OLD'!AH45 -> 52154.746 | AE44: ='Economist OLD'!AI45 -> 52154.746 | AF44: ='Economist OLD'!AJ45 -> 52154.746 | AG44: ='Economist OLD'!AK45 -> 52154.746 | AH44: ='Economist OLD'!AL45 -> 76500.524 | AI44: ='Economist OLD'!AM45 -> 24345.778 | AJ44: ='Economist OLD'!AN45 -> 52154.746 | ... AM44: ='Economist OLD'!AQ45 -> 43470.452 | AN44: 0 | AO44: =L44/11 -> 33.886617 | AP44: =AO44 -> 33.886617 | AQ44: =AP44 -> 33.886617 | AR44: =AQ44 -> 33.886617 | AS44: =AR44 -> 33.886617 | AT44: =AS44 -> 33.886617 | AU44: =AT44 -> 33.886617 | AV44: =AU44 -> 33.886617 | AW44: =AV44 -> 33.886617 | ... AY44: =AX44 -> 33.886617
D45: ='Economist OLD'!F46 -> Economist Subscribers | E45: Subscribers | F45: ='Economist OLD'!I46 -> 300x600 | G45: Economist_EMEATier1_Subscribers_Display_300x600 | H45: Economist_EMEATier1_Subscribers | I45: ='Economist OLD'!S46+P45 -> 18861.335 | J45: ='Economist OLD'!M46 -> 449936.43 | K45: ='Economist OLD'!Q46 -> 41.92 | L45: ='Economist OLD'!AW46 -> 224.96821 | M45: ='Economist OLD'!AV46 -> 0.0005 | N45: 0.75 | O45: ='Economist OLD'!AS46 -> 155000 | P45: 0 | Q45: ='Economist OLD'!U46 -> 1847.3254 | R45: ='Economist OLD'!V46 -> 1847.3254 | S45: ='Economist OLD'!W46 -> 1847.3254 | T45: ='Economist OLD'!X46 -> 1847.3254 | U45: ='Economist OLD'!Y46 -> 1847.3254 | V45: ='Economist OLD'!Z46 -> 2709.6549 | W45: ='Economist OLD'!AA46 -> 862.32947 | X45: ='Economist OLD'!AB46 -> 1847.3254 | ... AA45: ='Economist OLD'!AE46 -> 1539.727 | AB45: 0 | AC45: ='Economist OLD'!AG46 -> 44067.878 | AD45: ='Economist OLD'!AH46 -> 44067.878 | AE45: ='Economist OLD'!AI46 -> 44067.878 | AF45: ='Economist OLD'!AJ46 -> 44067.878 | AG45: ='Economist OLD'!AK46 -> 44067.878 | AH45: ='Economist OLD'!AL46 -> 64638.715 | AI45: ='Economist OLD'!AM46 -> 20570.836 | AJ45: ='Economist OLD'!AN46 -> 44067.878 | ... AM45: ='Economist OLD'!AQ46 -> 36730.13 | AN45: 0 | AO45: =L45/11 -> 20.451656 | AP45: =AO45 -> 20.451656 | AQ45: =AP45 -> 20.451656 | AR45: =AQ45 -> 20.451656 | AS45: =AR45 -> 20.451656 | AT45: =AS45 -> 20.451656 | AU45: =AT45 -> 20.451656 | AV45: =AU45 -> 20.451656 | AW45: =AV45 -> 20.451656 | ... AY45: =AX45 -> 20.451656
D46: ='Economist OLD'!F47 -> Economist Subscribers | E46: Subscribers | F46: ='Economist OLD'!I47 -> Interscroller | G46: Economist_EMEATier1_Subscribers_Display_Interscroller | H46: Economist_EMEATier1_Subscribers | I46: ='Economist OLD'!S47+P46 -> 25801.995 | J46: ='Economist OLD'!M47 -> 606505.61 | K46: ='Economist OLD'!Q47 -> 41.92 | L46: ='Economist OLD'!AW47 -> 1819.5168 | M46: ='Economist OLD'!AV47 -> 0.003 | N46: 0.75 | O46: ='Economist OLD'!AS47 -> 155000 | P46: 377.28 | Q46: ='Economist OLD'!U47 -> 2490.159 | R46: ='Economist OLD'!V47 -> 2490.159 | S46: ='Economist OLD'!W47 -> 2490.159 | T46: ='Economist OLD'!X47 -> 2490.159 | U46: ='Economist OLD'!Y47 -> 2490.159 | V46: ='Economist OLD'!Z47 -> 3652.5624 | W46: ='Economist OLD'!AA47 -> 1162.4034 | X46: ='Economist OLD'!AB47 -> 2490.159 | ... AA46: ='Economist OLD'!AE47 -> 2075.5223 | AB46: 9000 | AC46: ='Economist OLD'!AG47 -> 59402.648 | AD46: ='Economist OLD'!AH47 -> 59402.648 | AE46: ='Economist OLD'!AI47 -> 59402.648 | AF46: ='Economist OLD'!AJ47 -> 59402.648 | AG46: ='Economist OLD'!AK47 -> 59402.648 | AH46: ='Economist OLD'!AL47 -> 87131.738 | AI46: ='Economist OLD'!AM47 -> 27729.09 | AJ46: ='Economist OLD'!AN47 -> 59402.648 | ... AM46: ='Economist OLD'!AQ47 -> 49511.505 | AN46: 27 | AO46: =L46/11 -> 165.41062 | AP46: =AO46 -> 165.41062 | AQ46: =AP46 -> 165.41062 | AR46: =AQ46 -> 165.41062 | AS46: =AR46 -> 165.41062 | AT46: =AS46 -> 165.41062 | AU46: =AT46 -> 165.41062 | AV46: =AU46 -> 165.41062 | AW46: =AV46 -> 165.41062 | ... AY46: =AX46 -> 165.41062
D47: ='Economist OLD'!F48 -> Economist Subscribers | E47: Subscribers | F47: ='Economist OLD'!I48 -> 300x250 | G47: Economist_EMEATier1_Subscribers_Display_300x250 | H47: Economist_EMEATier1_Subscribers | I47: ='Economist OLD'!S48+P47 -> 17247.513 | J47: ='Economist OLD'!M48 -> 73072.216 | K47: ='Economist OLD'!Q48 -> 60 | L47: ='Economist OLD'!AW48 -> 51.150551 | M47: ='Economist OLD'!AV48 -> 0.0007 | N47: 0.75 | O47: ='Economist OLD'!AS48 -> 155000 | P47: 12863.18 | Q47: ='Economist OLD'!U48 -> 429.41233 | R47: ='Economist OLD'!V48 -> 429.41233 | S47: ='Economist OLD'!W48 -> 429.41233 | T47: ='Economist OLD'!X48 -> 429.41233 | U47: ='Economist OLD'!Y48 -> 429.41233 | V47: ='Economist OLD'!Z48 -> 629.86153 | W47: ='Economist OLD'!AA48 -> 200.4492 | X47: ='Economist OLD'!AB48 -> 429.41233 | ... AA47: ='Economist OLD'!AE48 -> 357.91082 | AB47: 214386 | AC47: ='Economist OLD'!AG48 -> 7156.8721 | AD47: ='Economist OLD'!AH48 -> 7156.8721 | AE47: ='Economist OLD'!AI48 -> 7156.8721 | AF47: ='Economist OLD'!AJ48 -> 7156.8721 | AG47: ='Economist OLD'!AK48 -> 7156.8721 | AH47: ='Economist OLD'!AL48 -> 10497.692 | AI47: ='Economist OLD'!AM48 -> 3340.82 | AJ47: ='Economist OLD'!AN48 -> 7156.8721 | ... AM47: ='Economist OLD'!AQ48 -> 5965.1804 | AN47: 150 | AO47: =L47/11 -> 4.6500501 | AP47: =AO47 -> 4.6500501 | AQ47: =AP47 -> 4.6500501 | AR47: =AQ47 -> 4.6500501 | AS47: =AR47 -> 4.6500501 | AT47: =AS47 -> 4.6500501 | AU47: =AT47 -> 4.6500501 | AV47: =AU47 -> 4.6500501 | AW47: =AV47 -> 4.6500501 | ... AY47: =AX47 -> 4.6500501
D48: ='Economist OLD'!F49 -> Economist Subscribers | E48: Subscribers | F48: ='Economist OLD'!I49 -> App Interscroller | G48: Economist_EMEATier1_Subscribers_Display_appInterscroller | H48: Economist_EMEATier1_Subscribers | I48: ='Economist OLD'!S49+P48 -> 10890 | J48: ='Economist OLD'!M49 -> 108900 | K48: ='Economist OLD'!Q49 -> 100 | L48: ='Economist OLD'!AW49 -> 0 | M48: ='Economist OLD'!AV49 -> 0 | N48: 0.75 | O48: ='Economist OLD'!AS49 -> 155000 | P48: 0 | Q48: ='Economist OLD'!U49 -> 990 | R48: ='Economist OLD'!V49 -> 990 | S48: ='Economist OLD'!W49 -> 990 | T48: ='Economist OLD'!X49 -> 990 | U48: ='Economist OLD'!Y49 -> 990 | V48: ='Economist OLD'!Z49 -> 0 | W48: ='Economist OLD'!AA49 -> 1980 | X48: ='Economist OLD'!AB49 -> 990 | ... AA48: ='Economist OLD'!AE49 -> 990 | AB48: 0 | AC48: ='Economist OLD'!AG49 -> 9900 | AD48: ='Economist OLD'!AH49 -> 9900 | AE48: ='Economist OLD'!AI49 -> 9900 | AF48: ='Economist OLD'!AJ49 -> 9900 | AG48: ='Economist OLD'!AK49 -> 9900 | AH48: ='Economist OLD'!AL49 -> 0 | AI48: ='Economist OLD'!AM49 -> 19800 | AJ48: ='Economist OLD'!AN49 -> 9900 | ... AM48: ='Economist OLD'!AQ49 -> 9900 | AN48: 0 | AO48: 0 | AP48: 0 | AQ48: 0 | AR48: 0 | AS48: 0 | AT48: 0 | AU48: 0 | AV48: 0 | AW48: 0 | AX48: 0 | AY48: 0
D49: ='Economist OLD'!F50 -> Science & Technology (COP) | E49: Takeover | F49: Takeover | I49: ='Economist OLD'!S50+P49 -> 411.25 | J49: ='Economist OLD'!M50 -> 6500 | K49: ='Economist OLD'!Q50 -> 411.25 | L49: ='Economist OLD'!AW50 -> 4.55 | M49: ='Economist OLD'!AV50 -> 0.0007 | N49: 0.75 | O49: ='Economist OLD'!AS50 -> 445000 | P49: 0 | Q49: ='Economist OLD'!U50 -> 0 | R49: ='Economist OLD'!V50 -> 0 | S49: ='Economist OLD'!W50 -> 0 | T49: ='Economist OLD'!X50 -> 0 | U49: ='Economist OLD'!Y50 -> 0 | V49: ='Economist OLD'!Z50 -> 0 | W49: ='Economist OLD'!AA50 -> 411.25 | X49: ='Economist OLD'!AB50 -> 0 | ... AA49: ='Economist OLD'!AE50 -> 0 | AB49: 0 | AC49: ='Economist OLD'!AG50 -> 0 | AD49: ='Economist OLD'!AH50 -> 0 | AE49: ='Economist OLD'!AI50 -> 0 | AF49: ='Economist OLD'!AJ50 -> 0 | AG49: ='Economist OLD'!AK50 -> 0 | AH49: ='Economist OLD'!AL50 -> 0 | AI49: ='Economist OLD'!AM50 -> 6500 | AJ49: ='Economist OLD'!AN50 -> 0 | ... AM49: ='Economist OLD'!AQ50 -> 0 | AN49: 0 | AO49: 0 | AP49: =AO49 -> 0 | AQ49: =AP49 -> 0 | AR49: =AQ49 -> 0 | AS49: =AR49 -> 0 | AT49: =AS49 -> 0 | AU49: =L49 -> 4.55 | AV49: 0 | AW49: 0 | AX49: 0 | AY49: =AX49 -> 0
D50: ='Economist OLD'!F51 -> Science & Technology (COP) | E50: Takeover | F50: Takeover | I50: ='Economist OLD'!S51+P50 -> 411.25 | J50: ='Economist OLD'!M51 -> 6500 | K50: ='Economist OLD'!Q51 -> 411.25 | L50: ='Economist OLD'!AW51 -> 4.55 | M50: ='Economist OLD'!AV51 -> 0.0007 | N50: 0.75 | O50: ='Economist OLD'!AS51 -> 445000 | P50: 0 | Q50: ='Economist OLD'!U51 -> 0 | R50: ='Economist OLD'!V51 -> 0 | S50: ='Economist OLD'!W51 -> 0 | T50: ='Economist OLD'!X51 -> 0 | U50: ='Economist OLD'!Y51 -> 0 | V50: ='Economist OLD'!Z51 -> 0 | W50: ='Economist OLD'!AA51 -> 411.25 | X50: ='Economist OLD'!AB51 -> 0 | ... AA50: ='Economist OLD'!AE51 -> 0 | AB50: 0 | AC50: ='Economist OLD'!AG51 -> 0 | AD50: ='Economist OLD'!AH51 -> 0 | AE50: ='Economist OLD'!AI51 -> 0 | AF50: ='Economist OLD'!AJ51 -> 0 | AG50: ='Economist OLD'!AK51 -> 0 | AH50: ='Economist OLD'!AL51 -> 0 | AI50: ='Economist OLD'!AM51 -> 6500 | AJ50: ='Economist OLD'!AN51 -> 0 | ... AM50: ='Economist OLD'!AQ51 -> 0 | AN50: 0 | AO50: 0 | AP50: =AO50 -> 0 | AQ50: =AP50 -> 0 | AR50: =AQ50 -> 0 | AS50: =AR50 -> 0 | AT50: =AS50 -> 0 | AU50: =L50 -> 4.55 | AV50: 0 | AW50: 0 | AX50: =AW50 -> 0 | AY50: =AX50 -> 0
D51: ='Economist OLD'!F52 -> Science & Technology (COP) | E51: Takeover | F51: Takeover | I51: ='Economist OLD'!S52+P51 -> 411.25 | J51: ='Economist OLD'!M52 -> 6500 | K51: ='Economist OLD'!Q52 -> 411.25 | L51: ='Economist OLD'!AW52 -> 4.55 | M51: ='Economist OLD'!AV52 -> 0.0007 | N51: 0.75 | O51: ='Economist OLD'!AS52 -> 445000 | P51: 0 | Q51: ='Economist OLD'!U52 -> 0 | R51: ='Economist OLD'!V52 -> 0 | S51: ='Economist OLD'!W52 -> 0 | T51: ='Economist OLD'!X52 -> 0 | U51: ='Economist OLD'!Y52 -> 0 | V51: ='Economist OLD'!Z52 -> 0 | W51: ='Economist OLD'!AA52 -> 0 | X51: ='Economist OLD'!AB52 -> 0 | ... AA51: ='Economist OLD'!AE52 -> 0 | AB51: 0 | AC51: ='Economist OLD'!AG52 -> 0 | AD51: ='Economist OLD'!AH52 -> 0 | AE51: ='Economist OLD'!AI52 -> 0 | AF51: ='Economist OLD'!AJ52 -> 0 | AG51: ='Economist OLD'!AK52 -> 0 | AH51: ='Economist OLD'!AL52 -> 0 | AI51: ='Economist OLD'!AM52 -> 0 | AJ51: ='Economist OLD'!AN52 -> 0 | ... AM51: ='Economist OLD'!AQ52 -> 0 | AN51: 0 | AO51: 0 | AP51: =AO51 -> 0 | AQ51: =AP51 -> 0 | AR51: =AQ51 -> 0 | AS51: =AR51 -> 0 | AT51: =AS51 -> 0 | AU51: =AT51 -> 0 | AV51: =AU51 -> 0 | AW51: =L51 -> 4.55 | AX51: 0 | AY51: 0
D52: ='Economist OLD'!F53 -> Business & Finance (Davos) | E52: Takeover | F52: Takeover | I52: ='Economist OLD'!S53+P52 -> 2062.5 | J52: ='Economist OLD'!M53 -> 33000 | K52: ='Economist OLD'!Q53 -> 2062.5 | L52: ='Economist OLD'!AW53 -> 23.1 | M52: ='Economist OLD'!AV53 -> 0.0007 | N52: 0.75 | O52: ='Economist OLD'!AS53 -> 445000 | P52: 0 | Q52: ='Economist OLD'!U53 -> 0 | R52: ='Economist OLD'!V53 -> 0 | S52: ='Economist OLD'!W53 -> 0 | T52: ='Economist OLD'!X53 -> 0 | U52: ='Economist OLD'!Y53 -> 0 | V52: ='Economist OLD'!Z53 -> 0 | W52: ='Economist OLD'!AA53 -> 0 | X52: ='Economist OLD'!AB53 -> 0 | ... AA52: ='Economist OLD'!AE53 -> 2062.5 | AB52: 0 | AC52: ='Economist OLD'!AG53 -> 0 | AD52: ='Economist OLD'!AH53 -> 0 | AE52: ='Economist OLD'!AI53 -> 0 | AF52: ='Economist OLD'!AJ53 -> 0 | AG52: ='Economist OLD'!AK53 -> 0 | AH52: ='Economist OLD'!AL53 -> 0 | AI52: ='Economist OLD'!AM53 -> 0 | AJ52: ='Economist OLD'!AN53 -> 0 | ... AM52: ='Economist OLD'!AQ53 -> 33000 | AN52: 0 | AO52: 0 | AP52: =AO52 -> 0 | AQ52: =AP52 -> 0 | AR52: =AQ52 -> 0 | AS52: =AR52 -> 0 | AT52: =AS52 -> 0 | AU52: =AT52 -> 0 | AV52: =AU52 -> 0 | AW52: =AV52 -> 0 | AX52: =AW52 -> 0 | AY52: =L52 -> 23.1
C53: TOTAL | D53: ='Economist OLD'!F54 | F53: ='Economist OLD'!I54 | I53: =SUM(I38:I52) -> 153999.99 | J53: =SUM(J38:J52) -> 3026359.5 | K53: ='Economist OLD'!Q54 | L53: =SUM(L38:L52) -> 4310.8767 | M53: ='Economist OLD'!AV54 | O53: ='Economist OLD'!AS54 | P53: ='Economist OLD'!AT54 | Q53: ='Economist OLD'!AU54 | R53: ='Economist OLD'!AV54 | S53: ='Economist OLD'!AW54 | T53: ='Economist OLD'!AX54 | U53: ='Economist OLD'!AY54 | V53: ='Economist OLD'!AZ54 | ... AM53: ='Economist OLD'!BQ54
C54: ='Economist OLD'!B54 -> EMEA 0 Tier 2 | D54: ='Economist OLD'!F55 -> C0Level + Custom audience targeting companies 5,000+ | E54: Audience | F54: ResponsiveBillboard | G54: Economist_EMEATier2_Audience_Display_ResponsiveBillboard | H54: Economist_EMEATier2_Audience | I54: ='Economist OLD'!S55+P54 -> 4936.8571 | J54: ='Economist OLD'!M55 -> 99381.133 | K54: ='Economist OLD'!Q55 -> 49.676 | L54: ='Economist OLD'!AW55 -> 69.566793 | M54: ='Economist OLD'!AV55 -> 0.0007 | N54: 0.75 | O54: ='Economist OLD'!AS55 -> 279500 | P54: 0 | Q54: ='Economist OLD'!U55 -> 504.94466 | R54: ='Economist OLD'!V55 -> 504.94466 | S54: ='Economist OLD'!W55 -> 504.94466 | T54: ='Economist OLD'!X55 -> 504.94466 | U54: ='Economist OLD'!Y55 -> 504.94466 | V54: ='Economist OLD'!Z55 -> 504.94466 | W54: ='Economist OLD'!AA55 -> 416.85218 | X54: ='Economist OLD'!AB55 -> 504.94466 | ... AA54: ='Economist OLD'!AE55 -> 284.04407 | AB54: 0 | AC54: ='Economist OLD'!AG55 -> 10164.761 | AD54: ='Economist OLD'!AH55 -> 10164.761 | AE54: ='Economist OLD'!AI55 -> 10164.761 | AF54: ='Economist OLD'!AJ55 -> 10164.761 | AG54: ='Economist OLD'!AK55 -> 10164.761 | AH54: ='Economist OLD'!AL55 -> 10164.761 | AI54: ='Economist OLD'!AM55 -> 8391.42 | AJ54: ='Economist OLD'!AN55 -> 10164.761 | ... AM54: ='Economist OLD'!AQ55 -> 5717.9335 | AN54: 0 | AO54: =L54/11 -> 6.3242539 | AP54: =AO54 -> 6.3242539 | AQ54: =AP54 -> 6.3242539 | AR54: =AQ54 -> 6.3242539 | AS54: =AR54 -> 6.3242539 | AT54: =AS54 -> 6.3242539 | AU54: =AT54 -> 6.3242539 | AV54: =AU54 -> 6.3242539 | AW54: =AV54 -> 6.3242539 | ... AY54: =AX54 -> 6.3242539
D55: ='Economist OLD'!F56 -> C0Level + Custom audience targeting companies 5,000+ | E55: Audience | F55: ='Economist OLD'!I56 -> 300x600 | G55: Economist_EMEATier2_Audience_Display_300x600 | H55: Economist_EMEATier2_Audience | I55: ='Economist OLD'!S56+P55 -> 3512 | J55: ='Economist OLD'!M56 -> 83778.626 | K55: ='Economist OLD'!Q56 -> 41.92 | L55: ='Economist OLD'!AW56 -> 41.889313 | M55: ='Economist OLD'!AV56 -> 0.0005 | N55: 0.75 | O55: ='Economist OLD'!AS56 -> 279500 | P55: 0 | Q55: ='Economist OLD'!U56 -> 359.20943 | R55: ='Economist OLD'!V56 -> 359.20943 | S55: ='Economist OLD'!W56 -> 359.20943 | T55: ='Economist OLD'!X56 -> 359.20943 | U55: ='Economist OLD'!Y56 -> 359.20943 | V55: ='Economist OLD'!Z56 -> 359.20943 | W55: ='Economist OLD'!AA56 -> 296.54187 | X55: ='Economist OLD'!AB56 -> 359.20943 | ... AA55: ='Economist OLD'!AE56 -> 202.06434 | AB55: 0 | AC55: ='Economist OLD'!AG56 -> 8568.9273 | AD55: ='Economist OLD'!AH56 -> 8568.9273 | AE55: ='Economist OLD'!AI56 -> 8568.9273 | AF55: ='Economist OLD'!AJ56 -> 8568.9273 | AG55: ='Economist OLD'!AK56 -> 8568.9273 | AH55: ='Economist OLD'!AL56 -> 8568.9273 | AI55: ='Economist OLD'!AM56 -> 7073.9951 | AJ55: ='Economist OLD'!AN56 -> 8568.9273 | ... AM55: ='Economist OLD'!AQ56 -> 4820.237 | AN55: 0 | AO55: =L55/11 -> 3.8081194 | AP55: =AO55 -> 3.8081194 | AQ55: =AP55 -> 3.8081194 | AR55: =AQ55 -> 3.8081194 | AS55: =AR55 -> 3.8081194 | AT55: =AS55 -> 3.8081194 | AU55: =AT55 -> 3.8081194 | AV55: =AU55 -> 3.8081194 | AW55: =AV55 -> 3.8081194 | ... AY55: =AX55 -> 3.8081194
D56: ='Economist OLD'!F57 -> C0Level + Custom audience targeting companies 5,000+ | E56: Audience | F56: ='Economist OLD'!I57 -> Interscroller | G56: Economist_EMEATier2_Audience_Display_Interscroller | H56: Economist_EMEATier2_Audience | I56: ='Economist OLD'!S57+P56 -> 5265.4286 | J56: ='Economist OLD'!M57 -> 125606.6 | K56: ='Economist OLD'!Q57 -> 41.92 | L56: ='Economist OLD'!AW57 -> 376.81979 | M56: ='Economist OLD'!AV57 -> 0.003 | N56: 0.75 | O56: ='Economist OLD'!AS57 -> 279500 | P56: 0 | Q56: ='Economist OLD'!U57 -> 538.55114 | R56: ='Economist OLD'!V57 -> 538.55114 | S56: ='Economist OLD'!W57 -> 538.55114 | T56: ='Economist OLD'!X57 -> 538.55114 | U56: ='Economist OLD'!Y57 -> 538.55114 | V56: ='Economist OLD'!Z57 -> 538.55114 | W56: ='Economist OLD'!AA57 -> 444.59569 | X56: ='Economist OLD'!AB57 -> 538.55114 | ... AA56: ='Economist OLD'!AE57 -> 302.94856 | AB56: 0 | AC56: ='Economist OLD'!AG57 -> 12847.117 | AD56: ='Economist OLD'!AH57 -> 12847.117 | AE56: ='Economist OLD'!AI57 -> 12847.117 | AF56: ='Economist OLD'!AJ57 -> 12847.117 | AG56: ='Economist OLD'!AK57 -> 12847.117 | AH56: ='Economist OLD'!AL57 -> 12847.117 | AI56: ='Economist OLD'!AM57 -> 10605.813 | AJ56: ='Economist OLD'!AN57 -> 12847.117 | ... AM56: ='Economist OLD'!AQ57 -> 7226.8262 | AN56: 0 | AO56: =L56/11 -> 34.256345 | AP56: =AO56 -> 34.256345 | AQ56: =AP56 -> 34.256345 | AR56: =AQ56 -> 34.256345 | AS56: =AR56 -> 34.256345 | AT56: =AS56 -> 34.256345 | AU56: =AT56 -> 34.256345 | AV56: =AU56 -> 34.256345 | AW56: =AV56 -> 34.256345 | ... AY56: =AX56 -> 34.256345
D57: ='Economist OLD'!F58 -> C0Level + ESG articles and content | E57: Audience+Contextual | F57: ResponsiveBillboard | G57: Economist_EMEATier2_Audience+Contextual_Display_ResponsiveBillboard | H57: Economist_EMEATier2_Audience+Contextual | I57: ='Economist OLD'!S58+P57 -> 2585.7143 | J57: ='Economist OLD'!M58 -> 58302.464 | K57: ='Economist OLD'!Q58 -> 44.35 | L57: ='Economist OLD'!AW58 -> 40.811725 | M57: ='Economist OLD'!AV58 -> 0.0007 | N57: 0.75 | O57: ='Economist OLD'!AS58 -> 1060000 | P57: 0 | Q57: ='Economist OLD'!U58 -> 264.46838 | R57: ='Economist OLD'!V58 -> 264.46838 | S57: ='Economist OLD'!W58 -> 264.46838 | T57: ='Economist OLD'!X58 -> 264.46838 | U57: ='Economist OLD'!Y58 -> 264.46838 | V57: ='Economist OLD'!Z58 -> 264.46838 | W57: ='Economist OLD'!AA58 -> 218.32932 | X57: ='Economist OLD'!AB58 -> 264.46838 | ... AA57: ='Economist OLD'!AE58 -> 148.77011 | AB57: 0 | AC57: ='Economist OLD'!AG58 -> 5963.2104 | AD57: ='Economist OLD'!AH58 -> 5963.2104 | AE57: ='Economist OLD'!AI58 -> 5963.2104 | AF57: ='Economist OLD'!AJ58 -> 5963.2104 | AG57: ='Economist OLD'!AK58 -> 5963.2104 | AH57: ='Economist OLD'!AL58 -> 5963.2104 | AI57: ='Economist OLD'!AM58 -> 4922.8707 | AJ57: ='Economist OLD'!AN58 -> 5963.2104 | ... AM57: ='Economist OLD'!AQ58 -> 3354.4558 | AN57: 0 | AO57: =L57/11 -> 3.7101568 | AP57: =AO57 -> 3.7101568 | AQ57: =AP57 -> 3.7101568 | AR57: =AQ57 -> 3.7101568 | AS57: =AR57 -> 3.7101568 | AT57: =AS57 -> 3.7101568 | AU57: =AT57 -> 3.7101568 | AV57: =AU57 -> 3.7101568 | AW57: =AV57 -> 3.7101568 | ... AY57: =AX57 -> 3.7101568
D58: ='Economist OLD'!F59 -> C0Level + ESG articles and content | E58: Audience+Contextual | F58: ='Economist OLD'!I59 -> 300x600 | G58: Economist_EMEATier2_Audience+Contextual_Display_300x600 | H58: Economist_EMEATier2_Audience+Contextual | I58: ='Economist OLD'!S59+P58 -> 1165.7143 | J58: ='Economist OLD'!M59 -> 30757.633 | K58: ='Economist OLD'!Q59 -> 37.9 | L58: ='Economist OLD'!AW59 -> 15.378816 | M58: ='Economist OLD'!AV59 -> 0.0005 | N58: 0.75 | O58: ='Economist OLD'!AS59 -> 1060000 | P58: 0 | Q58: ='Economist OLD'!U59 -> 119.22995 | R58: ='Economist OLD'!V59 -> 119.22995 | S58: ='Economist OLD'!W59 -> 119.22995 | T58: ='Economist OLD'!X59 -> 119.22995 | U58: ='Economist OLD'!Y59 -> 119.22995 | V58: ='Economist OLD'!Z59 -> 119.22995 | W58: ='Economist OLD'!AA59 -> 98.429128 | X58: ='Economist OLD'!AB59 -> 119.22995 | ... AA58: ='Economist OLD'!AE59 -> 67.069841 | AB58: 0 | AC58: ='Economist OLD'!AG59 -> 3145.9088 | AD58: ='Economist OLD'!AH59 -> 3145.9088 | AE58: ='Economist OLD'!AI59 -> 3145.9088 | AF58: ='Economist OLD'!AJ59 -> 3145.9088 | AG58: ='Economist OLD'!AK59 -> 3145.9088 | AH58: ='Economist OLD'!AL59 -> 3145.9088 | AI58: ='Economist OLD'!AM59 -> 2597.0746 | AJ58: ='Economist OLD'!AN59 -> 3145.9088 | ... AM58: ='Economist OLD'!AQ59 -> 1769.6528 | AN58: 0 | AO58: =L58/11 -> 1.3980742 | AP58: =AO58 -> 1.3980742 | AQ58: =AP58 -> 1.3980742 | AR58: =AQ58 -> 1.3980742 | AS58: =AR58 -> 1.3980742 | AT58: =AS58 -> 1.3980742 | AU58: =AT58 -> 1.3980742 | AV58: =AU58 -> 1.3980742 | AW58: =AV58 -> 1.3980742 | ... AY58: =AX58 -> 1.3980742
D59: ='Economist OLD'!F60 -> C0Level + ESG articles and content | E59: Audience+Contextual | F59: ='Economist OLD'!I60 -> Interscroller | G59: Economist_EMEATier2_Audience+Contextual_Display_Interscroller | H59: Economist_EMEATier2_Audience+Contextual | I59: ='Economist OLD'!S60+P59 -> 2585.7143 | J59: ='Economist OLD'!M60 -> 66224.651 | K59: ='Economist OLD'!Q60 -> 37.9 | L59: ='Economist OLD'!AW60 -> 198.67395 | M59: ='Economist OLD'!AV60 -> 0.003 | N59: 0.75 | O59: ='Economist OLD'!AS60 -> 1060000 | P59: 75.8 | Q59: ='Economist OLD'!U60 -> 256.71551 | R59: ='Economist OLD'!V60 -> 256.71551 | S59: ='Economist OLD'!W60 -> 256.71551 | T59: ='Economist OLD'!X60 -> 256.71551 | U59: ='Economist OLD'!Y60 -> 256.71551 | V59: ='Economist OLD'!Z60 -> 256.71551 | W59: ='Economist OLD'!AA60 -> 211.92901 | X59: ='Economist OLD'!AB60 -> 256.71551 | ... AA59: ='Economist OLD'!AE60 -> 144.40893 | AB59: 2000 | AC59: ='Economist OLD'!AG60 -> 6773.4964 | AD59: ='Economist OLD'!AH60 -> 6773.4964 | AE59: ='Economist OLD'!AI60 -> 6773.4964 | AF59: ='Economist OLD'!AJ60 -> 6773.4964 | AG59: ='Economist OLD'!AK60 -> 6773.4964 | AH59: ='Economist OLD'!AL60 -> 6773.4964 | AI59: ='Economist OLD'!AM60 -> 5591.7945 | AJ59: ='Economist OLD'!AN60 -> 6773.4964 | ... AM59: ='Economist OLD'!AQ60 -> 3810.262 | AN59: 6 | AO59: =L59/11 -> 18.061269 | AP59: =AO59 -> 18.061269 | AQ59: =AP59 -> 18.061269 | AR59: =AQ59 -> 18.061269 | AS59: =AR59 -> 18.061269 | AT59: =AS59 -> 18.061269 | AU59: =AT59 -> 18.061269 | AV59: =AU59 -> 18.061269 | AW59: =AV59 -> 18.061269 | ... AY59: =AX59 -> 18.061269
D60: ='Economist OLD'!F61 -> Economist Subscribers | E60: Subscribers | F60: ResponsiveBillboard | G60: Economist_EMEATier2_Subscribers_Display_ResponsiveBillboard | H60: Economist_EMEATier2_Subscribers | I60: ='Economist OLD'!S61+P60 -> 8336.8531 | J60: ='Economist OLD'!M61 -> 167824.57 | K60: ='Economist OLD'!Q61 -> 49.676 | L60: ='Economist OLD'!AW61 -> 117.4772 | M60: ='Economist OLD'!AV61 -> 0.0007 | N60: 0.75 | O60: ='Economist OLD'!AS61 -> 155000 | P60: 0 | Q60: ='Economist OLD'!U61 -> 852.69826 | R60: ='Economist OLD'!V61 -> 852.69826 | S60: ='Economist OLD'!W61 -> 852.69826 | T60: ='Economist OLD'!X61 -> 852.69826 | U60: ='Economist OLD'!Y61 -> 852.69826 | V60: ='Economist OLD'!Z61 -> 852.69826 | W60: ='Economist OLD'!AA61 -> 703.9368 | X60: ='Economist OLD'!AB61 -> 852.69826 | ... AA60: ='Economist OLD'!AE61 -> 479.6642 | AB60: 0 | AC60: ='Economist OLD'!AG61 -> 17165.196 | AD60: ='Economist OLD'!AH61 -> 17165.196 | AE60: ='Economist OLD'!AI61 -> 17165.196 | AF60: ='Economist OLD'!AJ61 -> 17165.196 | AG60: ='Economist OLD'!AK61 -> 17165.196 | AH60: ='Economist OLD'!AL61 -> 17165.196 | AI60: ='Economist OLD'!AM61 -> 14170.561 | AJ60: ='Economist OLD'!AN61 -> 17165.196 | ... AM60: ='Economist OLD'!AQ61 -> 9655.854 | AN60: 0 | AO60: =L60/11 -> 10.679745 | AP60: =AO60 -> 10.679745 | AQ60: =AP60 -> 10.679745 | AR60: =AQ60 -> 10.679745 | AS60: =AR60 -> 10.679745 | AT60: =AS60 -> 10.679745 | AU60: =AT60 -> 10.679745 | AV60: =AU60 -> 10.679745 | AW60: =AV60 -> 10.679745 | ... AY60: =AX60 -> 10.679745
D61: ='Economist OLD'!F62 -> Economist Subscribers | E61: Subscribers | F61: ='Economist OLD'!I62 -> 300x600 | G61: Economist_EMEATier2_Subscribers_Display_300x600 | H61: Economist_EMEATier2_Subscribers | I61: ='Economist OLD'!S62+P61 -> 7975.67 | J61: ='Economist OLD'!M62 -> 187259.3 | K61: ='Economist OLD'!Q62 -> 41.92 | L61: ='Economist OLD'!AW62 -> 93.629652 | M61: ='Economist OLD'!AV62 -> 0.0005 | N61: 0.75 | O61: ='Economist OLD'!AS62 -> 155000 | P61: 125.76 | Q61: ='Economist OLD'!U62 -> 802.89343 | R61: ='Economist OLD'!V62 -> 802.89343 | S61: ='Economist OLD'!W62 -> 802.89343 | T61: ='Economist OLD'!X62 -> 802.89343 | U61: ='Economist OLD'!Y62 -> 802.89343 | V61: ='Economist OLD'!Z62 -> 802.89343 | W61: ='Economist OLD'!AA62 -> 662.8209 | X61: ='Economist OLD'!AB62 -> 802.89343 | ... AA61: ='Economist OLD'!AE62 -> 451.64774 | AB61: 3000 | AC61: ='Economist OLD'!AG62 -> 19152.992 | AD61: ='Economist OLD'!AH62 -> 19152.992 | AE61: ='Economist OLD'!AI62 -> 19152.992 | AF61: ='Economist OLD'!AJ62 -> 19152.992 | AG61: ='Economist OLD'!AK62 -> 19152.992 | AH61: ='Economist OLD'!AL62 -> 19152.992 | AI61: ='Economist OLD'!AM62 -> 15811.567 | AJ61: ='Economist OLD'!AN62 -> 19152.992 | ... AM61: ='Economist OLD'!AQ62 -> 10774.04 | AN61: 2 | AO61: =L61/11 -> 8.5117865 | AP61: =AO61 -> 8.5117865 | AQ61: =AP61 -> 8.5117865 | AR61: =AQ61 -> 8.5117865 | AS61: =AR61 -> 8.5117865 | AT61: =AS61 -> 8.5117865 | AU61: =AT61 -> 8.5117865 | AV61: =AU61 -> 8.5117865 | AW61: =AV61 -> 8.5117865 | ... AY61: =AX61 -> 8.5117865
D62: ='Economist OLD'!F63 -> Economist Subscribers | E62: Subscribers | F62: ='Economist OLD'!I63 -> Interscroller | G62: Economist_EMEATier2_Subscribers_Display_Interscroller | H62: Economist_EMEATier2_Subscribers | I62: ='Economist OLD'!S63+P62 -> 8058.0016 | J62: ='Economist OLD'!M63 -> 188223.32 | K62: ='Economist OLD'!Q63 -> 41.92 | L62: ='Economist OLD'!AW63 -> 564.66996 | M62: ='Economist OLD'!AV63 -> 0.003 | N62: 0.75 | O62: ='Economist OLD'!AS63 -> 155000 | P62: 167.68 | Q62: ='Economist OLD'!U63 -> 807.02675 | R62: ='Economist OLD'!V63 -> 807.02675 | S62: ='Economist OLD'!W63 -> 807.02675 | T62: ='Economist OLD'!X63 -> 807.02675 | U62: ='Economist OLD'!Y63 -> 807.02675 | V62: ='Economist OLD'!Z63 -> 807.02675 | W62: ='Economist OLD'!AA63 -> 666.23313 | X62: ='Economist OLD'!AB63 -> 807.02675 | ... AA62: ='Economist OLD'!AE63 -> 453.97284 | AB62: 4000 | AC62: ='Economist OLD'!AG63 -> 19251.592 | AD62: ='Economist OLD'!AH63 -> 19251.592 | AE62: ='Economist OLD'!AI63 -> 19251.592 | AF62: ='Economist OLD'!AJ63 -> 19251.592 | AG62: ='Economist OLD'!AK63 -> 19251.592 | AH62: ='Economist OLD'!AL63 -> 19251.592 | AI62: ='Economist OLD'!AM63 -> 15892.966 | AJ62: ='Economist OLD'!AN63 -> 19251.592 | ... AM62: ='Economist OLD'!AQ63 -> 10829.505 | AN62: 12 | AO62: =L62/11 -> 51.333633 | AP62: =AO62 -> 51.333633 | AQ62: =AP62 -> 51.333633 | AR62: =AQ62 -> 51.333633 | AS62: =AR62 -> 51.333633 | AT62: =AS62 -> 51.333633 | AU62: =AT62 -> 51.333633 | AV62: =AU62 -> 51.333633 | AW62: =AV62 -> 51.333633 | ... AY62: =AX62 -> 51.333633
D63: ='Economist OLD'!F64 -> Economist Subscribers | E63: Subscribers | F63: ='Economist OLD'!I64 -> 300x250 | G63: Economist_EMEATier2_Subscribers_Display_300x250 | H63: Economist_EMEATier2_Subscribers | I63: ='Economist OLD'!S64+P63 -> 7391.7898 | J63: ='Economist OLD'!M64 -> 34027.163 | K63: ='Economist OLD'!Q64 -> 60 | L63: ='Economist OLD'!AW64 -> 23.819014 | M63: ='Economist OLD'!AV64 -> 0.0007 | N63: 0.75 | O63: ='Economist OLD'!AS64 -> 155000 | P63: 5350.16 | Q63: ='Economist OLD'!U64 -> 208.8191 | R63: ='Economist OLD'!V64 -> 208.8191 | S63: ='Economist OLD'!W64 -> 208.8191 | T63: ='Economist OLD'!X64 -> 208.8191 | U63: ='Economist OLD'!Y64 -> 208.8191 | V63: ='Economist OLD'!Z64 -> 208.8191 | W63: ='Economist OLD'!AA64 -> 172.38859 | X63: ='Economist OLD'!AB64 -> 208.8191 | ... AA63: ='Economist OLD'!AE64 -> 117.46599 | AB63: 89169 | AC63: ='Economist OLD'!AG64 -> 3480.3184 | AD63: ='Economist OLD'!AH64 -> 3480.3184 | AE63: ='Economist OLD'!AI64 -> 3480.3184 | AF63: ='Economist OLD'!AJ64 -> 3480.3184 | AG63: ='Economist OLD'!AK64 -> 3480.3184 | AH63: ='Economist OLD'!AL64 -> 3480.3184 | AI63: ='Economist OLD'!AM64 -> 2873.1432 | AJ63: ='Economist OLD'!AN64 -> 3480.3184 | ... AM63: ='Economist OLD'!AQ64 -> 1957.7666 | AN63: 62 | AO63: =L63/11 -> 2.1653649 | AP63: =AO63 -> 2.1653649 | AQ63: =AP63 -> 2.1653649 | AR63: =AQ63 -> 2.1653649 | AS63: =AR63 -> 2.1653649 | AT63: =AS63 -> 2.1653649 | AU63: =AT63 -> 2.1653649 | AV63: =AU63 -> 2.1653649 | AW63: =AV63 -> 2.1653649 | ... AY63: =AX63 -> 2.1653649
D64: ='Economist OLD'!F65 -> Economist Subscribers | E64: Subscribers | F64: ='Economist OLD'!I65 -> App Interscroller | G64: Economist_EMEATier2_Subscribers_Display_appInterscroller | H64: Economist_EMEATier2_Subscribers | I64: ='Economist OLD'!S65+P64 -> 10890 | J64: ='Economist OLD'!M65 -> 108900 | K64: ='Economist OLD'!Q65 -> 100 | L64: ='Economist OLD'!AW65 -> 0 | M64: ='Economist OLD'!AV65 -> 0 | N64: 0.75 | O64: ='Economist OLD'!AS65 -> 155000 | P64: 0 | Q64: ='Economist OLD'!U65 -> 990 | R64: ='Economist OLD'!V65 -> 990 | S64: ='Economist OLD'!W65 -> 990 | T64: ='Economist OLD'!X65 -> 990 | U64: ='Economist OLD'!Y65 -> 990 | V64: ='Economist OLD'!Z65 -> 0 | W64: ='Economist OLD'!AA65 -> 1980 | X64: ='Economist OLD'!AB65 -> 990 | ... AA64: ='Economist OLD'!AE65 -> 990 | AB64: 0 | AC64: ='Economist OLD'!AG65 -> 9900 | AD64: ='Economist OLD'!AH65 -> 9900 | AE64: ='Economist OLD'!AI65 -> 9900 | AF64: ='Economist OLD'!AJ65 -> 9900 | AG64: ='Economist OLD'!AK65 -> 9900 | AH64: ='Economist OLD'!AL65 -> 0 | AI64: ='Economist OLD'!AM65 -> 19800 | AJ64: ='Economist OLD'!AN65 -> 9900 | ... AM64: ='Economist OLD'!AQ65 -> 9900 | AN64: 0 | AO64: 0 | AP64: 0 | AQ64: 0 | AR64: 0 | AS64: 0 | AT64: 0 | AU64: 0 | AV64: 0 | AW64: 0 | AX64: 0 | AY64: 0
D65: ='Economist OLD'!F66 -> Science & Technology (COP) | E65: Takeover | F65: Takeover | I65: ='Economist OLD'!S66+P65 -> 411.25 | J65: ='Economist OLD'!M66 -> 6500 | K65: ='Economist OLD'!Q66 -> 411.25 | L65: ='Economist OLD'!AW66 -> 4.55 | M65: ='Economist OLD'!AV66 -> 0.0007 | N65: 0.75 | O65: ='Economist OLD'!AS66 -> 445000 | P65: 0 | Q65: ='Economist OLD'!U66 -> 0 | R65: ='Economist OLD'!V66 -> 0 | S65: ='Economist OLD'!W66 -> 0 | T65: ='Economist OLD'!X66 -> 0 | U65: ='Economist OLD'!Y66 -> 0 | V65: ='Economist OLD'!Z66 -> 0 | W65: ='Economist OLD'!AA66 -> 411.25 | X65: ='Economist OLD'!AB66 -> 0 | ... AA65: ='Economist OLD'!AE66 -> 0 | AB65: 0 | AC65: ='Economist OLD'!AG66 -> 0 | AD65: ='Economist OLD'!AH66 -> 0 | AE65: ='Economist OLD'!AI66 -> 0 | AF65: ='Economist OLD'!AJ66 -> 0 | AG65: ='Economist OLD'!AK66 -> 0 | AH65: ='Economist OLD'!AL66 -> 0 | AI65: ='Economist OLD'!AM66 -> 6500 | AJ65: ='Economist OLD'!AN66 -> 0 | ... AM65: ='Economist OLD'!AQ66 -> 0 | AN65: 0 | AO65: 0 | AP65: =AO65 -> 0 | AQ65: =AP65 -> 0 | AR65: =AQ65 -> 0 | AS65: =AR65 -> 0 | AT65: =AS65 -> 0 | AU65: =L65 -> 4.55 | AV65: 0 | AW65: =AV65 -> 0 | AX65: =AW65 -> 0 | AY65: =AX65 -> 0
D66: ='Economist OLD'!F67 -> Science & Technology (COP) | E66: Takeover | F66: Takeover | I66: ='Economist OLD'!S67+P66 -> 411.25 | J66: ='Economist OLD'!M67 -> 6500 | K66: ='Economist OLD'!Q67 -> 411.25 | L66: ='Economist OLD'!AW67 -> 4.55 | M66: ='Economist OLD'!AV67 -> 0.0007 | N66: 0.75 | O66: ='Economist OLD'!AS67 -> 445000 | P66: 0 | Q66: ='Economist OLD'!U67 -> 0 | R66: ='Economist OLD'!V67 -> 0 | S66: ='Economist OLD'!W67 -> 0 | T66: ='Economist OLD'!X67 -> 0 | U66: ='Economist OLD'!Y67 -> 0 | V66: ='Economist OLD'!Z67 -> 0 | W66: ='Economist OLD'!AA67 -> 411.25 | X66: ='Economist OLD'!AB67 -> 0 | ... AA66: ='Economist OLD'!AE67 -> 0 | AB66: 0 | AC66: ='Economist OLD'!AG67 -> 0 | AD66: ='Economist OLD'!AH67 -> 0 | AE66: ='Economist OLD'!AI67 -> 0 | AF66: ='Economist OLD'!AJ67 -> 0 | AG66: ='Economist OLD'!AK67 -> 0 | AH66: ='Economist OLD'!AL67 -> 0 | AI66: ='Economist OLD'!AM67 -> 6500 | AJ66: ='Economist OLD'!AN67 -> 0 | ... AM66: ='Economist OLD'!AQ67 -> 0 | AN66: 0 | AO66: 0 | AP66: =AO66 -> 0 | AQ66: =AP66 -> 0 | AR66: =AQ66 -> 0 | AS66: =AR66 -> 0 | AT66: =AS66 -> 0 | AU66: =L66 -> 4.55 | AV66: 0 | AW66: =AV66 -> 0 | AX66: =AW66 -> 0 | AY66: =AX66 -> 0
D67: ='Economist OLD'!F68 -> Science & Technology (COP) | E67: Takeover | F67: Takeover | I67: ='Economist OLD'!S68+P67 -> 411.25 | J67: ='Economist OLD'!M68 -> 6500 | K67: ='Economist OLD'!Q68 -> 411.25 | L67: ='Economist OLD'!AW68 -> 4.55 | M67: ='Economist OLD'!AV68 -> 0.0007 | N67: 0.75 | O67: ='Economist OLD'!AS68 -> 445000 | P67: 0 | Q67: ='Economist OLD'!U68 -> 0 | R67: ='Economist OLD'!V68 -> 0 | S67: ='Economist OLD'!W68 -> 0 | T67: ='Economist OLD'!X68 -> 0 | U67: ='Economist OLD'!Y68 -> 0 | V67: ='Economist OLD'!Z68 -> 0 | W67: ='Economist OLD'!AA68 -> 0 | X67: ='Economist OLD'!AB68 -> 0 | ... AA67: ='Economist OLD'!AE68 -> 0 | AB67: 0 | AC67: ='Economist OLD'!AG68 -> 0 | AD67: ='Economist OLD'!AH68 -> 0 | AE67: ='Economist OLD'!AI68 -> 0 | AF67: ='Economist OLD'!AJ68 -> 0 | AG67: ='Economist OLD'!AK68 -> 0 | AH67: ='Economist OLD'!AL68 -> 0 | AI67: ='Economist OLD'!AM68 -> 0 | AJ67: ='Economist OLD'!AN68 -> 0 | ... AM67: ='Economist OLD'!AQ68 -> 0 | AN67: 0 | AO67: 0 | AP67: =AO67 -> 0 | AQ67: =AP67 -> 0 | AR67: =AQ67 -> 0 | AS67: =AR67 -> 0 | AT67: =AS67 -> 0 | AU67: =AT67 -> 0 | AV67: =AU67 -> 0 | AW67: =L67 -> 4.55 | AX67: 0 | AY67: =AX67 -> 0
D68: ='Economist OLD'!F69 -> Business & Finance (Davos) | E68: Takeover | F68: Takeover | I68: ='Economist OLD'!S69+P68 -> 2062.5 | J68: ='Economist OLD'!M69 -> 33000 | K68: ='Economist OLD'!Q69 -> 2062.5 | L68: ='Economist OLD'!AW69 -> 23.1 | M68: ='Economist OLD'!AV69 -> 0.0007 | N68: 0.75 | O68: ='Economist OLD'!AS69 -> 445000 | P68: 0 | Q68: ='Economist OLD'!U69 -> 0 | R68: ='Economist OLD'!V69 -> 0 | S68: ='Economist OLD'!W69 -> 0 | T68: ='Economist OLD'!X69 -> 0 | U68: ='Economist OLD'!Y69 -> 0 | V68: ='Economist OLD'!Z69 -> 0 | W68: ='Economist OLD'!AA69 -> 0 | X68: ='Economist OLD'!AB69 -> 0 | ... AA68: ='Economist OLD'!AE69 -> 2062.5 | AB68: 0 | AC68: ='Economist OLD'!AG69 -> 0 | AD68: ='Economist OLD'!AH69 -> 0 | AE68: ='Economist OLD'!AI69 -> 0 | AF68: ='Economist OLD'!AJ69 -> 0 | AG68: ='Economist OLD'!AK69 -> 0 | AH68: ='Economist OLD'!AL69 -> 0 | AI68: ='Economist OLD'!AM69 -> 0 | AJ68: ='Economist OLD'!AN69 -> 0 | ... AM68: ='Economist OLD'!AQ69 -> 33000 | AN68: 0 | AO68: 0 | AP68: =AO68 -> 0 | AQ68: =AP68 -> 0 | AR68: =AQ68 -> 0 | AS68: =AR68 -> 0 | AT68: =AS68 -> 0 | AU68: =AT68 -> 0 | AV68: =AU68 -> 0 | AW68: =AV68 -> 0 | AX68: =AW68 -> 0 | AY68: =L68 -> 23.1
C69: TOTAL | D69: ='Economist OLD'!F70 | F69: ='Economist OLD'!I70 | I69: =SUM(I54:I68) -> 65999.993 | J69: =SUM(J54:J68) -> 1202785.5 | K69: ='Economist OLD'!Q70 | L69: =SUM(L54:L68) -> 1579.4862
C70: ='Economist OLD'!B70 -> LATAM | D70: ='Economist OLD'!F71 -> C0Level + Custom audience targeting companies 5,000+ | E70: Audience | F70: ResponsiveBillboard | G70: Economist_LATAM_Audience_Display_ResponsiveBillboard | H70: Economist_LATAM_Audience | I70: ='Economist OLD'!S71+P70 -> 2057.0239 | J70: ='Economist OLD'!M71 -> 41408.806 | K70: ='Economist OLD'!Q71 -> 49.676 | L70: ='Economist OLD'!AW71 -> 28.986164 | M70: ='Economist OLD'!AV71 -> 0.0007 | N70: 0.75 | O70: ='Economist OLD'!AS71 -> 42000 | P70: 0 | Q70: ='Economist OLD'!U71 -> 210.09803 | R70: ='Economist OLD'!V71 -> 210.09803 | S70: ='Economist OLD'!W71 -> 210.09803 | T70: ='Economist OLD'!X71 -> 210.09803 | U70: ='Economist OLD'!Y71 -> 210.09803 | V70: ='Economist OLD'!Z71 -> 210.09803 | W70: ='Economist OLD'!AA71 -> 168.66614 | X70: ='Economist OLD'!AB71 -> 210.09803 | ... AA70: ='Economist OLD'!AE71 -> 128.24271 | AB70: 0 | AC70: ='Economist OLD'!AG71 -> 4229.367 | AD70: ='Economist OLD'!AH71 -> 4229.367 | AE70: ='Economist OLD'!AI71 -> 4229.367 | AF70: ='Economist OLD'!AJ71 -> 4229.367 | AG70: ='Economist OLD'!AK71 -> 4229.367 | AH70: ='Economist OLD'!AL71 -> 4229.367 | AI70: ='Economist OLD'!AM71 -> 3395.3246 | AJ70: ='Economist OLD'!AN71 -> 4229.367 | ... AM70: ='Economist OLD'!AQ71 -> 2581.5829 | AN70: 0 | AO70: =L70/11 -> 2.6351059 | AP70: =AO70 -> 2.6351059 | AQ70: =AP70 -> 2.6351059 | AR70: =AQ70 -> 2.6351059 | AS70: =AR70 -> 2.6351059 | AT70: =AS70 -> 2.6351059 | AU70: =AT70 -> 2.6351059 | AV70: =AU70 -> 2.6351059 | AW70: =AV70 -> 2.6351059 | ... AY70: =AX70 -> 2.6351059
D71: ='Economist OLD'!F72 -> C0Level + Custom audience targeting companies 5,000+ | E71: Audience | F71: ='Economist OLD'!I72 -> 300x600 | G71: Economist_LATAM_Audience_Display_300x600 | H71: Economist_LATAM_Audience | I71: ='Economist OLD'!S72+P71 -> 1463.3373 | J71: ='Economist OLD'!M72 -> 32107.761 | K71: ='Economist OLD'!Q72 -> 41.92 | L71: ='Economist OLD'!AW72 -> 16.05388 | M71: ='Economist OLD'!AV72 -> 0.0005 | N71: 0.75 | O71: ='Economist OLD'!AS72 -> 42000 | P71: 117.38 | Q71: ='Economist OLD'!U72 -> 137.47191 | R71: ='Economist OLD'!V72 -> 137.47191 | S71: ='Economist OLD'!W72 -> 137.47191 | T71: ='Economist OLD'!X72 -> 137.47191 | U71: ='Economist OLD'!Y72 -> 137.47191 | V71: ='Economist OLD'!Z72 -> 137.47191 | W71: ='Economist OLD'!AA72 -> 110.36208 | X71: ='Economist OLD'!AB72 -> 137.47191 | ... AA71: ='Economist OLD'!AE72 -> 83.912113 | AB71: 2800 | AC71: ='Economist OLD'!AG72 -> 3279.387 | AD71: ='Economist OLD'!AH72 -> 3279.387 | AE71: ='Economist OLD'!AI72 -> 3279.387 | AF71: ='Economist OLD'!AJ72 -> 3279.387 | AG71: ='Economist OLD'!AK72 -> 3279.387 | AH71: ='Economist OLD'!AL72 -> 3279.387 | AI71: ='Economist OLD'!AM72 -> 2632.6832 | AJ71: ='Economist OLD'!AN72 -> 3279.387 | ... AM71: ='Economist OLD'!AQ72 -> 2001.7202 | AN71: 1 | AO71: =L71/11 -> 1.4594437 | AP71: =AO71 -> 1.4594437 | AQ71: =AP71 -> 1.4594437 | AR71: =AQ71 -> 1.4594437 | AS71: =AR71 -> 1.4594437 | AT71: =AS71 -> 1.4594437 | AU71: =AT71 -> 1.4594437 | AV71: =AU71 -> 1.4594437 | AW71: =AV71 -> 1.4594437 | ... AY71: =AX71 -> 1.4594437
D72: ='Economist OLD'!F73 -> C0Level + Custom audience targeting companies 5,000+ | E72: Audience | F72: ='Economist OLD'!I73 -> Interscroller | G72: Economist_LATAM_Audience_Display_Interscroller | H72: Economist_LATAM_Audience | I72: ='Economist OLD'!S73+P72 -> 2193.9286 | J72: ='Economist OLD'!M73 -> 51336.082 | K72: ='Economist OLD'!Q73 -> 41.92 | L72: ='Economist OLD'!AW73 -> 154.00825 | M72: ='Economist OLD'!AV73 -> 0.003 | N72: 0.75 | O72: ='Economist OLD'!AS73 -> 42000 | P72: 41.92 | Q72: ='Economist OLD'!U73 -> 219.79948 | R72: ='Economist OLD'!V73 -> 219.79948 | S72: ='Economist OLD'!W73 -> 219.79948 | T72: ='Economist OLD'!X73 -> 219.79948 | U72: ='Economist OLD'!Y73 -> 219.79948 | V72: ='Economist OLD'!Z73 -> 219.79948 | W72: ='Economist OLD'!AA73 -> 176.45444 | X72: ='Economist OLD'!AB73 -> 219.79948 | ... AA72: ='Economist OLD'!AE73 -> 134.16442 | AB72: 1000 | AC72: ='Economist OLD'!AG73 -> 5243.3081 | AD72: ='Economist OLD'!AH73 -> 5243.3081 | AE72: ='Economist OLD'!AI73 -> 5243.3081 | AF72: ='Economist OLD'!AJ73 -> 5243.3081 | AG72: ='Economist OLD'!AK73 -> 5243.3081 | AH72: ='Economist OLD'!AL73 -> 5243.3081 | AI72: ='Economist OLD'!AM73 -> 4209.3139 | AJ72: ='Economist OLD'!AN73 -> 5243.3081 | ... AM72: ='Economist OLD'!AQ73 -> 3200.4871 | AN72: 3 | AO72: =L72/11 -> 14.00075 | AP72: =AO72 -> 14.00075 | AQ72: =AP72 -> 14.00075 | AR72: =AQ72 -> 14.00075 | AS72: =AR72 -> 14.00075 | AT72: =AS72 -> 14.00075 | AU72: =AT72 -> 14.00075 | AV72: =AU72 -> 14.00075 | AW72: =AV72 -> 14.00075 | ... AY72: =AX72 -> 14.00075
D73: ='Economist OLD'!F74 -> C0Level + ESG articles and content | E73: Audience+Contextual | F73: ResponsiveBillboard | G73: Economist_LATAM_Audience+Contextual_Display_ResponsiveBillboard | H73: Economist_LATAM_Audience+Contextual | I73: ='Economist OLD'!S74+P73 -> 1077.381 | J73: ='Economist OLD'!M74 -> 24292.693 | K73: ='Economist OLD'!Q74 -> 44.35 | L73: ='Economist OLD'!AW74 -> 17.004885 | M73: ='Economist OLD'!AV74 -> 0.0007 | N73: 0.75 | O73: ='Economist OLD'!AS74 -> 594000 | P73: 0 | Q73: ='Economist OLD'!U74 -> 110.04035 | R73: ='Economist OLD'!V74 -> 110.04035 | S73: ='Economist OLD'!W74 -> 110.04035 | T73: ='Economist OLD'!X74 -> 110.04035 | U73: ='Economist OLD'!Y74 -> 110.04035 | V73: ='Economist OLD'!Z74 -> 110.04035 | W73: ='Economist OLD'!AA74 -> 88.340098 | X73: ='Economist OLD'!AB74 -> 110.04035 | ... AA73: ='Economist OLD'!AE74 -> 67.168037 | AB73: 0 | AC73: ='Economist OLD'!AG74 -> 2481.1803 | AD73: ='Economist OLD'!AH74 -> 2481.1803 | AE73: ='Economist OLD'!AI74 -> 2481.1803 | AF73: ='Economist OLD'!AJ74 -> 2481.1803 | AG73: ='Economist OLD'!AK74 -> 2481.1803 | AH73: ='Economist OLD'!AL74 -> 2481.1803 | AI73: ='Economist OLD'!AM74 -> 1991.885 | AJ73: ='Economist OLD'!AN74 -> 2481.1803 | ... AM73: ='Economist OLD'!AQ74 -> 1514.4991 | AN73: 0 | AO73: =L73/11 -> 1.5458987 | AP73: =AO73 -> 1.5458987 | AQ73: =AP73 -> 1.5458987 | AR73: =AQ73 -> 1.5458987 | AS73: =AR73 -> 1.5458987 | AT73: =AS73 -> 1.5458987 | AU73: =AT73 -> 1.5458987 | AV73: =AU73 -> 1.5458987 | AW73: =AV73 -> 1.5458987 | ... AY73: =AX73 -> 1.5458987
D74: ='Economist OLD'!F75 -> C0Level + ESG articles and content | E74: Audience+Contextual | F74: ='Economist OLD'!I75 -> 300x600 | G74: Economist_LATAM_Audience+Contextual_Display_300x600 | H74: Economist_LATAM_Audience+Contextual | I74: ='Economist OLD'!S75+P74 -> 485.71634 | J74: ='Economist OLD'!M75 -> 8970.3521 | K74: ='Economist OLD'!Q75 -> 37.9 | L74: ='Economist OLD'!AW75 -> 4.485176 | M74: ='Economist OLD'!AV75 -> 0.0005 | N74: 0.75 | O74: ='Economist OLD'!AS75 -> 594000 | P74: 145.74 | Q74: ='Economist OLD'!U75 -> 34.724129 | R74: ='Economist OLD'!V75 -> 34.724129 | S74: ='Economist OLD'!W75 -> 34.724129 | T74: ='Economist OLD'!X75 -> 34.724129 | U74: ='Economist OLD'!Y75 -> 34.724129 | V74: ='Economist OLD'!Z75 -> 34.724129 | W74: ='Economist OLD'!AA75 -> 27.876438 | X74: ='Economist OLD'!AB75 -> 34.724129 | ... AA74: ='Economist OLD'!AE75 -> 21.195422 | AB74: 3845 | AC74: ='Economist OLD'!AG75 -> 916.20392 | AD74: ='Economist OLD'!AH75 -> 916.20392 | AE74: ='Economist OLD'!AI75 -> 916.20392 | AF74: ='Economist OLD'!AJ75 -> 916.20392 | AG74: ='Economist OLD'!AK75 -> 916.20392 | AH74: ='Economist OLD'!AL75 -> 916.20392 | AI74: ='Economist OLD'!AM75 -> 735.52608 | AJ74: ='Economist OLD'!AN75 -> 916.20392 | ... AM74: ='Economist OLD'!AQ75 -> 559.24595 | AN74: 2 | AO74: =L74/11 -> 0.40774328 | AP74: =AO74 -> 0.40774328 | AQ74: =AP74 -> 0.40774328 | AR74: =AQ74 -> 0.40774328 | AS74: =AR74 -> 0.40774328 | AT74: =AS74 -> 0.40774328 | AU74: =AT74 -> 0.40774328 | AV74: =AU74 -> 0.40774328 | AW74: =AV74 -> 0.40774328 | ... AY74: =AX74 -> 0.40774328
D75: ='Economist OLD'!F76 -> C0Level + ESG articles and content | E75: Audience+Contextual | F75: ='Economist OLD'!I76 -> Interscroller | G75: Economist_LATAM_Audience+Contextual_Display_Interscroller | H75: Economist_LATAM_Audience+Contextual | I75: ='Economist OLD'!S76+P75 -> 1077.3779 | J75: ='Economist OLD'!M76 -> 25750.077 | K75: ='Economist OLD'!Q76 -> 37.9 | L75: ='Economist OLD'!AW76 -> 77.250231 | M75: ='Economist OLD'!AV76 -> 0.003 | N75: 0.75 | O75: ='Economist OLD'!AS76 -> 594000 | P75: 101.45 | Q75: ='Economist OLD'!U76 -> 99.678249 | R75: ='Economist OLD'!V76 -> 99.678249 | S75: ='Economist OLD'!W76 -> 99.678249 | T75: ='Economist OLD'!X76 -> 99.678249 | U75: ='Economist OLD'!Y76 -> 99.678249 | V75: ='Economist OLD'!Z76 -> 99.678249 | W75: ='Economist OLD'!AA76 -> 80.021434 | X75: ='Economist OLD'!AB76 -> 99.678249 | ... AA75: ='Economist OLD'!AE76 -> 60.843068 | AB75: 2677 | AC75: ='Economist OLD'!AG76 -> 2630.033 | AD75: ='Economist OLD'!AH76 -> 2630.033 | AE75: ='Economist OLD'!AI76 -> 2630.033 | AF75: ='Economist OLD'!AJ76 -> 2630.033 | AG75: ='Economist OLD'!AK76 -> 2630.033 | AH75: ='Economist OLD'!AL76 -> 2630.033 | AI75: ='Economist OLD'!AM76 -> 2111.3835 | AJ75: ='Economist OLD'!AN76 -> 2630.033 | ... AM75: ='Economist OLD'!AQ76 -> 1605.358 | AN75: 8 | AO75: =L75/11 -> 7.0227483 | AP75: =AO75 -> 7.0227483 | AQ75: =AP75 -> 7.0227483 | AR75: =AQ75 -> 7.0227483 | AS75: =AR75 -> 7.0227483 | AT75: =AS75 -> 7.0227483 | AU75: =AT75 -> 7.0227483 | AV75: =AU75 -> 7.0227483 | AW75: =AV75 -> 7.0227483 | ... AY75: =AX75 -> 7.0227483
D76: ='Economist OLD'!F77 -> Economist Subscribers | E76: Subscribers | F76: ResponsiveBillboard | G76: Economist_LATAM_Subscribers_Display_ResponsiveBillboard | H76: Economist_LATAM_Subscribers | I76: ='Economist OLD'!S77+P76 -> 3422.5603 | J76: ='Economist OLD'!M77 -> 68897.662 | K76: ='Economist OLD'!Q77 -> 49.676 | L76: ='Economist OLD'!AW77 -> 48.228364 | M76: ='Economist OLD'!AV77 -> 0.0007 | N76: 0.75 | O76: ='Economist OLD'!AS77 -> 23000 | P76: 0 | Q76: ='Economist OLD'!U77 -> 349.56968 | R76: ='Economist OLD'!V77 -> 349.56968 | S76: ='Economist OLD'!W77 -> 349.56968 | T76: ='Economist OLD'!X77 -> 349.56968 | U76: ='Economist OLD'!Y77 -> 349.56968 | V76: ='Economist OLD'!Z77 -> 349.56968 | W76: ='Economist OLD'!AA77 -> 280.63361 | X76: ='Economist OLD'!AB77 -> 349.56968 | ... AA76: ='Economist OLD'!AE77 -> 213.37546 | AB76: 0 | AC76: ='Economist OLD'!AG77 -> 7036.9934 | AD76: ='Economist OLD'!AH77 -> 7036.9934 | AE76: ='Economist OLD'!AI77 -> 7036.9934 | AF76: ='Economist OLD'!AJ77 -> 7036.9934 | AG76: ='Economist OLD'!AK77 -> 7036.9934 | AH76: ='Economist OLD'!AL77 -> 7036.9934 | AI76: ='Economist OLD'!AM77 -> 5649.2796 | AJ76: ='Economist OLD'!AN77 -> 7036.9934 | ... AM76: ='Economist OLD'!AQ77 -> 4295.343 | AN76: 0 | AO76: =L76/11 -> 4.3843967 | AP76: =AO76 -> 4.3843967 | AQ76: =AP76 -> 4.3843967 | AR76: =AQ76 -> 4.3843967 | AS76: =AR76 -> 4.3843967 | AT76: =AS76 -> 4.3843967 | AU76: =AT76 -> 4.3843967 | AV76: =AU76 -> 4.3843967 | AW76: =AV76 -> 4.3843967 | ... AY76: =AX76 -> 4.3843967
D77: ='Economist OLD'!F78 -> Economist Subscribers | E77: Subscribers | F77: ='Economist OLD'!I78 -> 300x600 | G77: Economist_LATAM_Subscribers_Display_300x600 | H77: Economist_LATAM_Subscribers | I77: ='Economist OLD'!S78+P77 -> 3066.9688 | J77: ='Economist OLD'!M78 -> 65596.583 | K77: ='Economist OLD'!Q78 -> 41.92 | L77: ='Economist OLD'!AW78 -> 32.798291 | M77: ='Economist OLD'!AV78 -> 0.0005 | N77: 0.75 | O77: ='Economist OLD'!AS78 -> 23000 | P77: 317.16 | Q77: ='Economist OLD'!U78 -> 280.85693 | R77: ='Economist OLD'!V78 -> 280.85693 | S77: ='Economist OLD'!W78 -> 280.85693 | T77: ='Economist OLD'!X78 -> 280.85693 | U77: ='Economist OLD'!Y78 -> 280.85693 | V77: ='Economist OLD'!Z78 -> 280.85693 | W77: ='Economist OLD'!AA78 -> 225.4712 | X77: ='Economist OLD'!AB78 -> 280.85693 | ... AA77: ='Economist OLD'!AE78 -> 171.43356 | AB77: 7566 | AC77: ='Economist OLD'!AG78 -> 6699.8314 | AD77: ='Economist OLD'!AH78 -> 6699.8314 | AE77: ='Economist OLD'!AI78 -> 6699.8314 | AF77: ='Economist OLD'!AJ78 -> 6699.8314 | AG77: ='Economist OLD'!AK78 -> 6699.8314 | AH77: ='Economist OLD'!AL78 -> 6699.8314 | AI77: ='Economist OLD'!AM78 -> 5378.6069 | AJ77: ='Economist OLD'!AN78 -> 6699.8314 | ... AM77: ='Economist OLD'!AQ78 -> 4089.5411 | AN77: 4 | AO77: =L77/11 -> 2.9816629 | AP77: =AO77 -> 2.9816629 | AQ77: =AP77 -> 2.9816629 | AR77: =AQ77 -> 2.9816629 | AS77: =AR77 -> 2.9816629 | AT77: =AS77 -> 2.9816629 | AU77: =AT77 -> 2.9816629 | AV77: =AU77 -> 2.9816629 | AW77: =AV77 -> 2.9816629 | ... AY77: =AX77 -> 2.9816629
D78: ='Economist OLD'!F79 -> Economist Subscribers | E78: Subscribers | F78: ='Economist OLD'!I79 -> Interscroller | G78: Economist_LATAM_Subscribers_Display_Interscroller | H78: Economist_LATAM_Subscribers | I78: ='Economist OLD'!S79+P78 -> 3306.37 | J78: ='Economist OLD'!M79 -> 71373.33 | K78: ='Economist OLD'!Q79 -> 41.92 | L78: ='Economist OLD'!AW79 -> 214.11999 | M78: ='Economist OLD'!AV79 -> 0.003 | N78: 0.75 | O78: ='Economist OLD'!AS79 -> 23000 | P78: 314.4 | Q78: ='Economist OLD'!U79 -> 305.59053 | R78: ='Economist OLD'!V79 -> 305.59053 | S78: ='Economist OLD'!W79 -> 305.59053 | T78: ='Economist OLD'!X79 -> 305.59053 | U78: ='Economist OLD'!Y79 -> 305.59053 | V78: ='Economist OLD'!Z79 -> 305.59053 | W78: ='Economist OLD'!AA79 -> 245.32727 | X78: ='Economist OLD'!AB79 -> 305.59053 | ... AA78: ='Economist OLD'!AE79 -> 186.53082 | AB78: 7500 | AC78: ='Economist OLD'!AG79 -> 7289.8504 | AD78: ='Economist OLD'!AH79 -> 7289.8504 | AE78: ='Economist OLD'!AI79 -> 7289.8504 | AF78: ='Economist OLD'!AJ79 -> 7289.8504 | AG78: ='Economist OLD'!AK79 -> 7289.8504 | AH78: ='Economist OLD'!AL79 -> 7289.8504 | AI78: ='Economist OLD'!AM79 -> 5852.2726 | AJ78: ='Economist OLD'!AN79 -> 7289.8504 | ... AM78: ='Economist OLD'!AQ79 -> 4449.6856 | AN78: 23 | AO78: =L78/11 -> 19.465454 | AP78: =AO78 -> 19.465454 | AQ78: =AP78 -> 19.465454 | AR78: =AQ78 -> 19.465454 | AS78: =AR78 -> 19.465454 | AT78: =AS78 -> 19.465454 | AU78: =AT78 -> 19.465454 | AV78: =AU78 -> 19.465454 | AW78: =AV78 -> 19.465454 | ... AY78: =AX78 -> 19.465454
D79: ='Economist OLD'!F80 -> Economist Subscribers | E79: Subscribers | F79: ='Economist OLD'!I80 -> 300x250 | G79: Economist_LATAM_Subscribers_Display_300x250 | H79: Economist_LATAM_Subscribers | I79: ='Economist OLD'!S80+P79 -> 3079.9124 | J79: ='Economist OLD'!M80 -> 28914.707 | K79: ='Economist OLD'!Q80 -> 60 | L79: ='Economist OLD'!AW80 -> 20.240295 | M79: ='Economist OLD'!AV80 -> 0.0007 | N79: 0.75 | O79: ='Economist OLD'!AS80 -> 23000 | P79: 1345.03 | Q79: ='Economist OLD'!U80 -> 177.19551 | R79: ='Economist OLD'!V80 -> 177.19551 | S79: ='Economist OLD'!W80 -> 177.19551 | T79: ='Economist OLD'!X80 -> 177.19551 | U79: ='Economist OLD'!Y80 -> 177.19551 | V79: ='Economist OLD'!Z80 -> 177.19551 | W79: ='Economist OLD'!AA80 -> 142.25208 | X79: ='Economist OLD'!AB80 -> 177.19551 | ... AA79: ='Economist OLD'!AE80 -> 108.15919 | AB79: 22417 | AC79: ='Economist OLD'!AG80 -> 2953.2585 | AD79: ='Economist OLD'!AH80 -> 2953.2585 | AE79: ='Economist OLD'!AI80 -> 2953.2585 | AF79: ='Economist OLD'!AJ80 -> 2953.2585 | AG79: ='Economist OLD'!AK80 -> 2953.2585 | AH79: ='Economist OLD'!AL80 -> 2953.2585 | AI79: ='Economist OLD'!AM80 -> 2370.8681 | AJ79: ='Economist OLD'!AN80 -> 2953.2585 | ... AM79: ='Economist OLD'!AQ80 -> 1802.6531 | AN79: 16 | AO79: =L79/11 -> 1.8400268 | AP79: =AO79 -> 1.8400268 | AQ79: =AP79 -> 1.8400268 | AR79: =AQ79 -> 1.8400268 | AS79: =AR79 -> 1.8400268 | AT79: =AS79 -> 1.8400268 | AU79: =AT79 -> 1.8400268 | AV79: =AU79 -> 1.8400268 | AW79: =AV79 -> 1.8400268 | ... AY79: =AX79 -> 1.8400268
D80: ='Economist OLD'!F81 -> Economist Subscribers | E80: Subscribers | F80: ='Economist OLD'!I81 -> App Interscroller | G80: Economist_LATAM_Subscribers_Display_appInterscroller | H80: Economist_LATAM_Subscribers | I80: ='Economist OLD'!S81+P80 -> 4950 | J80: ='Economist OLD'!M81 -> 49500 | K80: ='Economist OLD'!Q81 -> 100 | L80: ='Economist OLD'!AW81 -> 0 | M80: ='Economist OLD'!AV81 -> 0 | N80: 0.75 | O80: ='Economist OLD'!AS81 -> 23000 | P80: 0 | Q80: ='Economist OLD'!U81 -> 450 | R80: ='Economist OLD'!V81 -> 450 | S80: ='Economist OLD'!W81 -> 450 | T80: ='Economist OLD'!X81 -> 450 | U80: ='Economist OLD'!Y81 -> 450 | V80: ='Economist OLD'!Z81 -> 0 | W80: ='Economist OLD'!AA81 -> 900 | X80: ='Economist OLD'!AB81 -> 450 | ... AA80: ='Economist OLD'!AE81 -> 450 | AB80: 0 | AC80: ='Economist OLD'!AG81 -> 4500 | AD80: ='Economist OLD'!AH81 -> 4500 | AE80: ='Economist OLD'!AI81 -> 4500 | AF80: ='Economist OLD'!AJ81 -> 4500 | AG80: ='Economist OLD'!AK81 -> 4500 | AH80: ='Economist OLD'!AL81 -> 0 | AI80: ='Economist OLD'!AM81 -> 9000 | AJ80: ='Economist OLD'!AN81 -> 4500 | ... AM80: ='Economist OLD'!AQ81 -> 4500 | AN80: 0 | AO80: 0 | AP80: 0 | AQ80: 0 | AR80: 0 | AS80: 0 | AT80: 0 | AU80: 0 | AV80: 0 | AW80: 0 | AX80: 0 | AY80: 0
D81: ='Economist OLD'!F82 -> Science & Technology (COP) | E81: Takeover | F81: Takeover | I81: ='Economist OLD'!S82+P81 -> 189.81 | J81: ='Economist OLD'!M82 -> 3000 | K81: ='Economist OLD'!Q82 -> 189.81 | L81: ='Economist OLD'!AW82 -> 2.1 | M81: ='Economist OLD'!AV82 -> 0.0007 | N81: 0.75 | O81: ='Economist OLD'!AS82 -> 445000 | P81: 0 | Q81: ='Economist OLD'!U82 -> 0 | R81: ='Economist OLD'!V82 -> 0 | S81: ='Economist OLD'!W82 -> 0 | T81: ='Economist OLD'!X82 -> 0 | U81: ='Economist OLD'!Y82 -> 0 | V81: ='Economist OLD'!Z82 -> 0 | W81: ='Economist OLD'!AA82 -> 189.81 | X81: ='Economist OLD'!AB82 -> 0 | ... AA81: ='Economist OLD'!AE82 -> 0 | AB81: 0 | AC81: ='Economist OLD'!AG82 -> 0 | AD81: ='Economist OLD'!AH82 -> 0 | AE81: ='Economist OLD'!AI82 -> 0 | AF81: ='Economist OLD'!AJ82 -> 0 | AG81: ='Economist OLD'!AK82 -> 0 | AH81: ='Economist OLD'!AL82 -> 0 | AI81: ='Economist OLD'!AM82 -> 3000 | AJ81: ='Economist OLD'!AN82 -> 0 | ... AM81: ='Economist OLD'!AQ82 -> 0 | AN81: 0 | AO81: =L81/11 -> 0.19090909 | AP81: =AO81 -> 0.19090909 | AQ81: =AP81 -> 0.19090909 | AR81: =AQ81 -> 0.19090909 | AS81: =AR81 -> 0.19090909 | AT81: =AS81 -> 0.19090909 | AU81: =L81 -> 2.1 | AV81: 0 | AW81: =AV81 -> 0 | AX81: =AW81 -> 0 | AY81: =AX81 -> 0
D82: ='Economist OLD'!F83 -> Science & Technology (COP) | E82: Takeover | F82: Takeover | I82: ='Economist OLD'!S83+P82 -> 189.81 | J82: ='Economist OLD'!M83 -> 3000 | K82: ='Economist OLD'!Q83 -> 189.81 | L82: ='Economist OLD'!AW83 -> 2.1 | M82: ='Economist OLD'!AV83 -> 0.0007 | N82: 0.75 | O82: ='Economist OLD'!AS83 -> 445000 | P82: 0 | Q82: ='Economist OLD'!U83 -> 0 | R82: ='Economist OLD'!V83 -> 0 | S82: ='Economist OLD'!W83 -> 0 | T82: ='Economist OLD'!X83 -> 0 | U82: ='Economist OLD'!Y83 -> 0 | V82: ='Economist OLD'!Z83 -> 0 | W82: ='Economist OLD'!AA83 -> 189.81 | X82: ='Economist OLD'!AB83 -> 0 | ... AA82: ='Economist OLD'!AE83 -> 0 | AB82: 0 | AC82: ='Economist OLD'!AG83 -> 0 | AD82: ='Economist OLD'!AH83 -> 0 | AE82: ='Economist OLD'!AI83 -> 0 | AF82: ='Economist OLD'!AJ83 -> 0 | AG82: ='Economist OLD'!AK83 -> 0 | AH82: ='Economist OLD'!AL83 -> 0 | AI82: ='Economist OLD'!AM83 -> 3000 | AJ82: ='Economist OLD'!AN83 -> 0 | ... AM82: ='Economist OLD'!AQ83 -> 0 | AN82: 0 | AO82: =L82/11 -> 0.19090909 | AP82: =AO82 -> 0.19090909 | AQ82: =AP82 -> 0.19090909 | AR82: =AQ82 -> 0.19090909 | AS82: =AR82 -> 0.19090909 | AT82: =AS82 -> 0.19090909 | AU82: =L82 -> 2.1 | AV82: 0 | AW82: =AV82 -> 0 | AX82: =AW82 -> 0 | AY82: =AX82 -> 0
D83: ='Economist OLD'!F84 -> Science & Technology (COP) | E83: Takeover | F83: Takeover | I83: ='Economist OLD'!S84+P83 -> 189.81 | J83: ='Economist OLD'!M84 -> 3000 | K83: ='Economist OLD'!Q84 -> 189.81 | L83: ='Economist OLD'!AW84 -> 2.1 | M83: ='Economist OLD'!AV84 -> 0.0007 | N83: 0.75 | O83: ='Economist OLD'!AS84 -> 445000 | P83: 0 | Q83: ='Economist OLD'!U84 -> 0 | R83: ='Economist OLD'!V84 -> 0 | S83: ='Economist OLD'!W84 -> 0 | T83: ='Economist OLD'!X84 -> 0 | U83: ='Economist OLD'!Y84 -> 0 | V83: ='Economist OLD'!Z84 -> 0 | W83: ='Economist OLD'!AA84 -> 0 | X83: ='Economist OLD'!AB84 -> 0 | ... AA83: ='Economist OLD'!AE84 -> 0 | AB83: 0 | AC83: ='Economist OLD'!AG84 -> 0 | AD83: ='Economist OLD'!AH84 -> 0 | AE83: ='Economist OLD'!AI84 -> 0 | AF83: ='Economist OLD'!AJ84 -> 0 | AG83: ='Economist OLD'!AK84 -> 0 | AH83: ='Economist OLD'!AL84 -> 0 | AI83: ='Economist OLD'!AM84 -> 0 | AJ83: ='Economist OLD'!AN84 -> 0 | ... AM83: ='Economist OLD'!AQ84 -> 0 | AN83: 0 | AO83: =L83/11 -> 0.19090909 | AP83: =AO83 -> 0.19090909 | AQ83: =AP83 -> 0.19090909 | AR83: =AQ83 -> 0.19090909 | AS83: =AR83 -> 0.19090909 | AT83: =AS83 -> 0.19090909 | AU83: =AT83 -> 0.19090909 | AV83: =AU83 -> 0.19090909 | AW83: =L83 -> 2.1 | AX83: 0 | AY83: =AX83 -> 0
D84: ='Economist OLD'!F85 -> Business & Finance (Davos) | E84: Takeover | F84: Takeover | I84: ='Economist OLD'!S85+P84 -> 750 | J84: ='Economist OLD'!M85 -> 12000 | K84: ='Economist OLD'!Q85 -> 750 | L84: ='Economist OLD'!AW85 -> 8.4 | M84: ='Economist OLD'!AV85 -> 0.0007 | N84: 0.75 | O84: ='Economist OLD'!AS85 -> 445000 | P84: 0 | Q84: ='Economist OLD'!U85 -> 0 | R84: ='Economist OLD'!V85 -> 0 | S84: ='Economist OLD'!W85 -> 0 | T84: ='Economist OLD'!X85 -> 0 | U84: ='Economist OLD'!Y85 -> 0 | V84: ='Economist OLD'!Z85 -> 0 | W84: ='Economist OLD'!AA85 -> 0 | X84: ='Economist OLD'!AB85 -> 0 | ... AA84: ='Economist OLD'!AE85 -> 750 | AB84: 0 | AC84: ='Economist OLD'!AG85 -> 0 | AD84: ='Economist OLD'!AH85 -> 0 | AE84: ='Economist OLD'!AI85 -> 0 | AF84: ='Economist OLD'!AJ85 -> 0 | AG84: ='Economist OLD'!AK85 -> 0 | AH84: ='Economist OLD'!AL85 -> 0 | AI84: ='Economist OLD'!AM85 -> 0 | AJ84: ='Economist OLD'!AN85 -> 0 | ... AM84: ='Economist OLD'!AQ85 -> 12000 | AN84: 0 | AO84: 0 | AP84: =AO84 -> 0 | AQ84: =AP84 -> 0 | AR84: =AQ84 -> 0 | AS84: =AR84 -> 0 | AT84: =AS84 -> 0 | AU84: =AT84 -> 0 | AV84: =AU84 -> 0 | AW84: =AV84 -> 0 | AX84: =AW84 -> 0 | AY84: =L84 -> 8.4
C85: TOTAL | D85: ='Economist OLD'!F86 | F85: ='Economist OLD'!I86 | I85: =SUM(I70:I84) -> 27500.006 | J85: =SUM(J70:J84) -> 489148.05 | K85: ='Economist OLD'!Q86 | L85: =SUM(L70:L84) -> 627.87552
C86: ='Economist OLD'!B86 -> APAC | D86: ='Economist OLD'!F87 -> C0Level + Custom audience targeting companies 5,000+ | E86: Audience | F86: ResponsiveBillboard | G86: Economist_APAC_Audience_Display_ResponsiveBillboard | H86: Economist_APAC_Audience | I86: ='Economist OLD'!S87+P86 -> 8228.0952 | J86: ='Economist OLD'!M87 -> 165635.22 | K86: ='Economist OLD'!Q87 -> 49.676 | L86: ='Economist OLD'!AW87 -> 115.94465 | M86: ='Economist OLD'!AV87 -> 0.0007 | N86: 0.75 | O86: ='Economist OLD'!AS87 -> 85000 | P86: 0 | Q86: ='Economist OLD'!U87 -> 824.84648 | R86: ='Economist OLD'!V87 -> 824.84648 | S86: ='Economist OLD'!W87 -> 824.84648 | T86: ='Economist OLD'!X87 -> 824.84648 | U86: ='Economist OLD'!Y87 -> 824.84648 | V86: ='Economist OLD'!Z87 -> 824.84648 | W86: ='Economist OLD'!AA87 -> 723.56793 | X86: ='Economist OLD'!AB87 -> 824.84648 | ... AA86: ='Economist OLD'!AE87 -> 563.61073 | AB86: 0 | AC86: ='Economist OLD'!AG87 -> 16604.527 | AD86: ='Economist OLD'!AH87 -> 16604.527 | AE86: ='Economist OLD'!AI87 -> 16604.527 | AF86: ='Economist OLD'!AJ87 -> 16604.527 | AG86: ='Economist OLD'!AK87 -> 16604.527 | AH86: ='Economist OLD'!AL87 -> 16604.527 | AI86: ='Economist OLD'!AM87 -> 14565.745 | AJ86: ='Economist OLD'!AN87 -> 16604.527 | ... AM86: ='Economist OLD'!AQ87 -> 11345.735 | AN86: 0 | AO86: =L86/11 -> 10.540423 | AP86: =AO86 -> 10.540423 | AQ86: =AP86 -> 10.540423 | AR86: =AQ86 -> 10.540423 | AS86: =AR86 -> 10.540423 | AT86: =AS86 -> 10.540423 | AU86: =AT86 -> 10.540423 | AV86: =AU86 -> 10.540423 | AW86: =AV86 -> 10.540423 | ... AY86: =AX86 -> 10.540423
D87: ='Economist OLD'!F88 -> C0Level + Custom audience targeting companies 5,000+ | E87: Audience | F87: ='Economist OLD'!I88 -> 300x600 | G87: Economist_APAC_Audience_Display_300x600 | H87: Economist_APAC_Audience | I87: ='Economist OLD'!S88+P87 -> 8371.73 | J87: ='Economist OLD'!M88 -> 199707.3 | K87: ='Economist OLD'!Q88 -> 41.92 | L87: ='Economist OLD'!AW88 -> 99.85365 | M87: ='Economist OLD'!AV88 -> 0.0005 | N87: 0.75 | O87: ='Economist OLD'!AS88 -> 85000 | P87: 0 | Q87: ='Economist OLD'!U88 -> 839.24551 | R87: ='Economist OLD'!V88 -> 839.24551 | S87: ='Economist OLD'!W88 -> 839.24551 | T87: ='Economist OLD'!X88 -> 839.24551 | U87: ='Economist OLD'!Y88 -> 839.24551 | V87: ='Economist OLD'!Z88 -> 839.24551 | W87: ='Economist OLD'!AA88 -> 736.19899 | X87: ='Economist OLD'!AB88 -> 839.24551 | ... AA87: ='Economist OLD'!AE88 -> 573.44947 | AB87: 0 | AC87: ='Economist OLD'!AG88 -> 20020.17 | AD87: ='Economist OLD'!AH88 -> 20020.17 | AE87: ='Economist OLD'!AI88 -> 20020.17 | AF87: ='Economist OLD'!AJ88 -> 20020.17 | AG87: ='Economist OLD'!AK88 -> 20020.17 | AH87: ='Economist OLD'!AL88 -> 20020.17 | AI87: ='Economist OLD'!AM88 -> 17561.999 | AJ87: ='Economist OLD'!AN88 -> 20020.17 | ... AM87: ='Economist OLD'!AQ88 -> 13679.615 | AN87: 0 | AO87: =L87/11 -> 9.0776045 | AP87: =AO87 -> 9.0776045 | AQ87: =AP87 -> 9.0776045 | AR87: =AQ87 -> 9.0776045 | AS87: =AR87 -> 9.0776045 | AT87: =AS87 -> 9.0776045 | AU87: =AT87 -> 9.0776045 | AV87: =AU87 -> 9.0776045 | AW87: =AV87 -> 9.0776045 | ... AY87: =AX87 -> 9.0776045
D88: ='Economist OLD'!F89 -> C0Level + Custom audience targeting companies 5,000+ | E88: Audience | F88: ='Economist OLD'!I89 -> Interscroller | G88: Economist_APAC_Audience_Display_Interscroller | H88: Economist_APAC_Audience | I88: ='Economist OLD'!S89+P88 -> 8775.7143 | J88: ='Economist OLD'!M89 -> 205344.33 | K88: ='Economist OLD'!Q89 -> 41.92 | L88: ='Economist OLD'!AW89 -> 616.03299 | M88: ='Economist OLD'!AV89 -> 0.003 | N88: 0.75 | O88: ='Economist OLD'!AS89 -> 85000 | P88: 167.68 | Q88: ='Economist OLD'!U89 -> 862.93444 | R88: ='Economist OLD'!V89 -> 862.93444 | S88: ='Economist OLD'!W89 -> 862.93444 | T88: ='Economist OLD'!X89 -> 862.93444 | U88: ='Economist OLD'!Y89 -> 862.93444 | V88: ='Economist OLD'!Z89 -> 862.93444 | W88: ='Economist OLD'!AA89 -> 756.97928 | X88: ='Economist OLD'!AB89 -> 862.93444 | ... AA88: ='Economist OLD'!AE89 -> 589.63591 | AB88: 4000 | AC88: ='Economist OLD'!AG89 -> 20585.268 | AD88: ='Economist OLD'!AH89 -> 20585.268 | AE88: ='Economist OLD'!AI89 -> 20585.268 | AF88: ='Economist OLD'!AJ89 -> 20585.268 | AG88: ='Economist OLD'!AK89 -> 20585.268 | AH88: ='Economist OLD'!AL89 -> 20585.268 | AI88: ='Economist OLD'!AM89 -> 18057.712 | AJ88: ='Economist OLD'!AN89 -> 20585.268 | ... AM88: ='Economist OLD'!AQ89 -> 14065.742 | AN88: 12 | AO88: =L88/11 -> 56.002999 | AP88: =AO88 -> 56.002999 | AQ88: =AP88 -> 56.002999 | AR88: =AQ88 -> 56.002999 | AS88: =AR88 -> 56.002999 | AT88: =AS88 -> 56.002999 | AU88: =AT88 -> 56.002999 | AV88: =AU88 -> 56.002999 | AW88: =AV88 -> 56.002999 | ... AY88: =AX88 -> 56.002999
D89: ='Economist OLD'!F90 -> C0Level + ESG articles and content | E89: Audience+Contextual | F89: ResponsiveBillboard | G89: Economist_APAC_Audience+Contextual_Display_ResponsiveBillboard | H89: Economist_APAC_Audience+Contextual | I89: ='Economist OLD'!S90+P89 -> 4309.5238 | J89: ='Economist OLD'!M90 -> 97170.774 | K89: ='Economist OLD'!Q90 -> 44.35 | L89: ='Economist OLD'!AW90 -> 68.019542 | M89: ='Economist OLD'!AV90 -> 0.0007 | N89: 0.75 | O89: ='Economist OLD'!AS90 -> 1220000 | P89: 0 | Q89: ='Economist OLD'!U90 -> 432.01925 | R89: ='Economist OLD'!V90 -> 432.01925 | S89: ='Economist OLD'!W90 -> 432.01925 | T89: ='Economist OLD'!X90 -> 432.01925 | U89: ='Economist OLD'!Y90 -> 432.01925 | V89: ='Economist OLD'!Z90 -> 432.01925 | W89: ='Economist OLD'!AA90 -> 378.97389 | X89: ='Economist OLD'!AB90 -> 432.01925 | ... AA89: ='Economist OLD'!AE90 -> 295.19515 | AB89: 0 | AC89: ='Economist OLD'!AG90 -> 9741.133 | AD89: ='Economist OLD'!AH90 -> 9741.133 | AE89: ='Economist OLD'!AI90 -> 9741.133 | AF89: ='Economist OLD'!AJ90 -> 9741.133 | AG89: ='Economist OLD'!AK90 -> 9741.133 | AH89: ='Economist OLD'!AL90 -> 9741.133 | AI89: ='Economist OLD'!AM90 -> 8545.0707 | AJ89: ='Economist OLD'!AN90 -> 9741.133 | ... AM89: ='Economist OLD'!AQ90 -> 6656.0351 | AN89: 0 | AO89: =L89/11 -> 6.1835947 | AP89: =AO89 -> 6.1835947 | AQ89: =AP89 -> 6.1835947 | AR89: =AQ89 -> 6.1835947 | AS89: =AR89 -> 6.1835947 | AT89: =AS89 -> 6.1835947 | AU89: =AT89 -> 6.1835947 | AV89: =AU89 -> 6.1835947 | AW89: =AV89 -> 6.1835947 | ... AY89: =AX89 -> 6.1835947
D90: ='Economist OLD'!F91 -> C0Level + ESG articles and content | E90: Audience+Contextual | F90: ='Economist OLD'!I91 -> 300x600 | G90: Economist_APAC_Audience+Contextual_Display_300x600 | H90: Economist_APAC_Audience+Contextual | I90: ='Economist OLD'!S91+P90 -> 1942.8554 | J90: ='Economist OLD'!M91 -> 40630.749 | K90: ='Economist OLD'!Q91 -> 37.9 | L90: ='Economist OLD'!AW91 -> 20.315374 | M90: ='Economist OLD'!AV91 -> 0.0005 | N90: 0.75 | O90: ='Economist OLD'!AS91 -> 1220000 | P90: 402.95 | Q90: ='Economist OLD'!U91 -> 154.37176 | R90: ='Economist OLD'!V91 -> 154.37176 | S90: ='Economist OLD'!W91 -> 154.37176 | T90: ='Economist OLD'!X91 -> 154.37176 | U90: ='Economist OLD'!Y91 -> 154.37176 | V90: ='Economist OLD'!Z91 -> 154.37176 | W90: ='Economist OLD'!AA91 -> 135.41726 | X90: ='Economist OLD'!AB91 -> 154.37176 | ... AA90: ='Economist OLD'!AE91 -> 105.48094 | AB90: 10632 | AC90: ='Economist OLD'!AG91 -> 4073.1334 | AD90: ='Economist OLD'!AH91 -> 4073.1334 | AE90: ='Economist OLD'!AI91 -> 4073.1334 | AF90: ='Economist OLD'!AJ91 -> 4073.1334 | AG90: ='Economist OLD'!AK91 -> 4073.1334 | AH90: ='Economist OLD'!AL91 -> 4073.1334 | AI90: ='Economist OLD'!AM91 -> 3573.0149 | AJ90: ='Economist OLD'!AN91 -> 4073.1334 | ... AM90: ='Economist OLD'!AQ91 -> 2783.1382 | AN90: 5 | AO90: =L90/11 -> 1.8468522 | AP90: =AO90 -> 1.8468522 | AQ90: =AP90 -> 1.8468522 | AR90: =AQ90 -> 1.8468522 | AS90: =AR90 -> 1.8468522 | AT90: =AS90 -> 1.8468522 | AU90: =AT90 -> 1.8468522 | AV90: =AU90 -> 1.8468522 | AW90: =AV90 -> 1.8468522 | ... AY90: =AX90 -> 1.8468522
D91: ='Economist OLD'!F92 -> C0Level + ESG articles and content | E91: Audience+Contextual | F91: ='Economist OLD'!I92 -> Interscroller | G91: Economist_APAC_Audience+Contextual_Display_Interscroller | H91: Economist_APAC_Audience+Contextual | I91: ='Economist OLD'!S92+P91 -> 4309.5217 | J91: ='Economist OLD'!M92 -> 104847.27 | K91: ='Economist OLD'!Q92 -> 37.9 | L91: ='Economist OLD'!AW92 -> 314.54182 | M91: ='Economist OLD'!AV92 -> 0.003 | N91: 0.75 | O91: ='Economist OLD'!AS92 -> 1220000 | P91: 335.81 | Q91: ='Economist OLD'!U92 -> 398.3549 | R91: ='Economist OLD'!V92 -> 398.3549 | S91: ='Economist OLD'!W92 -> 398.3549 | T91: ='Economist OLD'!X92 -> 398.3549 | U91: ='Economist OLD'!Y92 -> 398.3549 | V91: ='Economist OLD'!Z92 -> 398.3549 | W91: ='Economist OLD'!AA92 -> 349.44301 | X91: ='Economist OLD'!AB92 -> 398.3549 | ... AA91: ='Economist OLD'!AE92 -> 272.19259 | AB91: 8860 | AC91: ='Economist OLD'!AG92 -> 10510.683 | AD91: ='Economist OLD'!AH92 -> 10510.683 | AE91: ='Economist OLD'!AI92 -> 10510.683 | AF91: ='Economist OLD'!AJ92 -> 10510.683 | AG91: ='Economist OLD'!AK92 -> 10510.683 | AH91: ='Economist OLD'!AL92 -> 10510.683 | AI91: ='Economist OLD'!AM92 -> 9220.1321 | AJ91: ='Economist OLD'!AN92 -> 10510.683 | ... AM91: ='Economist OLD'!AQ92 -> 7181.8624 | AN91: 27 | AO91: =L91/11 -> 28.594711 | AP91: =AO91 -> 28.594711 | AQ91: =AP91 -> 28.594711 | AR91: =AQ91 -> 28.594711 | AS91: =AR91 -> 28.594711 | AT91: =AS91 -> 28.594711 | AU91: =AT91 -> 28.594711 | AV91: =AU91 -> 28.594711 | AW91: =AV91 -> 28.594711 | ... AY91: =AX91 -> 28.594711
D92: ='Economist OLD'!F93 -> Economist Subscribers | E92: Subscribers | F92: ResponsiveBillboard | G92: Economist_APAC_Subscribers_Display_ResponsiveBillboard | H92: Economist_APAC_Subscribers | I92: ='Economist OLD'!S93+P92 -> 18894.76 | J92: ='Economist OLD'!M93 -> 380359.92 | K92: ='Economist OLD'!Q93 -> 49.676 | L92: ='Economist OLD'!AW93 -> 266.25195 | M92: ='Economist OLD'!AV93 -> 0.0007 | N92: 0.75 | O92: ='Economist OLD'!AS93 -> 89000 | P92: 0 | Q92: ='Economist OLD'!U93 -> 1894.1535 | R92: ='Economist OLD'!V93 -> 1894.1535 | S92: ='Economist OLD'!W93 -> 1894.1535 | T92: ='Economist OLD'!X93 -> 1894.1535 | U92: ='Economist OLD'!Y93 -> 1894.1535 | V92: ='Economist OLD'!Z93 -> 1894.1535 | W92: ='Economist OLD'!AA93 -> 1661.5804 | X92: ='Economist OLD'!AB93 -> 1894.1535 | ... AA92: ='Economist OLD'!AE93 -> 1294.2593 | AB92: 0 | AC92: ='Economist OLD'!AG93 -> 38130.154 | AD92: ='Economist OLD'!AH93 -> 38130.154 | AE92: ='Economist OLD'!AI93 -> 38130.154 | AF92: ='Economist OLD'!AJ93 -> 38130.154 | AG92: ='Economist OLD'!AK93 -> 38130.154 | AH92: ='Economist OLD'!AL93 -> 38130.154 | AI92: ='Economist OLD'!AM93 -> 33448.354 | AJ92: ='Economist OLD'!AN93 -> 38130.154 | ... AM92: ='Economist OLD'!AQ93 -> 26054.017 | AN92: 0 | AO92: =L92/11 -> 24.204722 | AP92: =AO92 -> 24.204722 | AQ92: =AP92 -> 24.204722 | AR92: =AQ92 -> 24.204722 | AS92: =AR92 -> 24.204722 | AT92: =AS92 -> 24.204722 | AU92: =AT92 -> 24.204722 | AV92: =AU92 -> 24.204722 | AW92: =AV92 -> 24.204722 | ... AY92: =AX92 -> 24.204722
D93: ='Economist OLD'!F94 -> Economist Subscribers | E93: Subscribers | F93: ='Economist OLD'!I94 -> 300x600 | G93: Economist_APAC_Subscribers_Display_300x600 | H93: Economist_APAC_Subscribers | I93: ='Economist OLD'!S94+P93 -> 16472.376 | J93: ='Economist OLD'!M94 -> 362684.54 | K93: ='Economist OLD'!Q94 -> 41.92 | L93: ='Economist OLD'!AW94 -> 181.34227 | M93: ='Economist OLD'!AV94 -> 0.0005 | N93: 0.75 | O93: ='Economist OLD'!AS94 -> 89000 | P93: 1268.64 | Q93: ='Economist OLD'!U94 -> 1524.1374 | R93: ='Economist OLD'!V94 -> 1524.1374 | S93: ='Economist OLD'!W94 -> 1524.1374 | T93: ='Economist OLD'!X94 -> 1524.1374 | U93: ='Economist OLD'!Y94 -> 1524.1374 | V93: ='Economist OLD'!Z94 -> 1524.1374 | W93: ='Economist OLD'!AA94 -> 1336.9967 | X93: ='Economist OLD'!AB94 -> 1524.1374 | ... AA93: ='Economist OLD'!AE94 -> 1041.4304 | AB93: 30263 | AC93: ='Economist OLD'!AG94 -> 36358.241 | AD93: ='Economist OLD'!AH94 -> 36358.241 | AE93: ='Economist OLD'!AI94 -> 36358.241 | AF93: ='Economist OLD'!AJ94 -> 36358.241 | AG93: ='Economist OLD'!AK94 -> 36358.241 | AH93: ='Economist OLD'!AL94 -> 36358.241 | AI93: ='Economist OLD'!AM94 -> 31894.004 | AJ93: ='Economist OLD'!AN94 -> 36358.241 | ... AM93: ='Economist OLD'!AQ94 -> 24843.283 | AN93: 15 | AO93: =L93/11 -> 16.485661 | AP93: =AO93 -> 16.485661 | AQ93: =AP93 -> 16.485661 | AR93: =AQ93 -> 16.485661 | AS93: =AR93 -> 16.485661 | AT93: =AS93 -> 16.485661 | AU93: =AT93 -> 16.485661 | AV93: =AU93 -> 16.485661 | AW93: =AV93 -> 16.485661 | ... AY93: =AX93 -> 16.485661
D94: ='Economist OLD'!F95 -> Economist Subscribers | E94: Subscribers | F94: ='Economist OLD'!I95 -> Interscroller | G94: Economist_APAC_Subscribers_Display_Interscroller | H94: Economist_APAC_Subscribers | I94: ='Economist OLD'!S95+P94 -> 18430.001 | J94: ='Economist OLD'!M95 -> 409646.98 | K94: ='Economist OLD'!Q95 -> 41.92 | L94: ='Economist OLD'!AW95 -> 1228.9409 | M94: ='Economist OLD'!AV95 -> 0.003 | N94: 0.75 | O94: ='Economist OLD'!AS95 -> 89000 | P94: 1257.6 | Q94: ='Economist OLD'!U95 -> 1721.4914 | R94: ='Economist OLD'!V95 -> 1721.4914 | S94: ='Economist OLD'!W95 -> 1721.4914 | T94: ='Economist OLD'!X95 -> 1721.4914 | U94: ='Economist OLD'!Y95 -> 1721.4914 | V94: ='Economist OLD'!Z95 -> 1721.4914 | W94: ='Economist OLD'!AA95 -> 1510.1185 | X94: ='Economist OLD'!AB95 -> 1721.4914 | ... AA94: ='Economist OLD'!AE95 -> 1176.2807 | AB94: 30000 | AC94: ='Economist OLD'!AG95 -> 41066.111 | AD94: ='Economist OLD'!AH95 -> 41066.111 | AE94: ='Economist OLD'!AI95 -> 41066.111 | AF94: ='Economist OLD'!AJ95 -> 41066.111 | AG94: ='Economist OLD'!AK95 -> 41066.111 | AH94: ='Economist OLD'!AL95 -> 41066.111 | AI94: ='Economist OLD'!AM95 -> 36023.82 | AJ94: ='Economist OLD'!AN95 -> 41066.111 | ... AM94: ='Economist OLD'!AQ95 -> 28060.131 | AN94: 90 | AO94: =L94/11 -> 111.7219 | AP94: =AO94 -> 111.7219 | AQ94: =AP94 -> 111.7219 | AR94: =AQ94 -> 111.7219 | AS94: =AR94 -> 111.7219 | AT94: =AS94 -> 111.7219 | AU94: =AT94 -> 111.7219 | AV94: =AU94 -> 111.7219 | AW94: =AV94 -> 111.7219 | ... AY94: =AX94 -> 111.7219
D95: ='Economist OLD'!F96 -> Economist Subscribers | E95: Subscribers | F95: ='Economist OLD'!I96 -> 300x250 | G95: Economist_APAC_Subscribers_Display_300x250 | H95: Economist_APAC_Subscribers | I95: ='Economist OLD'!S96+P95 -> 12319.65 | J95: ='Economist OLD'!M96 -> 103666.83 | K95: ='Economist OLD'!Q96 -> 60 | L95: ='Economist OLD'!AW96 -> 72.56678 | M95: ='Economist OLD'!AV96 -> 0.0007 | N95: 0.75 | O95: ='Economist OLD'!AS96 -> 89000 | P95: 6099.64 | Q95: ='Economist OLD'!U96 -> 623.54081 | R95: ='Economist OLD'!V96 -> 623.54081 | S95: ='Economist OLD'!W96 -> 623.54081 | T95: ='Economist OLD'!X96 -> 623.54081 | U95: ='Economist OLD'!Y96 -> 623.54081 | V95: ='Economist OLD'!Z96 -> 623.54081 | W95: ='Economist OLD'!AA96 -> 546.97952 | X95: ='Economist OLD'!AB96 -> 623.54081 | ... AA95: ='Economist OLD'!AE96 -> 426.06024 | AB95: 101661 | AC95: ='Economist OLD'!AG96 -> 10392.347 | AD95: ='Economist OLD'!AH96 -> 10392.347 | AE95: ='Economist OLD'!AI96 -> 10392.347 | AF95: ='Economist OLD'!AJ96 -> 10392.347 | AG95: ='Economist OLD'!AK96 -> 10392.347 | AH95: ='Economist OLD'!AL96 -> 10392.347 | AI95: ='Economist OLD'!AM96 -> 9116.3254 | AJ95: ='Economist OLD'!AN96 -> 10392.347 | ... AM95: ='Economist OLD'!AQ96 -> 7101.004 | AN95: 71 | AO95: =L95/11 -> 6.59698 | AP95: =AO95 -> 6.59698 | AQ95: =AP95 -> 6.59698 | AR95: =AQ95 -> 6.59698 | AS95: =AR95 -> 6.59698 | AT95: =AS95 -> 6.59698 | AU95: =AT95 -> 6.59698 | AV95: =AU95 -> 6.59698 | AW95: =AV95 -> 6.59698 | ... AY95: =AX95 -> 6.59698
D96: ='Economist OLD'!F97 -> Economist Subscribers | E96: Subscribers | F96: ='Economist OLD'!I97 -> App Interscroller | G96: Economist_APAC_Subscribers_Display_appInterscroller | H96: Economist_APAC_Subscribers | I96: ='Economist OLD'!S97+P96 -> 3300 | J96: ='Economist OLD'!M97 -> 33000 | K96: ='Economist OLD'!Q97 -> 100 | L96: ='Economist OLD'!AW97 -> 0 | M96: ='Economist OLD'!AV97 -> 0 | N96: 0.75 | O96: ='Economist OLD'!AS97 -> 89000 | P96: 0 | Q96: ='Economist OLD'!U97 -> 300 | R96: ='Economist OLD'!V97 -> 300 | S96: ='Economist OLD'!W97 -> 300 | T96: ='Economist OLD'!X97 -> 300 | U96: ='Economist OLD'!Y97 -> 300 | V96: ='Economist OLD'!Z97 -> 0 | W96: ='Economist OLD'!AA97 -> 600 | X96: ='Economist OLD'!AB97 -> 300 | ... AA96: ='Economist OLD'!AE97 -> 300 | AB96: 0 | AC96: ='Economist OLD'!AG97 -> 3000 | AD96: ='Economist OLD'!AH97 -> 3000 | AE96: ='Economist OLD'!AI97 -> 3000 | AF96: ='Economist OLD'!AJ97 -> 3000 | AG96: ='Economist OLD'!AK97 -> 3000 | AH96: ='Economist OLD'!AL97 -> 0 | AI96: ='Economist OLD'!AM97 -> 6000 | AJ96: ='Economist OLD'!AN97 -> 3000 | ... AM96: ='Economist OLD'!AQ97 -> 3000 | AN96: 0 | AO96: 0 | AP96: 0 | AQ96: 0 | AR96: 0 | AS96: 0 | AT96: 0 | AU96: 0 | AV96: 0 | AW96: 0 | AX96: 0 | AY96: 0
D97: ='Economist OLD'!F98 -> Science & Technology (Fed Meeting NY) | E97: Takeover | F97: Takeover | I97: ='Economist OLD'!S98+P97 -> 569.42 | J97: ='Economist OLD'!M98 -> 9000 | K97: ='Economist OLD'!Q98 -> 569.42 | L97: ='Economist OLD'!AW98 -> 6.3 | M97: ='Economist OLD'!AV98 -> 0.0007 | N97: 0.75 | O97: ='Economist OLD'!AS98 -> 445000 | P97: 0 | Q97: ='Economist OLD'!U98 -> 0 | R97: ='Economist OLD'!V98 -> 0 | S97: ='Economist OLD'!W98 -> 0 | T97: ='Economist OLD'!X98 -> 0 | U97: ='Economist OLD'!Y98 -> 0 | V97: ='Economist OLD'!Z98 -> 0 | W97: ='Economist OLD'!AA98 -> 569.42 | X97: ='Economist OLD'!AB98 -> 0 | ... AA97: ='Economist OLD'!AE98 -> 0 | AB97: 0 | AC97: ='Economist OLD'!AG98 -> 0 | AD97: ='Economist OLD'!AH98 -> 0 | AE97: ='Economist OLD'!AI98 -> 0 | AF97: ='Economist OLD'!AJ98 -> 0 | AG97: ='Economist OLD'!AK98 -> 0 | AH97: ='Economist OLD'!AL98 -> 0 | AI97: ='Economist OLD'!AM98 -> 9000 | AJ97: ='Economist OLD'!AN98 -> 0 | ... AM97: ='Economist OLD'!AQ98 -> 0 | AN97: 0 | AO97: 0 | AP97: =AO97 -> 0 | AQ97: =AP97 -> 0 | AR97: =AQ97 -> 0 | AS97: =AR97 -> 0 | AT97: =AS97 -> 0 | AU97: =L97 -> 6.3 | AV97: 0 | AW97: =AV97 -> 0 | AX97: =AW97 -> 0 | AY97: =AX97 -> 0
D98: ='Economist OLD'!F99 -> Science & Technology (Climate Week NY) | E98: Takeover | F98: Takeover | I98: ='Economist OLD'!S99+P98 -> 569.42 | J98: ='Economist OLD'!M99 -> 9000 | K98: ='Economist OLD'!Q99 -> 569.42 | L98: ='Economist OLD'!AW99 -> 6.3 | M98: ='Economist OLD'!AV99 -> 0.0007 | N98: 0.75 | O98: ='Economist OLD'!AS99 -> 445000 | P98: 0 | Q98: ='Economist OLD'!U99 -> 0 | R98: ='Economist OLD'!V99 -> 0 | S98: ='Economist OLD'!W99 -> 0 | T98: ='Economist OLD'!X99 -> 0 | U98: ='Economist OLD'!Y99 -> 0 | V98: ='Economist OLD'!Z99 -> 0 | W98: ='Economist OLD'!AA99 -> 569.42 | X98: ='Economist OLD'!AB99 -> 0 | ... AA98: ='Economist OLD'!AE99 -> 0 | AB98: 0 | AC98: ='Economist OLD'!AG99 -> 0 | AD98: ='Economist OLD'!AH99 -> 0 | AE98: ='Economist OLD'!AI99 -> 0 | AF98: ='Economist OLD'!AJ99 -> 0 | AG98: ='Economist OLD'!AK99 -> 0 | AH98: ='Economist OLD'!AL99 -> 0 | AI98: ='Economist OLD'!AM99 -> 9000 | AJ98: ='Economist OLD'!AN99 -> 0 | ... AM98: ='Economist OLD'!AQ99 -> 0 | AN98: 0 | AO98: 0 | AP98: =AO98 -> 0 | AQ98: =AP98 -> 0 | AR98: =AQ98 -> 0 | AS98: =AR98 -> 0 | AT98: =AS98 -> 0 | AU98: =L98 -> 6.3 | AV98: 0 | AW98: =AV98 -> 0 | AX98: =AW98 -> 0 | AY98: =AX98 -> 0
D99: ='Economist OLD'!F100 -> Science & Technology (COP) | E99: Takeover | F99: Takeover | I99: ='Economist OLD'!S100+P99 -> 569.42 | J99: ='Economist OLD'!M100 -> 9000 | K99: ='Economist OLD'!Q100 -> 569.42 | L99: ='Economist OLD'!AW100 -> 6.3 | M99: ='Economist OLD'!AV100 -> 0.0007 | N99: 0.75 | O99: ='Economist OLD'!AS100 -> 445000 | P99: 0 | Q99: ='Economist OLD'!U100 -> 0 | R99: ='Economist OLD'!V100 -> 0 | S99: ='Economist OLD'!W100 -> 0 | T99: ='Economist OLD'!X100 -> 0 | U99: ='Economist OLD'!Y100 -> 0 | V99: ='Economist OLD'!Z100 -> 0 | W99: ='Economist OLD'!AA100 -> 0 | X99: ='Economist OLD'!AB100 -> 0 | ... AA99: ='Economist OLD'!AE100 -> 0 | AB99: 0 | AC99: ='Economist OLD'!AG100 -> 0 | AD99: ='Economist OLD'!AH100 -> 0 | AE99: ='Economist OLD'!AI100 -> 0 | AF99: ='Economist OLD'!AJ100 -> 0 | AG99: ='Economist OLD'!AK100 -> 0 | AH99: ='Economist OLD'!AL100 -> 0 | AI99: ='Economist OLD'!AM100 -> 0 | AJ99: ='Economist OLD'!AN100 -> 0 | ... AM99: ='Economist OLD'!AQ100 -> 0 | AN99: 0 | AO99: 0 | AP99: =AO99 -> 0 | AQ99: =AP99 -> 0 | AR99: =AQ99 -> 0 | AS99: =AR99 -> 0 | AT99: =AS99 -> 0 | AU99: =AT99 -> 0 | AV99: =AU99 -> 0 | AW99: =L99 -> 6.3 | AX99: 0 | AY99: =AX99 -> 0
D100: ='Economist OLD'!F101 -> Business & Finance (Davos) | E100: Takeover | F100: Takeover | I100: ='Economist OLD'!S101+P100 -> 2937.5 | J100: ='Economist OLD'!M101 -> 47000 | K100: ='Economist OLD'!Q101 -> 2937.5 | L100: ='Economist OLD'!AW101 -> 32.9 | M100: ='Economist OLD'!AV101 -> 0.0007 | N100: 0.75 | O100: ='Economist OLD'!AS101 -> 445000 | P100: 0 | Q100: ='Economist OLD'!U101 -> 0 | R100: ='Economist OLD'!V101 -> 0 | S100: ='Economist OLD'!W101 -> 0 | T100: ='Economist OLD'!X101 -> 0 | U100: ='Economist OLD'!Y101 -> 0 | V100: ='Economist OLD'!Z101 -> 0 | W100: ='Economist OLD'!AA101 -> 0 | X100: ='Economist OLD'!AB101 -> 0 | ... AA100: ='Economist OLD'!AE101 -> 2937.5 | AB100: 0 | AC100: ='Economist OLD'!AG101 -> 0 | AD100: ='Economist OLD'!AH101 -> 0 | AE100: ='Economist OLD'!AI101 -> 0 | AF100: ='Economist OLD'!AJ101 -> 0 | AG100: ='Economist OLD'!AK101 -> 0 | AH100: ='Economist OLD'!AL101 -> 0 | AI100: ='Economist OLD'!AM101 -> 0 | AJ100: ='Economist OLD'!AN101 -> 0 | ... AM100: ='Economist OLD'!AQ101 -> 47000 | AN100: 0 | AO100: 0 | AP100: =AO100 -> 0 | AQ100: =AP100 -> 0 | AR100: =AQ100 -> 0 | AS100: =AR100 -> 0 | AT100: =AS100 -> 0 | AU100: =AT100 -> 0 | AV100: =AU100 -> 0 | AW100: =AV100 -> 0 | AX100: =AW100 -> 0 | AY100: =L100 -> 32.9
C101: TOTAL | D101: ='Economist OLD'!F102 | F101: ='Economist OLD'!I102 | I101: =SUM(I86:I100) -> 109999.99 | J101: =SUM(J86:J100) -> 2176693.9 | K101: ='Economist OLD'!Q102 | L101: =SUM(L86:L100) -> 3035.61
C102: Added0Value | D102: ='Economist OLD'!F103 -> Interscroller Creative Build | F102: ='Economist OLD'!I103 -> Interscroller Production builld | G102: na | I102: ='Economist OLD'!S103 -> 30000 | J102: 0 | K102: ='Economist OLD'!Q103 -> 2500 | L102: 0 | M102: 0 | N102: 0 | O102: 0 | P102: 0 | Q102: 0 | R102: =Q102 -> 0 | S102: =R102 -> 0 | T102: =S102 -> 0 | U102: =T102 -> 0 | V102: =U102 -> 0 | W102: =V102 -> 0 | X102: =W102 -> 0 | Y102: =X102 -> 0 | ... AA102: =Z102 -> 0 | AB102: 0 | AC102: 0 | AD102: 0 | AE102: 0 | AF102: 0 | AG102: 0 | AH102: 0 | AI102: 0 | AJ102: 0 | AK102: 0 | AL102: 0 | AM102: 0 | AN102: 0 | AO102: 0 | AP102: 0 | AQ102: 0 | AR102: 0 | AS102: 0 | AT102: 0 | AU102: 0 | AV102: 0 | AW102: 0 | AX102: 0 | AY102: 0
C103: Added0Value | D103: Responsive Billboard | F103: Responsive Billboard Production Build | G103: na | I103: 30000 | J103: 0 | K103: ='Economist OLD'!Q104 -> 2500 | L103: 0 | M103: 0 | N103: 0 | O103: 17930 | P103: 30000 | Q103: 0 | R103: =Q103 -> 0 | S103: =R103 -> 0 | T103: =S103 -> 0 | U103: =T103 -> 0 | V103: =U103 -> 0 | W103: =V103 -> 0 | X103: =W103 -> 0 | Y103: =X103 -> 0 | ... AA103: =Z103 -> 0 | AB103: 0 | AC103: 0 | AD103: 0 | AE103: 0 | AF103: 0 | AG103: 0 | AH103: 0 | AI103: 0 | AJ103: 0 | AK103: 0 | AL103: 0 | AM103: 0 | AN103: 0 | AO103: 0 | AP103: 0 | AQ103: 0 | AR103: 0 | AS103: 0 | AT103: 0 | AU103: 0 | AV103: 0 | AW103: 0 | AX103: 0 | AY103: 0
...

Sheet Master_Plan_2025_Bigquery CB do
P4: SPEND | AB4: IMPRESSONS | AN4: CLICKS
B5: VENDOR | C5: REGION | D5: TARGETING | E5: TARGETING_TYPE | F5: PLACEMENT | G5: PLACEMENT_NAME | I5: SPEND | J5: IMPRESSIONS | K5: CPM | L5: CLICKS | M5: CTR | N5: VIEWABILITY | O5: Monthly_Unique_users | P5: FEBRUARY_spend | Q5: MARCH_spend | R5: APRIL_spend | S5: MAY_spend | T5: JUNE_spend | U5: JULY_spend | V5: AUGUST_spend | W5: SEPTEMBER_spend | X5: OCTOBER_spend | Y5: NOVEMBER_spend | Z5: DECEMBER_spend | AA5: JANUARY_spend | AB5: FEBRUARY_impressions | AC5: MARCH_impressions | AD5: APRIL_impressions | AE5: MAY_impressions | AF5: JUNE_impressions | AG5: JULY_impressions | AH5: AUGUST_impressions | AI5: SEPTEMBER_impressions | AJ5: OCTOBER_impressions | AK5: NOVEMBER_impressions | AL5: DECEMBER_impressions | AM5: JANUARY_impressions | AN5: FEBRUARY_clicks | AO5: MARCH_clicks | AP5: APRIL_clicks | AQ5: MAY_clicks | AR5: JUNE_clicks | AS5: JULY_clicks | AT5: AUGUST_clicks | AU5: SEPTEMBER_clicks | AV5: OCTOBER_clicks | AW5: NOVEMBER_clicks | AX5: DECEMBER_clicks | AY5: JANUARY_clicks
B6: THE ECONOMIST | C6: ='Economist OLD'!B6 -> North America 0 US (US Metro targetting, Canada Country targetting) | D6: ='Master Plan 2025'!D6 -> C0Level + Custom audience targeting companies 5,000+ | E6: ='Master Plan 2025'!E6 -> Audience | F6: ='Master Plan 2025'!F6 -> ResponsiveBillboard | G6: ='Master Plan 2025'!G6 -> Economist_US_Audience_Display_ResponsiveBillboard | I6: ='Master Plan 2025'!I6 -> 5799.38 | J6: ='Master Plan 2025'!J6 -> 116744.1 | K6: ='Master Plan 2025'!K6 -> 49.676 | L6: ='Master Plan 2025'!L6 -> 81.720871 | M6: ='Master Plan 2025'!M6 -> 0.0007 | N6: ='Master Plan 2025'!N6 -> 0.75 | O6: ='Master Plan 2025'!O6 -> 581400 | P6: ='Master Plan 2025'!P6 -> 0 | ... AY6: ='Master Plan 2025'!AY6 -> 7.4291701
D7: ='Master Plan 2025'!D7 -> C0Level + Custom audience targeting companies 5,000+ | E7: ='Master Plan 2025'!E7 -> Audience | F7: ='Master Plan 2025'!F7 -> 300x600 | G7: ='Master Plan 2025'!G7 -> Economist_US_Audience_Display_300x600 | I7: ='Master Plan 2025'!I7 -> 5682.4985 | J7: ='Master Plan 2025'!J7 -> 85263.085 | K7: ='Master Plan 2025'!K7 -> 41.92 | L7: ='Master Plan 2025'!L7 -> 42.631543 | M7: ='Master Plan 2025'!M7 -> 0.0005 | N7: ='Master Plan 2025'!N7 -> 0.75 | O7: ='Master Plan 2025'!O7 -> 581400 | P7: ='Master Plan 2025'!P7 -> 2108.27 | ... AY7: ='Master Plan 2025'!AY7 -> 3.8755948
D8: ='Master Plan 2025'!D8 -> C0Level + Custom audience targeting companies 5,000+ | E8: ='Master Plan 2025'!E8 -> Audience | F8: ='Master Plan 2025'!F8 -> Interscroller | G8: ='Master Plan 2025'!G8 -> Economist_US_Audience_Display_Interscroller | I8: ='Master Plan 2025'!I8 -> 5518.124 | J8: ='Master Plan 2025'!J8 -> 93833.589 | K8: ='Master Plan 2025'!K8 -> 41.92 | L8: ='Master Plan 2025'!L8 -> 281.50077 | M8: ='Master Plan 2025'!M8 -> 0.003 | N8: ='Master Plan 2025'!N8 -> 0.75 | O8: ='Master Plan 2025'!O8 -> 581400 | P8: ='Master Plan 2025'!P8 -> 1584.62 | ... AY8: ='Master Plan 2025'!AY8 -> 25.590979
D9: ='Master Plan 2025'!D9 -> C0Level + ESG articles and content | E9: ='Master Plan 2025'!E9 -> Audience+Contextual | F9: ='Master Plan 2025'!F9 -> ResponsiveBillboard | G9: ='Master Plan 2025'!G9 -> Economist_US_Audience+Contextual_Display_ResponsiveBillboard | I9: ='Master Plan 2025'!I9 -> 3656.25 | J9: ='Master Plan 2025'!J9 -> 82440.812 | K9: ='Master Plan 2025'!K9 -> 44.35 | L9: ='Master Plan 2025'!L9 -> 57.708568 | M9: ='Master Plan 2025'!M9 -> 0.0007 | N9: ='Master Plan 2025'!N9 -> 0.75 | O9: ='Master Plan 2025'!O9 -> 4175000 | P9: ='Master Plan 2025'!P9 -> 0 | ... AY9: ='Master Plan 2025'!AY9 -> 5.2462335
D10: ='Master Plan 2025'!D10 -> C0Level + ESG articles and content | E10: ='Master Plan 2025'!E10 -> Audience+Contextual | F10: ='Master Plan 2025'!F10 -> 300x600 | G10: ='Master Plan 2025'!G10 -> Economist_US_Audience+Contextual_Display_300x600 | I10: ='Master Plan 2025'!I10 -> 2549.999 | J10: ='Master Plan 2025'!J10 -> 47754.062 | K10: ='Master Plan 2025'!K10 -> 37.9 | L10: ='Master Plan 2025'!L10 -> 23.877031 | M10: ='Master Plan 2025'!M10 -> 0.0005 | N10: ='Master Plan 2025'!N10 -> 0.75 | O10: ='Master Plan 2025'!O10 -> 4175000 | P10: ='Master Plan 2025'!P10 -> 740.12 | ... AY10: ='Master Plan 2025'!AY10 -> 2.1706392
D11: ='Master Plan 2025'!D11 -> C0Level + ESG articles and content | E11: ='Master Plan 2025'!E11 -> Audience+Contextual | F11: ='Master Plan 2025'!F11 -> Interscroller | G11: ='Master Plan 2025'!G11 -> Economist_US_Audience+Contextual_Display_Interscroller | I11: ='Master Plan 2025'!I11 -> 3656.2558 | J11: ='Master Plan 2025'!J11 -> 82417.567 | K11: ='Master Plan 2025'!K11 -> 37.9 | L11: ='Master Plan 2025'!L11 -> 247.2527 | M11: ='Master Plan 2025'!M11 -> 0.003 | N11: ='Master Plan 2025'!N11 -> 0.75 | O11: ='Master Plan 2025'!O11 -> 4175000 | P11: ='Master Plan 2025'!P11 -> 532.63 | ... AY11: ='Master Plan 2025'!AY11 -> 22.477518
D12: ='Master Plan 2025'!D12 -> Economist Subscribers | E12: ='Master Plan 2025'!E12 -> Subscribers | F12: ='Master Plan 2025'!F12 -> ResponsiveBillboard | G12: ='Master Plan 2025'!G12 -> Economist_US_Subscribers_Display_ResponsiveBillboard | I12: ='Master Plan 2025'!I12 -> 12799.372 | J12: ='Master Plan 2025'!J12 -> 257657.06 | K12: ='Master Plan 2025'!K12 -> 49.676 | L12: ='Master Plan 2025'!L12 -> 180.35994 | M12: ='Master Plan 2025'!M12 -> 0.0007 | N12: ='Master Plan 2025'!N12 -> 0.75 | O12: ='Master Plan 2025'!O12 -> 456000 | P12: ='Master Plan 2025'!P12 -> 0 | ... AY12: ='Master Plan 2025'!AY12 -> 16.396358
D13: ='Master Plan 2025'!D13 -> Economist Subscribers | E13: ='Master Plan 2025'!E13 -> Subscribers | F13: ='Master Plan 2025'!F13 -> 300x600 | G13: ='Master Plan 2025'!G13 -> Economist_US_Subscribers_Display_300x600 | I13: ='Master Plan 2025'!I13 -> 13222.503 | J13: ='Master Plan 2025'!J13 -> 263773.94 | K13: ='Master Plan 2025'!K13 -> 41.92 | L13: ='Master Plan 2025'!L13 -> 131.88697 | M13: ='Master Plan 2025'!M13 -> 0.0005 | N13: ='Master Plan 2025'!N13 -> 0.75 | O13: ='Master Plan 2025'!O13 -> 456000 | P13: ='Master Plan 2025'!P13 -> 2165.1 | ... AY13: ='Master Plan 2025'!AY13 -> 11.989724
D14: ='Master Plan 2025'!D14 -> Economist Subscribers | E14: ='Master Plan 2025'!E14 -> Subscribers | F14: ='Master Plan 2025'!F14 -> Interscroller | G14: ='Master Plan 2025'!G14 -> Economist_US_Subscribers_Display_Interscroller | I14: ='Master Plan 2025'!I14 -> 12189.38 | J14: ='Master Plan 2025'!J14 -> 236439.64 | K14: ='Master Plan 2025'!K14 -> 41.92 | L14: ='Master Plan 2025'!L14 -> 709.31893 | M14: ='Master Plan 2025'!M14 -> 0.003 | N14: ='Master Plan 2025'!N14 -> 0.75 | O14: ='Master Plan 2025'!O14 -> 456000 | P14: ='Master Plan 2025'!P14 -> 2277.83 | ... AY14: ='Master Plan 2025'!AY14 -> 64.483539
D15: ='Master Plan 2025'!D15 -> Economist Subscribers | E15: ='Master Plan 2025'!E15 -> Subscribers | F15: ='Master Plan 2025'!F15 -> 300x250 | G15: ='Master Plan 2025'!G15 -> Economist_US_Subscribers_Display_300x250 | I15: ='Master Plan 2025'!I15 -> 11169.538 | J15: ='Master Plan 2025'!J15 -> 134448.47 | K15: ='Master Plan 2025'!K15 -> 60 | L15: ='Master Plan 2025'!L15 -> 94.113931 | M15: ='Master Plan 2025'!M15 -> 0.0007 | N15: ='Master Plan 2025'!N15 -> 0.75 | O15: ='Master Plan 2025'!O15 -> 445000 | P15: ='Master Plan 2025'!P15 -> 3102.63 | ... AY15: ='Master Plan 2025'!AY15 -> 8.5558119
D16: ='Master Plan 2025'!D16 -> Economist Subscribers | E16: ='Master Plan 2025'!E16 -> Subscribers | F16: ='Master Plan 2025'!F16 -> App Interscroller | G16: ='Master Plan 2025'!G16 -> Economist_US_Subscribers_Display_appInterscroller | I16: ='Master Plan 2025'!I16 -> 57420 | J16: ='Master Plan 2025'!J16 -> 574200 | K16: ='Master Plan 2025'!K16 -> 100 | L16: ='Master Plan 2025'!L16 -> 0 | M16: ='Master Plan 2025'!M16 -> 0 | N16: ='Master Plan 2025'!N16 -> 0.75 | O16: ='Master Plan 2025'!O16 -> 445000 | P16: ='Master Plan 2025'!P16 -> 0 | ... AY16: ='Master Plan 2025'!AY16 -> 0
D17: ='Master Plan 2025'!D17 -> Science & Technology (COP) | E17: ='Master Plan 2025'!E17 -> Takeover | F17: ='Master Plan 2025'!F17 -> Takeover | G17: ='Master Plan 2025'!G17 | I17: ='Master Plan 2025'!I17 -> 1486.1949 | J17: ='Master Plan 2025'!J17 -> 23490 | K17: ='Master Plan 2025'!K17 -> 1486.1949 | L17: ='Master Plan 2025'!L17 -> 16.443 | M17: ='Master Plan 2025'!M17 -> 0.0007 | N17: ='Master Plan 2025'!N17 -> 0.75 | O17: ='Master Plan 2025'!O17 -> 445000 | P17: ='Master Plan 2025'!P17 -> 0 | ... AY17: ='Master Plan 2025'!AY17 -> 1.4948182
D18: ='Master Plan 2025'!D18 -> Science & Technology (COP) | E18: ='Master Plan 2025'!E18 -> Takeover | F18: ='Master Plan 2025'!F18 -> Takeover | G18: ='Master Plan 2025'!G18 | I18: ='Master Plan 2025'!I18 -> 1486.1949 | J18: ='Master Plan 2025'!J18 -> 23490 | K18: ='Master Plan 2025'!K18 -> 1486.1949 | L18: ='Master Plan 2025'!L18 -> 16.443 | M18: ='Master Plan 2025'!M18 -> 0.0007 | N18: ='Master Plan 2025'!N18 -> 0.75 | O18: ='Master Plan 2025'!O18 -> 445000 | P18: ='Master Plan 2025'!P18 -> 0 | ... AY18: ='Master Plan 2025'!AY18 -> 1.4948182
... D20: ='Master Plan 2025'!D20 -> Business & Finance (Davos) | E20: ='Master Plan 2025'!E20 -> Takeover | F20: ='Master Plan 2025'!F20 -> Takeover | G20: ='Master Plan 2025'!G20 | I20: ='Master Plan 2025'!I20 -> 6253.125 | J20: ='Master Plan 2025'!J20 -> 100050 | K20: ='Master Plan 2025'!K20 -> 6253.125 | L20: ='Master Plan 2025'!L20 -> 70.035 | M20: ='Master Plan 2025'!M20 -> 0.0007 | N20: ='Master Plan 2025'!N20 -> 0.75 | O20: ='Master Plan 2025'!O20 -> 445000 | P20: ='Master Plan 2025'!P20 -> 0 | ... AY20: ='Master Plan 2025'!AY20 -> 6.3668182
D21: ='Master Plan 2025'!D21
C25: TOTAL | I25: =SUM(I6:I18) -> 136635.69 | J25: =SUM(J6:J18) -> 2021952.3 | L25: =SUM(L6:L18) -> 1883.2572
C26: REGION | D26: TARGETING | E26: TARGETING_TYPE | F26: PLACEMENT | G26: PLACEMENT_NAME | I26: SPEND | J26: IMPRESSIONS | K26: CPM | L26: CLICKS | M26: CTR | N26: VIEWABILITY | O26: Monthly_Unique_users | P26: FEBRUARY_spend | Q26: MARCH_spend | R26: APRIL_spend | S26: MAY_spend | T26: JUNE_spend | U26: JULY_spend | V26: AUGUST_spend | W26: SEPTEMBER_spend | X26: OCTOBER_spend | Y26: NOVEMBER_spend | Z26: DECEMBER_spend | AA26: JANUARY_spend | AB26: FEBRUARY_impressions | AC26: MARCH_impressions | AD26: APRIL_impressions | AE26: MAY_impressions | AF26: JUNE_impressions | AG26: JULY_impressions | AH26: AUGUST_impressions | AI26: SEPTEMBER_impressions | AJ26: OCTOBER_impressions | AK26: NOVEMBER_impressions | AL26: DECEMBER_impressions | AM26: JANUARY_impressions | AN26: FEBRUARY_clicks | AO26: MARCH_clicks | AP26: APRIL_clicks | AQ26: MAY_clicks | AR26: JUNE_clicks | AS26: JULY_clicks | AT26: AUGUST_clicks | AU26: SEPTEMBER_clicks | AV26: OCTOBER_clicks | AW26: NOVEMBER_clicks | AX26: DECEMBER_clicks | AY26: JANUARY_clicks
C27: ='Economist OLD'!B22 -> North America 0 CA | D27: ='Master Plan 2025'!D22 -> C0Level + Custom audience targeting companies 5,000+ | E27: ='Master Plan 2025'!E22 -> Audience | F27: ='Master Plan 2025'!F22 -> ResponsiveBillboard | G27: ='Master Plan 2025'!G22 -> Economist_CA_Audience_Display_ResponsiveBillboard | I27: ='Master Plan 2025'!I22 -> 3599.7917 | J27: ='Master Plan 2025'!J22 -> 72465.409 | K27: ='Master Plan 2025'!K22 -> 49.676 | L27: ='Master Plan 2025'!L22 -> 50.725786 | M27: ='Master Plan 2025'!M22 -> 0.0007 | N27: ='Master Plan 2025'!N22 -> 0.75 | O27: ='Master Plan 2025'!O22 -> 64600 | P27: ='Master Plan 2025'!P22 -> 0 | ... AY27: ='Master Plan 2025'!AY22 -> 4.6114351
D28: ='Master Plan 2025'!D23 -> C0Level + Custom audience targeting companies 5,000+ | E28: ='Master Plan 2025'!E23 -> Audience | F28: ='Master Plan 2025'!F23 -> 300x600 | G28: ='Master Plan 2025'!G23 -> Economist_CA_Audience_Display_300x600 | I28: ='Master Plan 2025'!I23 -> 2560.8286 | J28: ='Master Plan 2025'!J23 -> 55336.083 | K28: ='Master Plan 2025'!K23 -> 41.92 | L28: ='Master Plan 2025'!L23 -> 27.668041 | M28: ='Master Plan 2025'!M23 -> 0.0005 | N28: ='Master Plan 2025'!N23 -> 0.75 | O28: ='Master Plan 2025'!O23 -> 64600 | P28: ='Master Plan 2025'!P23 -> 241.14 | ... AY28: ='Master Plan 2025'!AY23 -> 2.5152765
D29: ='Master Plan 2025'!D24 -> C0Level + Custom audience targeting companies 5,000+ | E29: ='Master Plan 2025'!E24 -> Audience | F29: ='Master Plan 2025'!F24 -> Interscroller | G29: ='Master Plan 2025'!G24 -> Economist_CA_Audience_Display_Interscroller | I29: ='Master Plan 2025'!I24 -> 3839.3743 | J29: ='Master Plan 2025'!J24 -> 88303.775 | K29: ='Master Plan 2025'!K24 -> 41.92 | L29: ='Master Plan 2025'!L24 -> 264.91133 | M29: ='Master Plan 2025'!M24 -> 0.003 | N29: ='Master Plan 2025'!N24 -> 0.75 | O29: ='Master Plan 2025'!O24 -> 64600 | P29: ='Master Plan 2025'!P24 -> 137.68 | ... AY29: ='Master Plan 2025'!AY24 -> 24.082848
D30: ='Master Plan 2025'!D25 -> C0Level + ESG articles and content | E30: ='Master Plan 2025'!E25 -> Audience+Contextual | F30: ='Master Plan 2025'!F25 -> ResponsiveBillboard | G30: ='Master Plan 2025'!G25 -> Economist_CA_Audience+Contextual_Display_ResponsiveBillboard | I30: ='Master Plan 2025'!I25 -> 1885.4202 | J30: ='Master Plan 2025'!J25 -> 42512.292 | K30: ='Master Plan 2025'!K25 -> 44.35 | L30: ='Master Plan 2025'!L25 -> 29.758605 | M30: ='Master Plan 2025'!M25 -> 0.0007 | N30: ='Master Plan 2025'!N25 -> 0.75 | O30: ='Master Plan 2025'!O25 -> 402000 | P30: ='Master Plan 2025'!P25 -> 0 | ... AY30: ='Master Plan 2025'!AY25 -> 5.8333333e-05
D31: ='Master Plan 2025'!D26 -> C0Level + ESG articles and content | E31: ='Master Plan 2025'!E26 -> Audience+Contextual | F31: ='Master Plan 2025'!F26 -> 300x600 | G31: ='Master Plan 2025'!G26 -> Economist_CA_Audience+Contextual_Display_300x600 | I31: ='Master Plan 2025'!I26 -> 850.00357 | J31: ='Master Plan 2025'!J26 -> 19523.841 | K31: ='Master Plan 2025'!K26 -> 37.9 | L31: ='Master Plan 2025'!L26 -> 9.7619205 | M31: ='Master Plan 2025'!M26 -> 0.0005 | N31: ='Master Plan 2025'!N26 -> 0.75 | O31: ='Master Plan 2025'!O26 -> 402000 | P31: ='Master Plan 2025'!P26 -> 110.05 | ... AY31: ='Master Plan 2025'!AY26 -> 0.88744732
D32: ='Master Plan 2025'!D27 -> C0Level + ESG articles and content | E32: ='Master Plan 2025'!E27 -> Audience+Contextual | F32: ='Master Plan 2025'!F27 -> Interscroller | G32: ='Master Plan 2025'!G27 -> Economist_CA_Audience+Contextual_Display_Interscroller | I32: ='Master Plan 2025'!I27 -> 1885.4168 | J32: ='Master Plan 2025'!J27 -> 45062.713 | K32: ='Master Plan 2025'!K27 -> 37.9 | L32: ='Master Plan 2025'!L27 -> 135.18814 | M32: ='Master Plan 2025'!M27 -> 0.003 | N32: ='Master Plan 2025'!N27 -> 0.75 | O32: ='Master Plan 2025'!O27 -> 402000 | P32: ='Master Plan 2025'!P27 -> 177.54 | ... AY32: ='Master Plan 2025'!AY27 -> 12.289831
D33: ='Master Plan 2025'!D28 -> Economist Subscribers | E33: ='Master Plan 2025'!E28 -> Subscribers | F33: ='Master Plan 2025'!F28 -> ResponsiveBillboard | G33: ='Master Plan 2025'!G28 -> Economist_CA_Subscribers_Display_ResponsiveBillboard | I33: ='Master Plan 2025'!I28 -> 5976.435 | J33: ='Master Plan 2025'!J28 -> 120308.3 | K33: ='Master Plan 2025'!K28 -> 49.676 | L33: ='Master Plan 2025'!L28 -> 84.215808 | M33: ='Master Plan 2025'!M28 -> 0.0007 | N33: ='Master Plan 2025'!N28 -> 0.75 | O33: ='Master Plan 2025'!O28 -> 48000 | P33: ='Master Plan 2025'!P28 -> 0 | ... AY33: ='Master Plan 2025'!AY28 -> 7.6559825
D34: ='Master Plan 2025'!D29 -> Economist Subscribers | E34: ='Master Plan 2025'!E29 -> Subscribers | F34: ='Master Plan 2025'!F29 -> 300x600 | G34: ='Master Plan 2025'!G29 -> Economist_CA_Subscribers_Display_300x600 | I34: ='Master Plan 2025'!I29 -> 5894.1643 | J34: ='Master Plan 2025'!J29 -> 122593.85 | K34: ='Master Plan 2025'!K29 -> 41.92 | L34: ='Master Plan 2025'!L29 -> 61.296927 | M34: ='Master Plan 2025'!M29 -> 0.0005 | N34: ='Master Plan 2025'!N29 -> 0.75 | O34: ='Master Plan 2025'!O29 -> 48000 | P34: ='Master Plan 2025'!P29 -> 755.03 | ... AY34: ='Master Plan 2025'!AY29 -> 4.1666667e-05
D35: ='Master Plan 2025'!D30 -> Economist Subscribers | E35: ='Master Plan 2025'!E30 -> Subscribers | F35: ='Master Plan 2025'!F30 -> Interscroller | G35: ='Master Plan 2025'!G30 -> Economist_CA_Subscribers_Display_Interscroller | I35: ='Master Plan 2025'!I30 -> 6063.134 | J35: ='Master Plan 2025'!J30 -> 126523.23 | K35: ='Master Plan 2025'!K30 -> 41.92 | L35: ='Master Plan 2025'!L30 -> 379.5697 | M35: ='Master Plan 2025'!M30 -> 0.003 | N35: ='Master Plan 2025'!N30 -> 0.75 | O35: ='Master Plan 2025'!O30 -> 48000 | P35: ='Master Plan 2025'!P30 -> 759.28 | ... AY35: ='Master Plan 2025'!AY30 -> 34.506337
D36: ='Master Plan 2025'!D31 -> Economist Subscribers | E36: ='Master Plan 2025'!E31 -> Subscribers | F36: ='Master Plan 2025'!F31 -> 300x250 | G36: ='Master Plan 2025'!G31 -> Economist_CA_Subscribers_Display_300x250 | I36: ='Master Plan 2025'!I31 -> 5389.8471 | J36: ='Master Plan 2025'!J31 -> 56669.451 | K36: ='Master Plan 2025'!K31 -> 60 | L36: ='Master Plan 2025'!L31 -> 39.668616 | M36: ='Master Plan 2025'!M31 -> 0.0007 | N36: ='Master Plan 2025'!N31 -> 0.75 | O36: ='Master Plan 2025'!O31 -> 77000 | P36: ='Master Plan 2025'!P31 -> 1989.68 | ... AY36: ='Master Plan 2025'!AY31 -> 3.6062378
D37: ='Master Plan 2025'!D32 -> Economist Subscribers | E37: ='Master Plan 2025'!E32 -> Subscribers | F37: ='Master Plan 2025'!F32 -> App Interscroller | G37: ='Master Plan 2025'!G32 -> Economist_CA_Subscribers_Display_appInterscroller | I37: ='Master Plan 2025'!I32 -> 8580 | J37: ='Master Plan 2025'!J32 -> 85800 | K37: ='Master Plan 2025'!K32 -> 100 | L37: ='Master Plan 2025'!L32 -> 0 | M37: ='Master Plan 2025'!M32 -> 0 | N37: ='Master Plan 2025'!N32 -> 0.75 | O37: ='Master Plan 2025'!O32 -> 77000 | P37: ='Master Plan 2025'!P32 -> 0 | ... AY37: ='Master Plan 2025'!AY32 -> 0
D38: ='Master Plan 2025'!D33 -> Science & Technology (COP) | E38: ='Master Plan 2025'!E33 -> Takeover | F38: ='Master Plan 2025'!F33 -> Takeover | G38: ='Master Plan 2025'!G33 | I38: ='Master Plan 2025'!I33 -> 222.0751 | J38: ='Master Plan 2025'!J33 -> 3510 | K38: ='Master Plan 2025'!K33 -> 222.0751 | L38: ='Master Plan 2025'!L33 -> 2.457 | M38: ='Master Plan 2025'!M33 -> 0.0007 | N38: ='Master Plan 2025'!N33 -> 0.75 | O38: ='Master Plan 2025'!O33 -> 445000 | P38: ='Master Plan 2025'!P33 -> 0 | ... AY38: ='Master Plan 2025'!AY33 -> 5.8333333e-05
D39: ='Master Plan 2025'!D34 -> Science & Technology (COP) | E39: ='Master Plan 2025'!E34 -> Takeover | F39: ='Master Plan 2025'!F34 -> Takeover | G39: ='Master Plan 2025'!G34 | I39: ='Master Plan 2025'!I34 -> 222.0751 | J39: ='Master Plan 2025'!J34 -> 3510 | K39: ='Master Plan 2025'!K34 -> 222.0751 | L39: ='Master Plan 2025'!L34 -> 2.457 | M39: ='Master Plan 2025'!M34 -> 0.0007 | N39: ='Master Plan 2025'!N34 -> 0.75 | O39: ='Master Plan 2025'!O34 -> 445000 | P39: ='Master Plan 2025'!P34 -> 0 | ... AY39: ='Master Plan 2025'!AY34 -> 0.22336364
... D41: ='Master Plan 2025'!D36 -> Business & Finance (Davos) | E41: ='Master Plan 2025'!E36 -> Takeover | F41: ='Master Plan 2025'!F36 -> Takeover | G41: ='Master Plan 2025'!G36 | I41: ='Master Plan 2025'!I36 -> 934.375 | J41: ='Master Plan 2025'!J36 -> 14950 | K41: ='Master Plan 2025'!K36 -> 934.375 | L41: ='Master Plan 2025'!L36 -> 10.465 | M41: ='Master Plan 2025'!M36 -> 0.0007 | N41: ='Master Plan 2025'!N36 -> 0.75 | O41: ='Master Plan 2025'!O36 -> 445000 | P41: ='Master Plan 2025'!P36 -> 0 | ... AY41: ='Master Plan 2025'!AY36 -> 10.465
C46: TOTAL | D46: ='Economist OLD'!F38 | I46: =SUM(I27:I45) -> 48125.016 | J46: =SUM(J27:J45) -> 860578.95 | L46: =SUM(L27:L45) -> 1100.6009
D47: TARGETING | E47: TARGETING_TYPE | F47: PLACEMENT | G47: PLACEMENT_NAME | I47: SPEND | J47: IMPRESSIONS | K47: CPM | L47: CLICKS | M47: CTR | N47: VIEWABILITY | O47: Monthly_Unique_users | P47: FEBRUARY_spend | Q47: MARCH_spend | R47: APRIL_spend | S47: MAY_spend | T47: JUNE_spend | U47: JULY_spend | V47: AUGUST_spend | W47: SEPTEMBER_spend | X47: OCTOBER_spend | Y47: NOVEMBER_spend | Z47: DECEMBER_spend | AA47: JANUARY_spend | AB47: FEBRUARY_impressions | AC47: MARCH_impressions | AD47: APRIL_impressions | AE47: MAY_impressions | AF47: JUNE_impressions | AG47: JULY_impressions | AH47: AUGUST_impressions | AI47: SEPTEMBER_impressions | AJ47: OCTOBER_impressions | AK47: NOVEMBER_impressions | AL47: DECEMBER_impressions | AM47: JANUARY_impressions | AN47: FEBRUARY_clicks | AO47: MARCH_clicks | AP47: APRIL_clicks | AQ47: MAY_clicks | AR47: JUNE_clicks | AS47: JULY_clicks | AT47: AUGUST_clicks | AU47: SEPTEMBER_clicks | AV47: OCTOBER_clicks | AW47: NOVEMBER_clicks | AX47: DECEMBER_clicks | AY47: JANUARY_clicks
C48: ='Economist OLD'!B38 -> EMEA 0 Tier 1 | D48: ='Master Plan 2025'!D38 -> C0Level + Custom audience targeting companies 5,000+ | E48: ='Master Plan 2025'!E38 -> Audience | F48: ='Master Plan 2025'!F38 -> ResponsiveBillboard | G48: ='Master Plan 2025'!G38 -> Economist_EMEATier1_Audience_Display_ResponsiveBillboard | I48: ='Master Plan 2025'!I38 -> 11519.336 | J48: ='Master Plan 2025'!J38 -> 231889.36 | K48: ='Master Plan 2025'!K38 -> 49.676 | L48: ='Master Plan 2025'!L38 -> 162.32255 | M48: ='Master Plan 2025'!M38 -> 0.0007 | N48: ='Master Plan 2025'!N38 -> 0.75 | O48: ='Master Plan 2025'!O38 -> 279500 | P48: ='Master Plan 2025'!P38 -> 0 | ... AY48: ='Master Plan 2025'!AY38 -> 14.756595
D49: ='Master Plan 2025'!D39 -> C0Level + Custom audience targeting companies 5,000+ | E49: ='Master Plan 2025'!E39 -> Audience | F49: ='Master Plan 2025'!F39 -> 300x600 | G49: ='Master Plan 2025'!G39 -> Economist_EMEATier1_Audience_Display_300x600 | I49: ='Master Plan 2025'!I39 -> 10194.668 | J49: ='Master Plan 2025'!J39 -> 240693.41 | K49: ='Master Plan 2025'!K39 -> 41.92 | L49: ='Master Plan 2025'!L39 -> 120.34671 | M49: ='Master Plan 2025'!M39 -> 0.0005 | N49: ='Master Plan 2025'!N39 -> 0.75 | O49: ='Master Plan 2025'!O39 -> 279500 | P49: ='Master Plan 2025'!P39 -> 104.8 | ... AY49: ='Master Plan 2025'!AY39 -> 10.94061
D50: ='Master Plan 2025'!D40 -> C0Level + Custom audience targeting companies 5,000+ | E50: ='Master Plan 2025'!E40 -> Audience | F50: ='Master Plan 2025'!F40 -> Interscroller | G50: ='Master Plan 2025'!G40 -> Economist_EMEATier1_Audience_Display_Interscroller | I50: ='Master Plan 2025'!I40 -> 12285.997 | J50: ='Master Plan 2025'!J40 -> 293081.98 | K50: ='Master Plan 2025'!K40 -> 41.92 | L50: ='Master Plan 2025'!L40 -> 879.24593 | M50: ='Master Plan 2025'!M40 -> 0.003 | N50: ='Master Plan 2025'!N40 -> 0.75 | O50: ='Master Plan 2025'!O40 -> 279500 | P50: ='Master Plan 2025'!P40 -> 0 | ... AY50: ='Master Plan 2025'!AY40 -> 79.931448
D51: ='Master Plan 2025'!D41 -> C0Level + ESG articles and content | E51: ='Master Plan 2025'!E41 -> Audience+Contextual | F51: ='Master Plan 2025'!F41 -> ResponsiveBillboard | G51: ='Master Plan 2025'!G41 -> Economist_EMEATier1_Audience+Contextual_Display_ResponsiveBillboard | I51: ='Master Plan 2025'!I41 -> 6033.3325 | J51: ='Master Plan 2025'!J41 -> 136039.06 | K51: ='Master Plan 2025'!K41 -> 44.35 | L51: ='Master Plan 2025'!L41 -> 95.227344 | M51: ='Master Plan 2025'!M41 -> 0.0007 | N51: ='Master Plan 2025'!N41 -> 0.75 | O51: ='Master Plan 2025'!O41 -> 1060000 | P51: ='Master Plan 2025'!P41 -> 0 | ... AY51: ='Master Plan 2025'!AY41 -> 8.6570313
D52: ='Master Plan 2025'!D42 -> C0Level + ESG articles and content | E52: ='Master Plan 2025'!E42 -> Audience+Contextual | F52: ='Master Plan 2025'!F42 -> 300x600 | G52: ='Master Plan 2025'!G42 -> Economist_EMEATier1_Audience+Contextual_Display_300x600 | I52: ='Master Plan 2025'!I42 -> 5383.5662 | J52: ='Master Plan 2025'!J42 -> 142046.6 | K52: ='Master Plan 2025'!K42 -> 37.9 | L52: ='Master Plan 2025'!L42 -> 71.023301 | M52: ='Master Plan 2025'!M42 -> 0.0005 | N52: ='Master Plan 2025'!N42 -> 0.75 | O52: ='Master Plan 2025'!O42 -> 1060000 | P52: ='Master Plan 2025'!P42 -> 0 | ... AY52: ='Master Plan 2025'!AY42 -> 6.4566637
D53: ='Master Plan 2025'!D43 -> C0Level + ESG articles and content | E53: ='Master Plan 2025'!E43 -> Audience+Contextual | F53: ='Master Plan 2025'!F43 -> Interscroller | G53: ='Master Plan 2025'!G43 -> Economist_EMEATier1_Audience+Contextual_Display_Interscroller | I53: ='Master Plan 2025'!I43 -> 6033.3325 | J53: ='Master Plan 2025'!J43 -> 159190.83 | K53: ='Master Plan 2025'!K43 -> 37.9 | L53: ='Master Plan 2025'!L43 -> 477.57249 | M53: ='Master Plan 2025'!M43 -> 0.003 | N53: ='Master Plan 2025'!N43 -> 0.75 | O53: ='Master Plan 2025'!O43 -> 1060000 | P53: ='Master Plan 2025'!P43 -> 0 | ... AY53: ='Master Plan 2025'!AY43 -> 43.415681
D54: ='Master Plan 2025'!D44 -> Economist Subscribers | E54: ='Master Plan 2025'!E44 -> Subscribers | F54: ='Master Plan 2025'!F44 -> ResponsiveBillboard | G54: ='Master Plan 2025'!G44 -> Economist_EMEATier1_Subscribers_Display_ResponsiveBillboard | I54: ='Master Plan 2025'!I44 -> 26452.667 | J54: ='Master Plan 2025'!J44 -> 532503.97 | K54: ='Master Plan 2025'!K44 -> 49.676 | L54: ='Master Plan 2025'!L44 -> 372.75278 | M54: ='Master Plan 2025'!M44 -> 0.0007 | N54: ='Master Plan 2025'!N44 -> 0.75 | O54: ='Master Plan 2025'!O44 -> 155000 | P54: ='Master Plan 2025'!P44 -> 0 | ... AY54: ='Master Plan 2025'!AY44 -> 33.886617
D55: ='Master Plan 2025'!D45 -> Economist Subscribers | E55: ='Master Plan 2025'!E45 -> Subscribers | F55: ='Master Plan 2025'!F45 -> 300x600 | G55: ='Master Plan 2025'!G45 -> Economist_EMEATier1_Subscribers_Display_300x600 | I55: ='Master Plan 2025'!I45 -> 18861.335 | J55: ='Master Plan 2025'!J45 -> 449936.43 | K55: ='Master Plan 2025'!K45 -> 41.92 | L55: ='Master Plan 2025'!L45 -> 224.96821 | M55: ='Master Plan 2025'!M45 -> 0.0005 | N55: ='Master Plan 2025'!N45 -> 0.75 | O55: ='Master Plan 2025'!O45 -> 155000 | P55: ='Master Plan 2025'!P45 -> 0 | ... AY55: ='Master Plan 2025'!AY45 -> 20.451656
D56: ='Master Plan 2025'!D46 -> Economist Subscribers | E56: ='Master Plan 2025'!E46 -> Subscribers | F56: ='Master Plan 2025'!F46 -> Interscroller | G56: ='Master Plan 2025'!G46 -> Economist_EMEATier1_Subscribers_Display_Interscroller | I56: ='Master Plan 2025'!I46 -> 25801.995 | J56: ='Master Plan 2025'!J46 -> 606505.61 | K56: ='Master Plan 2025'!K46 -> 41.92 | L56: ='Master Plan 2025'!L46 -> 1819.5168 | M56: ='Master Plan 2025'!M46 -> 0.003 | N56: ='Master Plan 2025'!N46 -> 0.75 | O56: ='Master Plan 2025'!O46 -> 155000 | P56: ='Master Plan 2025'!P46 -> 377.28 | ... AY56: ='Master Plan 2025'!AY46 -> 165.41062
D57: ='Master Plan 2025'!D47 -> Economist Subscribers | E57: ='Master Plan 2025'!E47 -> Subscribers | F57: ='Master Plan 2025'!F47 -> 300x250 | G57: ='Master Plan 2025'!G47 -> Economist_EMEATier1_Subscribers_Display_300x250 | I57: ='Master Plan 2025'!I47 -> 17247.513 | J57: ='Master Plan 2025'!J47 -> 73072.216 | K57: ='Master Plan 2025'!K47 -> 60 | L57: ='Master Plan 2025'!L47 -> 51.150551 | M57: ='Master Plan 2025'!M47 -> 0.0007 | N57: ='Master Plan 2025'!N47 -> 0.75 | O57: ='Master Plan 2025'!O47 -> 155000 | P57: ='Master Plan 2025'!P47 -> 12863.18 | ... AY57: ='Master Plan 2025'!AY47 -> 4.6500501
D58: ='Master Plan 2025'!D48 -> Economist Subscribers | E58: ='Master Plan 2025'!E48 -> Subscribers | F58: ='Master Plan 2025'!F48 -> App Interscroller | G58: ='Master Plan 2025'!G48 -> Economist_EMEATier1_Subscribers_Display_appInterscroller | I58: ='Master Plan 2025'!I48 -> 10890 | J58: ='Master Plan 2025'!J48 -> 108900 | K58: ='Master Plan 2025'!K48 -> 100 | L58: ='Master Plan 2025'!L48 -> 0 | M58: ='Master Plan 2025'!M48 -> 0 | N58: ='Master Plan 2025'!N48 -> 0.75 | O58: ='Master Plan 2025'!O48 -> 155000 | P58: ='Master Plan 2025'!P48 -> 0 | ... AY58: ='Master Plan 2025'!AY48 -> 0
D59: ='Master Plan 2025'!D49 -> Science & Technology (COP) | E59: ='Master Plan 2025'!E49 -> Takeover | F59: ='Master Plan 2025'!F49 -> Takeover | G59: ='Master Plan 2025'!G49 | I59: ='Master Plan 2025'!I49 -> 411.25 | J59: ='Master Plan 2025'!J49 -> 6500 | K59: ='Master Plan 2025'!K49 -> 411.25 | L59: ='Master Plan 2025'!L49 -> 4.55 | M59: ='Master Plan 2025'!M49 -> 0.0007 | N59: ='Master Plan 2025'!N49 -> 0.75 | O59: ='Master Plan 2025'!O49 -> 445000 | P59: ='Master Plan 2025'!P49 -> 0 | ... AY59: ='Master Plan 2025'!AY49 -> 0
D60: ='Master Plan 2025'!D50 -> Science & Technology (COP) | E60: ='Master Plan 2025'!E50 -> Takeover | F60: ='Master Plan 2025'!F50 -> Takeover | G60: ='Master Plan 2025'!G50 | I60: ='Master Plan 2025'!I50 -> 411.25 | J60: ='Master Plan 2025'!J50 -> 6500 | K60: ='Master Plan 2025'!K50 -> 411.25 | L60: ='Master Plan 2025'!L50 -> 4.55 | M60: ='Master Plan 2025'!M50 -> 0.0007 | N60: ='Master Plan 2025'!N50 -> 0.75 | O60: ='Master Plan 2025'!O50 -> 445000 | P60: ='Master Plan 2025'!P50 -> 0 | ... AY60: ='Master Plan 2025'!AY50 -> 0
... D62: ='Master Plan 2025'!D52 -> Business & Finance (Davos) | E62: ='Master Plan 2025'!E52 -> Takeover | F62: ='Master Plan 2025'!F52 -> Takeover | G62: ='Master Plan 2025'!G52 | I62: ='Master Plan 2025'!I52 -> 2062.5 | J62: ='Master Plan 2025'!J52 -> 33000 | K62: ='Master Plan 2025'!K52 -> 2062.5 | L62: ='Master Plan 2025'!L52 -> 23.1 | M62: ='Master Plan 2025'!M52 -> 0.0007 | N62: ='Master Plan 2025'!N52 -> 0.75 | O62: ='Master Plan 2025'!O52 -> 445000 | P62: ='Master Plan 2025'!P52 -> 0 | ... AY62: ='Master Plan 2025'!AY52 -> 23.1
D66: ='Economist OLD'!F54 | F66: ='Economist OLD'!I54 | I66: =SUM(I48:I65) -> 153999.99 | J66: =SUM(J48:J65) -> 3026359.5 | K66: ='Economist OLD'!Q54 | L66: =SUM(L48:L65) -> 4310.8767 | M66: ='Economist OLD'!AV54 | O66: ='Economist OLD'!AS54
C67: REGION | D67: TARGETING | E67: TARGETING_TYPE | F67: PLACEMENT | G67: PLACEMENT_NAME | I67: SPEND | J67: IMPRESSIONS | K67: CPM | L67: CLICKS | M67: CTR | N67: VIEWABILITY | O67: Monthly_Unique_users | P67: FEBRUARY_spend | Q67: MARCH_spend | R67: APRIL_spend | S67: MAY_spend | T67: JUNE_spend | U67: JULY_spend | V67: AUGUST_spend | W67: SEPTEMBER_spend | X67: OCTOBER_spend | Y67: NOVEMBER_spend | Z67: DECEMBER_spend | AA67: JANUARY_spend | AB67: FEBRUARY_impressions | AC67: MARCH_impressions | AD67: APRIL_impressions | AE67: MAY_impressions | AF67: JUNE_impressions | AG67: JULY_impressions | AH67: AUGUST_impressions | AI67: SEPTEMBER_impressions | AJ67: OCTOBER_impressions | AK67: NOVEMBER_impressions | AL67: DECEMBER_impressions | AM67: JANUARY_impressions | AN67: FEBRUARY_clicks | AO67: MARCH_clicks | AP67: APRIL_clicks | AQ67: MAY_clicks | AR67: JUNE_clicks | AS67: JULY_clicks | AT67: AUGUST_clicks | AU67: SEPTEMBER_clicks | AV67: OCTOBER_clicks | AW67: NOVEMBER_clicks | AX67: DECEMBER_clicks | AY67: JANUARY_clicks
C68: ='Economist OLD'!B54 -> EMEA 0 Tier 2 | D68: ='Master Plan 2025'!D54 -> C0Level + Custom audience targeting companies 5,000+ | E68: ='Master Plan 2025'!E54 -> Audience | F68: ='Master Plan 2025'!F54 -> ResponsiveBillboard | G68: ='Master Plan 2025'!G54 -> Economist_EMEATier2_Audience_Display_ResponsiveBillboard | I68: ='Master Plan 2025'!I54 -> 4936.8571 | J68: ='Master Plan 2025'!J54 -> 99381.133 | K68: ='Master Plan 2025'!K54 -> 49.676 | L68: ='Master Plan 2025'!L54 -> 69.566793 | M68: ='Master Plan 2025'!M54 -> 0.0007 | N68: ='Master Plan 2025'!N54 -> 0.75 | O68: ='Master Plan 2025'!O54 -> 279500 | P68: ='Master Plan 2025'!P54 -> 0 | ... AY68: ='Master Plan 2025'!AY54 -> 6.3242539
D69: ='Master Plan 2025'!D55 -> C0Level + Custom audience targeting companies 5,000+ | E69: ='Master Plan 2025'!E55 -> Audience | F69: ='Master Plan 2025'!F55 -> 300x600 | G69: ='Master Plan 2025'!G55 -> Economist_EMEATier2_Audience_Display_300x600 | I69: ='Master Plan 2025'!I55 -> 3512 | J69: ='Master Plan 2025'!J55 -> 83778.626 | K69: ='Master Plan 2025'!K55 -> 41.92 | L69: ='Master Plan 2025'!L55 -> 41.889313 | M69: ='Master Plan 2025'!M55 -> 0.0005 | N69: ='Master Plan 2025'!N55 -> 0.75 | O69: ='Master Plan 2025'!O55 -> 279500 | P69: ='Master Plan 2025'!P55 -> 0 | ... AY69: ='Master Plan 2025'!AY55 -> 3.8081194
D70: ='Master Plan 2025'!D56 -> C0Level + Custom audience targeting companies 5,000+ | E70: ='Master Plan 2025'!E56 -> Audience | F70: ='Master Plan 2025'!F56 -> Interscroller | G70: ='Master Plan 2025'!G56 -> Economist_EMEATier2_Audience_Display_Interscroller | I70: ='Master Plan 2025'!I56 -> 5265.4286 | J70: ='Master Plan 2025'!J56 -> 125606.6 | K70: ='Master Plan 2025'!K56 -> 41.92 | L70: ='Master Plan 2025'!L56 -> 376.81979 | M70: ='Master Plan 2025'!M56 -> 0.003 | N70: ='Master Plan 2025'!N56 -> 0.75 | O70: ='Master Plan 2025'!O56 -> 279500 | P70: ='Master Plan 2025'!P56 -> 0 | ... AY70: ='Master Plan 2025'!AY56 -> 34.256345
D71: ='Master Plan 2025'!D57 -> C0Level + ESG articles and content | E71: ='Master Plan 2025'!E57 -> Audience+Contextual | F71: ='Master Plan 2025'!F57 -> ResponsiveBillboard | G71: ='Master Plan 2025'!G57 -> Economist_EMEATier2_Audience+Contextual_Display_ResponsiveBillboard | I71: ='Master Plan 2025'!I57 -> 2585.7143 | J71: ='Master Plan 2025'!J57 -> 58302.464 | K71: ='Master Plan 2025'!K57 -> 44.35 | L71: ='Master Plan 2025'!L57 -> 40.811725 | M71: ='Master Plan 2025'!M57 -> 0.0007 | N71: ='Master Plan 2025'!N57 -> 0.75 | O71: ='Master Plan 2025'!O57 -> 1060000 | P71: ='Master Plan 2025'!P57 -> 0 | ... AY71: ='Master Plan 2025'!AY57 -> 3.7101568
D72: ='Master Plan 2025'!D58 -> C0Level + ESG articles and content | E72: ='Master Plan 2025'!E58 -> Audience+Contextual | F72: ='Master Plan 2025'!F58 -> 300x600 | G72: ='Master Plan 2025'!G58 -> Economist_EMEATier2_Audience+Contextual_Display_300x600 | I72: ='Master Plan 2025'!I58 -> 1165.7143 | J72: ='Master Plan 2025'!J58 -> 30757.633 | K72: ='Master Plan 2025'!K58 -> 37.9 | L72: ='Master Plan 2025'!L58 -> 15.378816 | M72: ='Master Plan 2025'!M58 -> 0.0005 | N72: ='Master Plan 2025'!N58 -> 0.75 | O72: ='Master Plan 2025'!O58 -> 1060000 | P72: ='Master Plan 2025'!P58 -> 0 | ... AY72: ='Master Plan 2025'!AY58 -> 1.3980742
D73: ='Master Plan 2025'!D59 -> C0Level + ESG articles and content | E73: ='Master Plan 2025'!E59 -> Audience+Contextual | F73: ='Master Plan 2025'!F59 -> Interscroller | G73: ='Master Plan 2025'!G59 -> Economist_EMEATier2_Audience+Contextual_Display_Interscroller | I73: ='Master Plan 2025'!I59 -> 2585.7143 | J73: ='Master Plan 2025'!J59 -> 66224.651 | K73: ='Master Plan 2025'!K59 -> 37.9 | L73: ='Master Plan 2025'!L59 -> 198.67395 | M73: ='Master Plan 2025'!M59 -> 0.003 | N73: ='Master Plan 2025'!N59 -> 0.75 | O73: ='Master Plan 2025'!O59 -> 1060000 | P73: ='Master Plan 2025'!P59 -> 75.8 | ... AY73: ='Master Plan 2025'!AY59 -> 18.061269
D74: ='Master Plan 2025'!D60 -> Economist Subscribers | E74: ='Master Plan 2025'!E60 -> Subscribers | F74: ='Master Plan 2025'!F60 -> ResponsiveBillboard | G74: ='Master Plan 2025'!G60 -> Economist_EMEATier2_Subscribers_Display_ResponsiveBillboard | I74: ='Master Plan 2025'!I60 -> 8336.8531 | J74: ='Master Plan 2025'!J60 -> 167824.57 | K74: ='Master Plan 2025'!K60 -> 49.676 | L74: ='Master Plan 2025'!L60 -> 117.4772 | M74: ='Master Plan 2025'!M60 -> 0.0007 | N74: ='Master Plan 2025'!N60 -> 0.75 | O74: ='Master Plan 2025'!O60 -> 155000 | P74: ='Master Plan 2025'!P60 -> 0 | ... AY74: ='Master Plan 2025'!AY60 -> 10.679745
D75: ='Master Plan 2025'!D61 -> Economist Subscribers | E75: ='Master Plan 2025'!E61 -> Subscribers | F75: ='Master Plan 2025'!F61 -> 300x600 | G75: ='Master Plan 2025'!G61 -> Economist_EMEATier2_Subscribers_Display_300x600 | I75: ='Master Plan 2025'!I61 -> 7975.67 | J75: ='Master Plan 2025'!J61 -> 187259.3 | K75: ='Master Plan 2025'!K61 -> 41.92 | L75: ='Master Plan 2025'!L61 -> 93.629652 | M75: ='Master Plan 2025'!M61 -> 0.0005 | N75: ='Master Plan 2025'!N61 -> 0.75 | O75: ='Master Plan 2025'!O61 -> 155000 | P75: ='Master Plan 2025'!P61 -> 125.76 | ... AY75: ='Master Plan 2025'!AY61 -> 8.5117865
D76: ='Master Plan 2025'!D62 -> Economist Subscribers | E76: ='Master Plan 2025'!E62 -> Subscribers | F76: ='Master Plan 2025'!F62 -> Interscroller | G76: ='Master Plan 2025'!G62 -> Economist_EMEATier2_Subscribers_Display_Interscroller | I76: ='Master Plan 2025'!I62 -> 8058.0016 | J76: ='Master Plan 2025'!J62 -> 188223.32 | K76: ='Master Plan 2025'!K62 -> 41.92 | L76: ='Master Plan 2025'!L62 -> 564.66996 | M76: ='Master Plan 2025'!M62 -> 0.003 | N76: ='Master Plan 2025'!N62 -> 0.75 | O76: ='Master Plan 2025'!O62 -> 155000 | P76: ='Master Plan 2025'!P62 -> 167.68 | ... AY76: ='Master Plan 2025'!AY62 -> 51.333633
D77: ='Master Plan 2025'!D63 -> Economist Subscribers | E77: ='Master Plan 2025'!E63 -> Subscribers | F77: ='Master Plan 2025'!F63 -> 300x250 | G77: ='Master Plan 2025'!G63 -> Economist_EMEATier2_Subscribers_Display_300x250 | I77: ='Master Plan 2025'!I63 -> 7391.7898 | J77: ='Master Plan 2025'!J63 -> 34027.163 | K77: ='Master Plan 2025'!K63 -> 60 | L77: ='Master Plan 2025'!L63 -> 23.819014 | M77: ='Master Plan 2025'!M63 -> 0.0007 | N77: ='Master Plan 2025'!N63 -> 0.75 | O77: ='Master Plan 2025'!O63 -> 155000 | P77: ='Master Plan 2025'!P63 -> 5350.16 | ... AY77: ='Master Plan 2025'!AY63 -> 2.1653649
D78: ='Master Plan 2025'!D64 -> Economist Subscribers | E78: ='Master Plan 2025'!E64 -> Subscribers | F78: ='Master Plan 2025'!F64 -> App Interscroller | G78: ='Master Plan 2025'!G64 -> Economist_EMEATier2_Subscribers_Display_appInterscroller | I78: ='Master Plan 2025'!I64 -> 10890 | J78: ='Master Plan 2025'!J64 -> 108900 | K78: ='Master Plan 2025'!K64 -> 100 | L78: ='Master Plan 2025'!L64 -> 0 | M78: ='Master Plan 2025'!M64 -> 0 | N78: ='Master Plan 2025'!N64 -> 0.75 | O78: ='Master Plan 2025'!O64 -> 155000 | P78: ='Master Plan 2025'!P64 -> 0 | ... AY78: ='Master Plan 2025'!AY64 -> 0
D79: ='Master Plan 2025'!D65 -> Science & Technology (COP) | E79: ='Master Plan 2025'!E65 -> Takeover | F79: ='Master Plan 2025'!F65 -> Takeover | G79: ='Master Plan 2025'!G65 | I79: ='Master Plan 2025'!I65 -> 411.25 | J79: ='Master Plan 2025'!J65 -> 6500 | K79: ='Master Plan 2025'!K65 -> 411.25 | L79: ='Master Plan 2025'!L65 -> 4.55 | M79: ='Master Plan 2025'!M65 -> 0.0007 | N79: ='Master Plan 2025'!N65 -> 0.75 | O79: ='Master Plan 2025'!O65 -> 445000 | P79: ='Master Plan 2025'!P65 -> 0 | ... AY79: ='Master Plan 2025'!AY65 -> 0
D80: ='Master Plan 2025'!D66 -> Science & Technology (COP) | E80: ='Master Plan 2025'!E66 -> Takeover | F80: ='Master Plan 2025'!F66 -> Takeover | G80: ='Master Plan 2025'!G66 | I80: ='Master Plan 2025'!I66 -> 411.25 | J80: ='Master Plan 2025'!J66 -> 6500 | K80: ='Master Plan 2025'!K66 -> 411.25 | L80: ='Master Plan 2025'!L66 -> 4.55 | M80: ='Master Plan 2025'!M66 -> 0.0007 | N80: ='Master Plan 2025'!N66 -> 0.75 | O80: ='Master Plan 2025'!O66 -> 445000 | P80: ='Master Plan 2025'!P66 -> 0 | ... AY80: ='Master Plan 2025'!AY66 -> 0
... D82: ='Master Plan 2025'!D68 -> Business & Finance (Davos) | E82: ='Master Plan 2025'!E68 -> Takeover | F82: ='Master Plan 2025'!F68 -> Takeover | G82: ='Master Plan 2025'!G68 | I82: ='Master Plan 2025'!I68 -> 2062.5 | J82: ='Master Plan 2025'!J68 -> 33000 | K82: ='Master Plan 2025'!K68 -> 2062.5 | L82: ='Master Plan 2025'!L68 -> 23.1 | M82: ='Master Plan 2025'!M68 -> 0.0007 | N82: ='Master Plan 2025'!N68 -> 0.75 | O82: ='Master Plan 2025'!O68 -> 445000 | P82: ='Master Plan 2025'!P68 -> 0 | ... AY82: ='Master Plan 2025'!AY68 -> 23.1
D89: ='Economist OLD'!F70 | F89: ='Economist OLD'!I70 | I89: =SUM(I68:I88) -> 65999.993 | J89: =SUM(J68:J88) -> 1202785.5 | K89: ='Economist OLD'!Q70 | L89: =SUM(L68:L88) -> 1579.4862 | M89: ='Economist OLD'!AV70 | O89: ='Economist OLD'!AS70
C90: REGION | D90: TARGETING | E90: TARGETING_TYPE | F90: PLACEMENT | G90: PLACEMENT_NAME | I90: SPEND | J90: IMPRESSIONS | K90: CPM | L90: CLICKS | M90: CTR | N90: VIEWABILITY | O90: Monthly_Unique_users | P90: FEBRUARY_spend | Q90: MARCH_spend | R90: APRIL_spend | S90: MAY_spend | T90: JUNE_spend | U90: JULY_spend | V90: AUGUST_spend | W90: SEPTEMBER_spend | X90: OCTOBER_spend | Y90: NOVEMBER_spend | Z90: DECEMBER_spend | AA90: JANUARY_spend | AB90: FEBRUARY_impressions | AC90: MARCH_impressions | AD90: APRIL_impressions | AE90: MAY_impressions | AF90: JUNE_impressions | AG90: JULY_impressions | AH90: AUGUST_impressions | AI90: SEPTEMBER_impressions | AJ90: OCTOBER_impressions | AK90: NOVEMBER_impressions | AL90: DECEMBER_impressions | AM90: JANUARY_impressions | AN90: FEBRUARY_clicks | AO90: MARCH_clicks | AP90: APRIL_clicks | AQ90: MAY_clicks | AR90: JUNE_clicks | AS90: JULY_clicks | AT90: AUGUST_clicks | AU90: SEPTEMBER_clicks | AV90: OCTOBER_clicks | AW90: NOVEMBER_clicks | AX90: DECEMBER_clicks | AY90: JANUARY_clicks
C91: ='Economist OLD'!B70 -> LATAM | D91: ='Master Plan 2025'!D70 -> C0Level + Custom audience targeting companies 5,000+ | E91: ='Master Plan 2025'!E70 -> Audience | F91: ='Master Plan 2025'!F70 -> ResponsiveBillboard | G91: ='Master Plan 2025'!G70 -> Economist_LATAM_Audience_Display_ResponsiveBillboard | I91: ='Master Plan 2025'!I70 -> 2057.0239 | J91: ='Master Plan 2025'!J70 -> 41408.806 | K91: ='Master Plan 2025'!K70 -> 49.676 | L91: ='Master Plan 2025'!L70 -> 28.986164 | M91: ='Master Plan 2025'!M70 -> 0.0007 | N91: ='Master Plan 2025'!N70 -> 0.75 | O91: ='Master Plan 2025'!O70 -> 42000 | P91: ='Master Plan 2025'!P70 -> 0 | ... AY91: ='Master Plan 2025'!AY70 -> 2.6351059
D92: ='Master Plan 2025'!D71 -> C0Level + Custom audience targeting companies 5,000+ | E92: ='Master Plan 2025'!E71 -> Audience | F92: ='Master Plan 2025'!F71 -> 300x600 | G92: ='Master Plan 2025'!G71 -> Economist_LATAM_Audience_Display_300x600 | I92: ='Master Plan 2025'!I71 -> 1463.3373 | J92: ='Master Plan 2025'!J71 -> 32107.761 | K92: ='Master Plan 2025'!K71 -> 41.92 | L92: ='Master Plan 2025'!L71 -> 16.05388 | M92: ='Master Plan 2025'!M71 -> 0.0005 | N92: ='Master Plan 2025'!N71 -> 0.75 | O92: ='Master Plan 2025'!O71 -> 42000 | P92: ='Master Plan 2025'!P71 -> 117.38 | ... AY92: ='Master Plan 2025'!AY71 -> 1.4594437
D93: ='Master Plan 2025'!D72 -> C0Level + Custom audience targeting companies 5,000+ | E93: ='Master Plan 2025'!E72 -> Audience | F93: ='Master Plan 2025'!F72 -> Interscroller | G93: ='Master Plan 2025'!G72 -> Economist_LATAM_Audience_Display_Interscroller | I93: ='Master Plan 2025'!I72 -> 2193.9286 | J93: ='Master Plan 2025'!J72 -> 51336.082 | K93: ='Master Plan 2025'!K72 -> 41.92 | L93: ='Master Plan 2025'!L72 -> 154.00825 | M93: ='Master Plan 2025'!M72 -> 0.003 | N93: ='Master Plan 2025'!N72 -> 0.75 | O93: ='Master Plan 2025'!O72 -> 42000 | P93: ='Master Plan 2025'!P72 -> 41.92 | ... AY93: ='Master Plan 2025'!AY72 -> 14.00075
D94: ='Master Plan 2025'!D73 -> C0Level + ESG articles and content | E94: ='Master Plan 2025'!E73 -> Audience+Contextual | F94: ='Master Plan 2025'!F73 -> ResponsiveBillboard | G94: ='Master Plan 2025'!G73 -> Economist_LATAM_Audience+Contextual_Display_ResponsiveBillboard | I94: ='Master Plan 2025'!I73 -> 1077.381 | J94: ='Master Plan 2025'!J73 -> 24292.693 | K94: ='Master Plan 2025'!K73 -> 44.35 | L94: ='Master Plan 2025'!L73 -> 17.004885 | M94: ='Master Plan 2025'!M73 -> 0.0007 | N94: ='Master Plan 2025'!N73 -> 0.75 | O94: ='Master Plan 2025'!O73 -> 594000 | P94: ='Master Plan 2025'!P73 -> 0 | ... AY94: ='Master Plan 2025'!AY73 -> 1.5458987
D95: ='Master Plan 2025'!D74 -> C0Level + ESG articles and content | E95: ='Master Plan 2025'!E74 -> Audience+Contextual | F95: ='Master Plan 2025'!F74 -> 300x600 | G95: ='Master Plan 2025'!G74 -> Economist_LATAM_Audience+Contextual_Display_300x600 | I95: ='Master Plan 2025'!I74 -> 485.71634 | J95: ='Master Plan 2025'!J74 -> 8970.3521 | K95: ='Master Plan 2025'!K74 -> 37.9 | L95: ='Master Plan 2025'!L74 -> 4.485176 | M95: ='Master Plan 2025'!M74 -> 0.0005 | N95: ='Master Plan 2025'!N74 -> 0.75 | O95: ='Master Plan 2025'!O74 -> 594000 | P95: ='Master Plan 2025'!P74 -> 145.74 | ... AY95: ='Master Plan 2025'!AY74 -> 0.40774328
D96: ='Master Plan 2025'!D75 -> C0Level + ESG articles and content | E96: ='Master Plan 2025'!E75 -> Audience+Contextual | F96: ='Master Plan 2025'!F75 -> Interscroller | G96: ='Master Plan 2025'!G75 -> Economist_LATAM_Audience+Contextual_Display_Interscroller | I96: ='Master Plan 2025'!I75 -> 1077.3779 | J96: ='Master Plan 2025'!J75 -> 25750.077 | K96: ='Master Plan 2025'!K75 -> 37.9 | L96: ='Master Plan 2025'!L75 -> 77.250231 | M96: ='Master Plan 2025'!M75 -> 0.003 | N96: ='Master Plan 2025'!N75 -> 0.75 | O96: ='Master Plan 2025'!O75 -> 594000 | P96: ='Master Plan 2025'!P75 -> 101.45 | ... AY96: ='Master Plan 2025'!AY75 -> 7.0227483
D97: ='Master Plan 2025'!D76 -> Economist Subscribers | E97: ='Master Plan 2025'!E76 -> Subscribers | F97: ='Master Plan 2025'!F76 -> ResponsiveBillboard | G97: ='Master Plan 2025'!G76 -> Economist_LATAM_Subscribers_Display_ResponsiveBillboard | I97: ='Master Plan 2025'!I76 -> 3422.5603 | J97: ='Master Plan 2025'!J76 -> 68897.662 | K97: ='Master Plan 2025'!K76 -> 49.676 | L97: ='Master Plan 2025'!L76 -> 48.228364 | M97: ='Master Plan 2025'!M76 -> 0.0007 | N97: ='Master Plan 2025'!N76 -> 0.75 | O97: ='Master Plan 2025'!O76 -> 23000 | P97: ='Master Plan 2025'!P76 -> 0 | ... AY97: ='Master Plan 2025'!AY76 -> 4.3843967
D98: ='Master Plan 2025'!D77 -> Economist Subscribers | E98: ='Master Plan 2025'!E77 -> Subscribers | F98: ='Master Plan 2025'!F77 -> 300x600 | G98: ='Master Plan 2025'!G77 -> Economist_LATAM_Subscribers_Display_300x600 | I98: ='Master Plan 2025'!I77 -> 3066.9688 | J98: ='Master Plan 2025'!J77 -> 65596.583 | K98: ='Master Plan 2025'!K77 -> 41.92 | L98: ='Master Plan 2025'!L77 -> 32.798291 | M98: ='Master Plan 2025'!M77 -> 0.0005 | N98: ='Master Plan 2025'!N77 -> 0.75 | O98: ='Master Plan 2025'!O77 -> 23000 | P98: ='Master Plan 2025'!P77 -> 317.16 | ... AY98: ='Master Plan 2025'!AY77 -> 2.9816629
D99: ='Master Plan 2025'!D78 -> Economist Subscribers | E99: ='Master Plan 2025'!E78 -> Subscribers | F99: ='Master Plan 2025'!F78 -> Interscroller | G99: ='Master Plan 2025'!G78 -> Economist_LATAM_Subscribers_Display_Interscroller | I99: ='Master Plan 2025'!I78 -> 3306.37 | J99: ='Master Plan 2025'!J78 -> 71373.33 | K99: ='Master Plan 2025'!K78 -> 41.92 | L99: ='Master Plan 2025'!L78 -> 214.11999 | M99: ='Master Plan 2025'!M78 -> 0.003 | N99: ='Master Plan 2025'!N78 -> 0.75 | O99: ='Master Plan 2025'!O78 -> 23000 | P99: ='Master Plan 2025'!P78 -> 314.4 | ... AY99: ='Master Plan 2025'!AY78 -> 19.465454
D100: ='Master Plan 2025'!D79 -> Economist Subscribers | E100: ='Master Plan 2025'!E79 -> Subscribers | F100: ='Master Plan 2025'!F79 -> 300x250 | G100: ='Master Plan 2025'!G79 -> Economist_LATAM_Subscribers_Display_300x250 | I100: ='Master Plan 2025'!I79 -> 3079.9124 | J100: ='Master Plan 2025'!J79 -> 28914.707 | K100: ='Master Plan 2025'!K79 -> 60 | L100: ='Master Plan 2025'!L79 -> 20.240295 | M100: ='Master Plan 2025'!M79 -> 0.0007 | N100: ='Master Plan 2025'!N79 -> 0.75 | O100: ='Master Plan 2025'!O79 -> 23000 | P100: ='Master Plan 2025'!P79 -> 1345.03 | ... AY100: ='Master Plan 2025'!AY79 -> 1.8400268
D101: ='Master Plan 2025'!D80 -> Economist Subscribers | E101: ='Master Plan 2025'!E80 -> Subscribers | F101: ='Master Plan 2025'!F80 -> App Interscroller | G101: ='Master Plan 2025'!G80 -> Economist_LATAM_Subscribers_Display_appInterscroller | I101: ='Master Plan 2025'!I80 -> 4950 | J101: ='Master Plan 2025'!J80 -> 49500 | K101: ='Master Plan 2025'!K80 -> 100 | L101: ='Master Plan 2025'!L80 -> 0 | M101: ='Master Plan 2025'!M80 -> 0 | N101: ='Master Plan 2025'!N80 -> 0.75 | O101: ='Master Plan 2025'!O80 -> 23000 | P101: ='Master Plan 2025'!P80 -> 0 | ... AY101: ='Master Plan 2025'!AY80 -> 0
D102: ='Master Plan 2025'!D81 -> Science & Technology (COP) | E102: ='Master Plan 2025'!E81 -> Takeover | F102: ='Master Plan 2025'!F81 -> Takeover | G102: ='Master Plan 2025'!G81 | I102: ='Master Plan 2025'!I81 -> 189.81 | J102: ='Master Plan 2025'!J81 -> 3000 | K102: ='Master Plan 2025'!K81 -> 189.81 | L102: ='Master Plan 2025'!L81 -> 2.1 | M102: ='Master Plan 2025'!M81 -> 0.0007 | N102: ='Master Plan 2025'!N81 -> 0.75 | O102: ='Master Plan 2025'!O81 -> 445000 | P102: ='Master Plan 2025'!P81 -> 0 | ... AY102: ='Master Plan 2025'!AY81 -> 0
D103: ='Master Plan 2025'!D82 -> Science & Technology (COP) | E103: ='Master Plan 2025'!E82 -> Takeover | F103: ='Master Plan 2025'!F82 -> Takeover | G103: ='Master Plan 2025'!G82 | I103: ='Master Plan 2025'!I82 -> 189.81 | J103: ='Master Plan 2025'!J82 -> 3000 | K103: ='Master Plan 2025'!K82 -> 189.81 | L103: ='Master Plan 2025'!L82 -> 2.1 | M103: ='Master Plan 2025'!M82 -> 0.0007 | N103: ='Master Plan 2025'!N82 -> 0.75 | O103: ='Master Plan 2025'!O82 -> 445000 | P103: ='Master Plan 2025'!P82 -> 0 | ... AY103: ='Master Plan 2025'!AY82 -> 0
... D105: ='Master Plan 2025'!D84 -> Business & Finance (Davos) | E105: ='Master Plan 2025'!E84 -> Takeover | F105: ='Master Plan 2025'!F84 -> Takeover | G105: ='Master Plan 2025'!G84 | I105: ='Master Plan 2025'!I84 -> 750 | J105: ='Master Plan 2025'!J84 -> 12000 | K105: ='Master Plan 2025'!K84 -> 750 | L105: ='Master Plan 2025'!L84 -> 8.4 | M105: ='Master Plan 2025'!M84 -> 0.0007 | N105: ='Master Plan 2025'!N84 -> 0.75 | O105: ='Master Plan 2025'!O84 -> 445000 | P105: ='Master Plan 2025'!P84 -> 0 | ... AY105: ='Master Plan 2025'!AY84 -> 8.4
D112: ='Economist OLD'!F86 | F112: ='Economist OLD'!I86 | I112: =SUM(I91:I109) -> 27500.006 | J112: ='Economist OLD'!M86 | K112: ='Economist OLD'!Q86
C113: REGION | D113: TARGETING | E113: TARGETING_TYPE | F113: PLACEMENT | G113: PLACEMENT_NAME | I113: SPEND | J113: IMPRESSIONS | K113: CPM | L113: CLICKS | M113: CTR | N113: VIEWABILITY | O113: Monthly_Unique_users | P113: FEBRUARY_spend | Q113: MARCH_spend | R113: APRIL_spend | S113: MAY_spend | T113: JUNE_spend | U113: JULY_spend | V113: AUGUST_spend | W113: SEPTEMBER_spend | X113: OCTOBER_spend | Y113: NOVEMBER_spend | Z113: DECEMBER_spend | AA113: JANUARY_spend | AB113: FEBRUARY_impressions | AC113: MARCH_impressions | AD113: APRIL_impressions | AE113: MAY_impressions | AF113: JUNE_impressions | AG113: JULY_impressions | AH113: AUGUST_impressions | AI113: SEPTEMBER_impressions | AJ113: OCTOBER_impressions | AK113: NOVEMBER_impressions | AL113: DECEMBER_impressions | AM113: JANUARY_impressions | AN113: FEBRUARY_clicks | AO113: MARCH_clicks | AP113: APRIL_clicks | AQ113: MAY_clicks | AR113: JUNE_clicks | AS113: JULY_clicks | AT113: AUGUST_clicks | AU113: SEPTEMBER_clicks | AV113: OCTOBER_clicks | AW113: NOVEMBER_clicks | AX113: DECEMBER_clicks | AY113: JANUARY_clicks
C114: ='Economist OLD'!B86 -> APAC | D114: ='Master Plan 2025'!D86 -> C0Level + Custom audience targeting companies 5,000+ | E114: ='Master Plan 2025'!E86 -> Audience | F114: ='Master Plan 2025'!F86 -> ResponsiveBillboard | G114: ='Master Plan 2025'!G86 -> Economist_APAC_Audience_Display_ResponsiveBillboard | I114: ='Master Plan 2025'!I86 -> 8228.0952 | J114: ='Master Plan 2025'!J86 -> 165635.22 | K114: ='Master Plan 2025'!K86 -> 49.676 | L114: ='Master Plan 2025'!L86 -> 115.94465 | M114: ='Master Plan 2025'!M86 -> 0.0007 | N114: ='Master Plan 2025'!N86 -> 0.75 | O114: ='Master Plan 2025'!O86 -> 85000 | P114: ='Master Plan 2025'!P86 -> 0 | ... AY114: ='Master Plan 2025'!AY86 -> 10.540423
D115: ='Master Plan 2025'!D87 -> C0Level + Custom audience targeting companies 5,000+ | E115: ='Master Plan 2025'!E87 -> Audience | F115: ='Master Plan 2025'!F87 -> 300x600 | G115: ='Master Plan 2025'!G87 -> Economist_APAC_Audience_Display_300x600 | I115: ='Master Plan 2025'!I87 -> 8371.73 | J115: ='Master Plan 2025'!J87 -> 199707.3 | K115: ='Master Plan 2025'!K87 -> 41.92 | L115: ='Master Plan 2025'!L87 -> 99.85365 | M115: ='Master Plan 2025'!M87 -> 0.0005 | N115: ='Master Plan 2025'!N87 -> 0.75 | O115: ='Master Plan 2025'!O87 -> 85000 | P115: ='Master Plan 2025'!P87 -> 0 | ... AY115: ='Master Plan 2025'!AY87 -> 9.0776045
D116: ='Master Plan 2025'!D88 -> C0Level + Custom audience targeting companies 5,000+ | E116: ='Master Plan 2025'!E88 -> Audience | F116: ='Master Plan 2025'!F88 -> Interscroller | G116: ='Master Plan 2025'!G88 -> Economist_APAC_Audience_Display_Interscroller | I116: ='Master Plan 2025'!I88 -> 8775.7143 | J116: ='Master Plan 2025'!J88 -> 205344.33 | K116: ='Master Plan 2025'!K88 -> 41.92 | L116: ='Master Plan 2025'!L88 -> 616.03299 | M116: ='Master Plan 2025'!M88 -> 0.003 | N116: ='Master Plan 2025'!N88 -> 0.75 | O116: ='Master Plan 2025'!O88 -> 85000 | P116: ='Master Plan 2025'!P88 -> 167.68 | ... AY116: ='Master Plan 2025'!AY88 -> 56.002999
D117: ='Master Plan 2025'!D89 -> C0Level + ESG articles and content | E117: ='Master Plan 2025'!E89 -> Audience+Contextual | F117: ='Master Plan 2025'!F89 -> ResponsiveBillboard | G117: ='Master Plan 2025'!G89 -> Economist_APAC_Audience+Contextual_Display_ResponsiveBillboard | I117: ='Master Plan 2025'!I89 -> 4309.5238 | J117: ='Master Plan 2025'!J89 -> 97170.774 | K117: ='Master Plan 2025'!K89 -> 44.35 | L117: ='Master Plan 2025'!L89 -> 68.019542 | M117: ='Master Plan 2025'!M89 -> 0.0007 | N117: ='Master Plan 2025'!N89 -> 0.75 | O117: ='Master Plan 2025'!O89 -> 1220000 | P117: ='Master Plan 2025'!P89 -> 0 | ... AY117: ='Master Plan 2025'!AY89 -> 6.1835947
D118: ='Master Plan 2025'!D90 -> C0Level + ESG articles and content | E118: ='Master Plan 2025'!E90 -> Audience+Contextual | F118: ='Master Plan 2025'!F90 -> 300x600 | G118: ='Master Plan 2025'!G90 -> Economist_APAC_Audience+Contextual_Display_300x600 | I118: ='Master Plan 2025'!I90 -> 1942.8554 | J118: ='Master Plan 2025'!J90 -> 40630.749 | K118: ='Master Plan 2025'!K90 -> 37.9 | L118: ='Master Plan 2025'!L90 -> 20.315374 | M118: ='Master Plan 2025'!M90 -> 0.0005 | N118: ='Master Plan 2025'!N90 -> 0.75 | O118: ='Master Plan 2025'!O90 -> 1220000 | P118: ='Master Plan 2025'!P90 -> 402.95 | ... AY118: ='Master Plan 2025'!AY90 -> 1.8468522
D119: ='Master Plan 2025'!D91 -> C0Level + ESG articles and content | E119: ='Master Plan 2025'!E91 -> Audience+Contextual | F119: ='Master Plan 2025'!F91 -> Interscroller | G119: ='Master Plan 2025'!G91 -> Economist_APAC_Audience+Contextual_Display_Interscroller | I119: ='Master Plan 2025'!I91 -> 4309.5217 | J119: ='Master Plan 2025'!J91 -> 104847.27 | K119: ='Master Plan 2025'!K91 -> 37.9 | L119: ='Master Plan 2025'!L91 -> 314.54182 | M119: ='Master Plan 2025'!M91 -> 0.003 | N119: ='Master Plan 2025'!N91 -> 0.75 | O119: ='Master Plan 2025'!O91 -> 1220000 | P119: ='Master Plan 2025'!P91 -> 335.81 | ... AY119: ='Master Plan 2025'!AY91 -> 28.594711
D120: ='Master Plan 2025'!D92 -> Economist Subscribers | E120: ='Master Plan 2025'!E92 -> Subscribers | F120: ='Master Plan 2025'!F92 -> ResponsiveBillboard | G120: ='Master Plan 2025'!G92 -> Economist_APAC_Subscribers_Display_ResponsiveBillboard | I120: ='Master Plan 2025'!I92 -> 18894.76 | J120: ='Master Plan 2025'!J92 -> 380359.92 | K120: ='Master Plan 2025'!K92 -> 49.676 | L120: ='Master Plan 2025'!L92 -> 266.25195 | M120: ='Master Plan 2025'!M92 -> 0.0007 | N120: ='Master Plan 2025'!N92 -> 0.75 | O120: ='Master Plan 2025'!O92 -> 89000 | P120: ='Master Plan 2025'!P92 -> 0 | ... AY120: ='Master Plan 2025'!AY92 -> 24.204722
D121: ='Master Plan 2025'!D93 -> Economist Subscribers | E121: ='Master Plan 2025'!E93 -> Subscribers | F121: ='Master Plan 2025'!F93 -> 300x600 | G121: ='Master Plan 2025'!G93 -> Economist_APAC_Subscribers_Display_300x600 | I121: ='Master Plan 2025'!I93 -> 16472.376 | J121: ='Master Plan 2025'!J93 -> 362684.54 | K121: ='Master Plan 2025'!K93 -> 41.92 | L121: ='Master Plan 2025'!L93 -> 181.34227 | M121: ='Master Plan 2025'!M93 -> 0.0005 | N121: ='Master Plan 2025'!N93 -> 0.75 | O121: ='Master Plan 2025'!O93 -> 89000 | P121: ='Master Plan 2025'!P93 -> 1268.64 | ... AY121: ='Master Plan 2025'!AY93 -> 16.485661
D122: ='Master Plan 2025'!D94 -> Economist Subscribers | E122: ='Master Plan 2025'!E94 -> Subscribers | F122: ='Master Plan 2025'!F94 -> Interscroller | G122: ='Master Plan 2025'!G94 -> Economist_APAC_Subscribers_Display_Interscroller | I122: ='Master Plan 2025'!I94 -> 18430.001 | J122: ='Master Plan 2025'!J94 -> 409646.98 | K122: ='Master Plan 2025'!K94 -> 41.92 | L122: ='Master Plan 2025'!L94 -> 1228.9409 | M122: ='Master Plan 2025'!M94 -> 0.003 | N122: ='Master Plan 2025'!N94 -> 0.75 | O122: ='Master Plan 2025'!O94 -> 89000 | P122: ='Master Plan 2025'!P94 -> 1257.6 | ... AY122: ='Master Plan 2025'!AY94 -> 111.7219
D123: ='Master Plan 2025'!D95 -> Economist Subscribers | E123: ='Master Plan 2025'!E95 -> Subscribers | F123: ='Master Plan 2025'!F95 -> 300x250 | G123: ='Master Plan 2025'!G95 -> Economist_APAC_Subscribers_Display_300x250 | I123: ='Master Plan 2025'!I95 -> 12319.65 | J123: ='Master Plan 2025'!J95 -> 103666.83 | K123: ='Master Plan 2025'!K95 -> 60 | L123: ='Master Plan 2025'!L95 -> 72.56678 | M123: ='Master Plan 2025'!M95 -> 0.0007 | N123: ='Master Plan 2025'!N95 -> 0.75 | O123: ='Master Plan 2025'!O95 -> 89000 | P123: ='Master Plan 2025'!P95 -> 6099.64 | ... AY123: ='Master Plan 2025'!AY95 -> 6.59698
D124: ='Master Plan 2025'!D96 -> Economist Subscribers | E124: ='Master Plan 2025'!E96 -> Subscribers | F124: ='Master Plan 2025'!F96 -> App Interscroller | G124: ='Master Plan 2025'!G96 -> Economist_APAC_Subscribers_Display_appInterscroller | I124: ='Master Plan 2025'!I96 -> 3300 | J124: ='Master Plan 2025'!J96 -> 33000 | K124: ='Master Plan 2025'!K96 -> 100 | L124: ='Master Plan 2025'!L96 -> 0 | M124: ='Master Plan 2025'!M96 -> 0 | N124: ='Master Plan 2025'!N96 -> 0.75 | O124: ='Master Plan 2025'!O96 -> 89000 | P124: ='Master Plan 2025'!P96 -> 0 | ... AY124: ='Master Plan 2025'!AY96 -> 0
D125: ='Master Plan 2025'!D97 -> Science & Technology (Fed Meeting NY) | E125: ='Master Plan 2025'!E97 -> Takeover | F125: ='Master Plan 2025'!F97 -> Takeover | G125: ='Master Plan 2025'!G97 | I125: ='Master Plan 2025'!I97 -> 569.42 | J125: ='Master Plan 2025'!J97 -> 9000 | K125: ='Master Plan 2025'!K97 -> 569.42 | L125: ='Master Plan 2025'!L97 -> 6.3 | M125: ='Master Plan 2025'!M97 -> 0.0007 | N125: ='Master Plan 2025'!N97 -> 0.75 | O125: ='Master Plan 2025'!O97 -> 445000 | P125: ='Master Plan 2025'!P97 -> 0 | ... AY125: ='Master Plan 2025'!AY97 -> 0
D126: ='Master Plan 2025'!D98 -> Science & Technology (Climate Week NY) | E126: ='Master Plan 2025'!E98 -> Takeover | F126: ='Master Plan 2025'!F98 -> Takeover | G126: ='Master Plan 2025'!G98 | I126: ='Master Plan 2025'!I98 -> 569.42 | J126: ='Master Plan 2025'!J98 -> 9000 | K126: ='Master Plan 2025'!K98 -> 569.42 | L126: ='Master Plan 2025'!L98 -> 6.3 | M126: ='Master Plan 2025'!M98 -> 0.0007 | N126: ='Master Plan 2025'!N98 -> 0.75 | O126: ='Master Plan 2025'!O98 -> 445000 | P126: ='Master Plan 2025'!P98 -> 0 | ... AY126: ='Master Plan 2025'!AY98 -> 0
... D128: ='Master Plan 2025'!D100 -> Business & Finance (Davos) | E128: ='Master Plan 2025'!E100 -> Takeover | F128: ='Master Plan 2025'!F100 -> Takeover | G128: ='Master Plan 2025'!G100 | I128: ='Master Plan 2025'!I100 -> 2937.5 | J128: ='Master Plan 2025'!J100 -> 47000 | K128: ='Master Plan 2025'!K100 -> 2937.5 | L128: ='Master Plan 2025'!L100 -> 32.9 | M128: ='Master Plan 2025'!M100 -> 0.0007 | N128: ='Master Plan 2025'!N100 -> 0.75 | O128: ='Master Plan 2025'!O100 -> 445000 | P128: ='Master Plan 2025'!P100 -> 0 | ... AY128: ='Master Plan 2025'!AY100 -> 32.9
B130: VENDOR | C130: REGION | D130: TARGETING | E130: TARGETING_TYPE | F130: PLACEMENT | G130: PLACEMENT_NAME | I130: SPEND | J130: IMPRESSIONS | K130: CPM | L130: CLICKS | M130: CTR | N130: VIEWABILITY | O130: Monthly_Unique_users | P130: FEBRUARY_spend | Q130: MARCH_spend | R130: APRIL_spend | S130: MAY_spend | T130: JUNE_spend | U130: JULY_spend | V130: AUGUST_spend | W130: SEPTEMBER_spend | X130: OCTOBER_spend | Y130: NOVEMBER_spend | Z130: DECEMBER_spend | AA130: JANUARY_spend | AB130: FEBRUARY_impressions | AC130: MARCH_impressions | AD130: APRIL_impressions | AE130: MAY_impressions | AF130: JUNE_impressions | AG130: JULY_impressions | AH130: AUGUST_impressions | AI130: SEPTEMBER_impressions | AJ130: OCTOBER_impressions | AK130: NOVEMBER_impressions | AL130: DECEMBER_impressions | AM130: JANUARY_impressions | AN130: FEBRUARY_clicks | AO130: MARCH_clicks | AP130: APRIL_clicks | AQ130: MAY_clicks | AR130: JUNE_clicks | AS130: JULY_clicks | AT130: AUGUST_clicks | AU130: SEPTEMBER_clicks | AV130: OCTOBER_clicks | AW130: NOVEMBER_clicks | AX130: DECEMBER_clicks | AY130: JANUARY_clicks
C131: ='Master Plan 2025'!C102 -> Added0Value | D131: ='Master Plan 2025'!D102 -> Interscroller Creative Build | E131: ='Master Plan 2025'!E102 | F131: ='Master Plan 2025'!F102 -> Interscroller Production builld | G131: ='Master Plan 2025'!G102 -> na | H131: ='Master Plan 2025'!H102 | I131: ='Master Plan 2025'!I102 -> 30000 | J131: ='Master Plan 2025'!J102 -> 0 | ... AY131: ='Master Plan 2025'!AY102 -> 0
C132: ='Master Plan 2025'!C103 -> Added0Value | D132: ='Master Plan 2025'!D103 -> Responsive Billboard | E132: ='Master Plan 2025'!E103 | F132: ='Master Plan 2025'!F103 -> Responsive Billboard Production Build | G132: ='Master Plan 2025'!G103 -> na | H132: ='Master Plan 2025'!H103 | I132: ='Master Plan 2025'!I103 -> 30000 | J132: ='Master Plan 2025'!J103 -> 0 | ... AY132: ='Master Plan 2025'!AY103 -> 0
...

Sheet Optimisation Log
A1: Optimisation | B1: Priority | C1: Vendor | D1: Approved (Y/N) | E1: Status | F1: Month | G1: Start date | H1: End date | I1: Why suggested | J1: Results | K1: Bain Comments | L1: VCCP Comments
A2: Trial pausing the 970x250 & 300x600 formats for the next 2 weeks accross both regions to try and deliver out in full across Mobile placements and Folio as deemed more engaging | B2: P1 | C2: WSJ | D2: Yes | E2: Completed | F2: March | G2: 45721 | H2: 45735 | I2: Folio's have much stronger CTR 0 more value in impression | L2: Actioned by Sian on call (5th) 0 Call (11th) Sian hadn't activated the optimization so she activated it now.
A3: Moved RAM study from WSJ 0 Production Fee 0 RAM Study for Buyout | Added Value | B3: P2 | C3: WSJ | D3: Yes | E3: Completed | F3: March | G3: 45727 | H3: 45730 | I3: Messaging v. similar to Feb so wants to move to later in the year 0 to another buy out (buyout TBC)
A4: Moving inventory out of the Interscrollers which are running behind due to late launch. | B4: P1 | C4: Economist | E4: Completed | F4: March
A5: Plan updated to break out the standard sizes from the folio, and placement group budget split 50/50 on the IO for April 0 January | B5: P0 | C5: WSJ | E5: Completed | F5: March | G5: 45748
A6: $2,052.88 moved out of the interscroller placements and put into the subscriber targeted responsive billboard and 300x250 placements. | B6: P0 | C6: Economist | D6: Yes | E6: Completed | F6: March | G6: 45740 | H6: 45747 | I6: Interscroller underdelivering
A7: Nativo May-June Campaign to go live | B7: P1 | C7: Nativo | D7: Yes | E7: Completed | F7: May | G7: 45790 | H7: 45838 | I7: This line is to keep track of when the campaign went finally live
A8: - ABM Folio line (US & Canada): Remove $2,360.00 from this line given the underpacing - Subscriber Folio line (US & Canada): Add $2,360.00 to this line. | B8: P0 | C8: WSJ | D8: Yes | E8: Completed | F8: May | G8: 45798 | H8: 45808 | I8: The ABM Folio line is underpacing at 76%
A9: A reallocation of the remaining budget from the 300x600 format to higher-performing formats, such as the responsive billboard and interscroller, would likely lead to improved engagement for the campaign without compromising viewability. | B9: P0 | C9: Economist | D9: Yes | E9: Completed | F9: May | G9: 45839 | H9: 46053 | I9: The CTR for Bain's 300x600 placement in this campaign is 0.02% which is below benchmarks. This trend consists different tactics and creative executions each month | L9: - $59,807.74 moved out of 300x600 format and into other placements. - Placements in orange have had their budget reduced, those in green have been increased. - Due to inventory limitations, June is unchanged from the current plan. - Allocations between regions remain the same and total spend is the same.
A10: To move 20K impressions from Folio to the ABM Standard Sizes line item, Plus 30K impressions to NAM Subscribers Folio as WSJ doesn't have enough impressions. | B10: P0 | C10: WSJ | D10: Yes | E10: Completed | F10: June | G10: 45824 | H10: 45838 | I10: The ABM Folio line is pacing behind at 69%. There are 50K impressions at risk of not delivering.
A11: Reallocate 25K impressions out of the ABM Standard Sizes line into the US Subscriber Standard Sizes line. | B11: P0 | C11: WSJ | D11: Yes | E11: Completed | F11: June | G11: 45834 | H11: 45838 | I11: WSJ was pacing behind at 82% and they don't have enough impressions available to deliver in full.
A12: MW/Barron's have been added to the 2 ABM lines for July onwards as well as Adelaide tracking across all rotational media. | B12: P1 | C12: WSJ | D12: Yes | E12: In progress | F12: July | G12: 45839 | H12: 46053

Sheet Sheet7
